package com.roadtrack.onstar.BO;

import android.app.Activity;
import android.content.Context;
import com.roadtrack.onstar.sockets.SSLSocketFactoryInstance;
import com.roadtrack.onstar.utils.CryptedSoapGenerator;
import com.roadtrack.onstar.utils.Utilities;
import javax.net.ssl.SSLSocketFactory;

public class RequestManager {
  OnPostExecuteListener _onPostExecuteListener;
  
  private Context ctx;
  
  private JsonRequestObject jsonRequestObject = null;
  
  private int responseCode = -1;
  
  private String respuesta = "";
  
  private SimpleRequestObject simpleObject = null;
  
  private SoapRequestObject soapObject = null;
  
  private StringBuilder xml_builder = new StringBuilder();
  
  public RequestManager(Activity paramActivity, SimpleRequestObject paramSimpleRequestObject) {
    this.simpleObject = paramSimpleRequestObject;
    this.ctx = paramActivity.getApplicationContext();
  }
  
  public RequestManager(Activity paramActivity, SoapRequestObject paramSoapRequestObject) {
    this.soapObject = paramSoapRequestObject;
    this.ctx = paramActivity.getApplicationContext();
  }
  
  public RequestManager(Context paramContext, JsonRequestObject paramJsonRequestObject) {
    this.jsonRequestObject = paramJsonRequestObject;
    this.ctx = paramContext;
  }
  
  public RequestManager(Context paramContext, SimpleRequestObject paramSimpleRequestObject) {
    this.simpleObject = paramSimpleRequestObject;
    this.ctx = paramContext;
  }
  
  public RequestManager(Context paramContext, SoapRequestObject paramSoapRequestObject) {
    this.ctx = paramContext;
    this.soapObject = paramSoapRequestObject;
  }
  
  private String GetResponseFromXML(String paramString) {
    if (paramString.length() <= 0)
      return ""; 
    try {
      StringBuilder stringBuilder = new StringBuilder();
      this();
      stringBuilder.append("<");
      stringBuilder.append(this.soapObject.get_response_tag());
      stringBuilder.append(">");
      int i = paramString.indexOf(stringBuilder.toString());
      stringBuilder = new StringBuilder();
      this();
      stringBuilder.append("</");
      stringBuilder.append(this.soapObject.get_response_tag());
      stringBuilder.append(">");
      null = paramString.substring(i, paramString.indexOf(stringBuilder.toString()));
      null = null.substring(null.indexOf(">") + 1, null.length());
      return CryptedSoapGenerator.getInstance().getDecryptedResult(null);
    } catch (Exception exception) {
      Utilities.escribeArchivo("Request Manager", "Error: getTokenFromXML", exception.getMessage());
      return paramString;
    } 
  }
  
  private SSLSocketFactory getSocketFactory(int paramInt, String paramString) {
    SSLSocketFactoryInstance sSLSocketFactoryInstance;
    if (paramInt != -1) {
      sSLSocketFactoryInstance = new SSLSocketFactoryInstance(this.ctx, paramInt, paramString);
    } else {
      sSLSocketFactoryInstance = new SSLSocketFactoryInstance(this.ctx);
    } 
    return sSLSocketFactoryInstance.getSSLFactory();
  }
  
  public int getResponseCode() {
    return this.responseCode;
  }
  
  public String getRespuesta() {
    return this.respuesta;
  }
  
  public void sendRequest(int paramInt) throws Exception {
    // Byte code:
    //   0: aconst_null
    //   1: astore #8
    //   3: aconst_null
    //   4: astore #11
    //   6: aconst_null
    //   7: astore #12
    //   9: new java/util/LinkedHashMap
    //   12: invokespecial <init> : ()V
    //   15: aload_0
    //   16: getfield ctx : Landroid/content/Context;
    //   19: astore #5
    //   21: iconst_0
    //   22: istore_3
    //   23: aload #5
    //   25: iconst_0
    //   26: invokestatic validateNetwork : (Landroid/content/Context;Z)Z
    //   29: istore #4
    //   31: iload #4
    //   33: ifne -> 122
    //   36: aload_0
    //   37: ldc 'Network error'
    //   39: putfield respuesta : Ljava/lang/String;
    //   42: aload_0
    //   43: iconst_m1
    //   44: putfield responseCode : I
    //   47: new java/lang/StringBuilder
    //   50: astore #5
    //   52: aload #5
    //   54: invokespecial <init> : ()V
    //   57: aload #5
    //   59: aload_0
    //   60: getfield respuesta : Ljava/lang/String;
    //   63: invokevirtual append : (Ljava/lang/String;)Ljava/lang/StringBuilder;
    //   66: pop
    //   67: aload #5
    //   69: ldc ' code:'
    //   71: invokevirtual append : (Ljava/lang/String;)Ljava/lang/StringBuilder;
    //   74: pop
    //   75: aload #5
    //   77: aload_0
    //   78: getfield responseCode : I
    //   81: invokevirtual append : (I)Ljava/lang/StringBuilder;
    //   84: pop
    //   85: ldc 'Request Manager'
    //   87: ldc 'ERROR Error : '
    //   89: aload #5
    //   91: invokevirtual toString : ()Ljava/lang/String;
    //   94: invokestatic escribeArchivo : (Ljava/lang/String;Ljava/lang/String;Ljava/lang/String;)V
    //   97: aload_0
    //   98: getfield _onPostExecuteListener : Lcom/roadtrack/onstar/BO/RequestManager$OnPostExecuteListener;
    //   101: ifnull -> 121
    //   104: aload_0
    //   105: getfield _onPostExecuteListener : Lcom/roadtrack/onstar/BO/RequestManager$OnPostExecuteListener;
    //   108: aload_0
    //   109: getfield respuesta : Ljava/lang/String;
    //   112: aload_0
    //   113: getfield responseCode : I
    //   116: invokeinterface onPostExecuteListener : (Ljava/lang/String;I)V
    //   121: return
    //   122: ldc ''
    //   124: astore #10
    //   126: iload_1
    //   127: tableswitch default -> 168, 1 -> 1156, 2 -> 922, 3 -> 805, 4 -> 662, 5 -> 428, 6 -> 314, 7 -> 171
    //   168: goto -> 2870
    //   171: aload_0
    //   172: getfield simpleObject : Lcom/roadtrack/onstar/BO/SimpleRequestObject;
    //   175: ifnonnull -> 264
    //   178: aload_0
    //   179: ldc 'Error, SoapRequestObject is null'
    //   181: putfield respuesta : Ljava/lang/String;
    //   184: aload_0
    //   185: iconst_m1
    //   186: putfield responseCode : I
    //   189: new java/lang/StringBuilder
    //   192: astore #5
    //   194: aload #5
    //   196: invokespecial <init> : ()V
    //   199: aload #5
    //   201: aload_0
    //   202: getfield respuesta : Ljava/lang/String;
    //   205: invokevirtual append : (Ljava/lang/String;)Ljava/lang/StringBuilder;
    //   208: pop
    //   209: aload #5
    //   211: ldc ' code:'
    //   213: invokevirtual append : (Ljava/lang/String;)Ljava/lang/StringBuilder;
    //   216: pop
    //   217: aload #5
    //   219: aload_0
    //   220: getfield responseCode : I
    //   223: invokevirtual append : (I)Ljava/lang/StringBuilder;
    //   226: pop
    //   227: ldc 'Request Manager'
    //   229: ldc 'Error : '
    //   231: aload #5
    //   233: invokevirtual toString : ()Ljava/lang/String;
    //   236: invokestatic escribeArchivo : (Ljava/lang/String;Ljava/lang/String;Ljava/lang/String;)V
    //   239: aload_0
    //   240: getfield _onPostExecuteListener : Lcom/roadtrack/onstar/BO/RequestManager$OnPostExecuteListener;
    //   243: ifnull -> 263
    //   246: aload_0
    //   247: getfield _onPostExecuteListener : Lcom/roadtrack/onstar/BO/RequestManager$OnPostExecuteListener;
    //   250: aload_0
    //   251: getfield respuesta : Ljava/lang/String;
    //   254: aload_0
    //   255: getfield responseCode : I
    //   258: invokeinterface onPostExecuteListener : (Ljava/lang/String;I)V
    //   263: return
    //   264: aload_0
    //   265: getfield simpleObject : Lcom/roadtrack/onstar/BO/SimpleRequestObject;
    //   268: invokevirtual buildSimpleRequest2 : ()Ljava/lang/String;
    //   271: astore #10
    //   273: aload_0
    //   274: getfield simpleObject : Lcom/roadtrack/onstar/BO/SimpleRequestObject;
    //   277: invokevirtual get_url : ()Ljava/lang/String;
    //   280: astore #6
    //   282: aload_0
    //   283: aload_0
    //   284: getfield simpleObject : Lcom/roadtrack/onstar/BO/SimpleRequestObject;
    //   287: invokevirtual get_keyStoreId : ()I
    //   290: aload_0
    //   291: getfield simpleObject : Lcom/roadtrack/onstar/BO/SimpleRequestObject;
    //   294: invokevirtual get_nameKeyStore : ()Ljava/lang/String;
    //   297: invokespecial getSocketFactory : (ILjava/lang/String;)Ljavax/net/ssl/SSLSocketFactory;
    //   300: astore #5
    //   302: aload_0
    //   303: getfield simpleObject : Lcom/roadtrack/onstar/BO/SimpleRequestObject;
    //   306: invokevirtual getRequest_propertys : ()Ljava/util/LinkedHashMap;
    //   309: astore #7
    //   311: goto -> 1387
    //   314: aload_0
    //   315: getfield simpleObject : Lcom/roadtrack/onstar/BO/SimpleRequestObject;
    //   318: ifnonnull -> 407
    //   321: aload_0
    //   322: ldc 'Error, SoapRequestObject is null'
    //   324: putfield respuesta : Ljava/lang/String;
    //   327: aload_0
    //   328: iconst_m1
    //   329: putfield responseCode : I
    //   332: new java/lang/StringBuilder
    //   335: astore #5
    //   337: aload #5
    //   339: invokespecial <init> : ()V
    //   342: aload #5
    //   344: aload_0
    //   345: getfield respuesta : Ljava/lang/String;
    //   348: invokevirtual append : (Ljava/lang/String;)Ljava/lang/StringBuilder;
    //   351: pop
    //   352: aload #5
    //   354: ldc ' code:'
    //   356: invokevirtual append : (Ljava/lang/String;)Ljava/lang/StringBuilder;
    //   359: pop
    //   360: aload #5
    //   362: aload_0
    //   363: getfield responseCode : I
    //   366: invokevirtual append : (I)Ljava/lang/StringBuilder;
    //   369: pop
    //   370: ldc 'Request Manager'
    //   372: ldc 'Error : '
    //   374: aload #5
    //   376: invokevirtual toString : ()Ljava/lang/String;
    //   379: invokestatic escribeArchivo : (Ljava/lang/String;Ljava/lang/String;Ljava/lang/String;)V
    //   382: aload_0
    //   383: getfield _onPostExecuteListener : Lcom/roadtrack/onstar/BO/RequestManager$OnPostExecuteListener;
    //   386: ifnull -> 406
    //   389: aload_0
    //   390: getfield _onPostExecuteListener : Lcom/roadtrack/onstar/BO/RequestManager$OnPostExecuteListener;
    //   393: aload_0
    //   394: getfield respuesta : Ljava/lang/String;
    //   397: aload_0
    //   398: getfield responseCode : I
    //   401: invokeinterface onPostExecuteListener : (Ljava/lang/String;I)V
    //   406: return
    //   407: aload_0
    //   408: getfield simpleObject : Lcom/roadtrack/onstar/BO/SimpleRequestObject;
    //   411: invokevirtual get_url : ()Ljava/lang/String;
    //   414: astore #6
    //   416: aload_0
    //   417: getfield simpleObject : Lcom/roadtrack/onstar/BO/SimpleRequestObject;
    //   420: invokevirtual getRequest_propertys : ()Ljava/util/LinkedHashMap;
    //   423: astore #7
    //   425: goto -> 916
    //   428: aload_0
    //   429: getfield jsonRequestObject : Lcom/roadtrack/onstar/BO/JsonRequestObject;
    //   432: ifnonnull -> 521
    //   435: aload_0
    //   436: ldc 'Error, SoapRequestObject is null'
    //   438: putfield respuesta : Ljava/lang/String;
    //   441: aload_0
    //   442: iconst_m1
    //   443: putfield responseCode : I
    //   446: new java/lang/StringBuilder
    //   449: astore #5
    //   451: aload #5
    //   453: invokespecial <init> : ()V
    //   456: aload #5
    //   458: aload_0
    //   459: getfield respuesta : Ljava/lang/String;
    //   462: invokevirtual append : (Ljava/lang/String;)Ljava/lang/StringBuilder;
    //   465: pop
    //   466: aload #5
    //   468: ldc ' code:'
    //   470: invokevirtual append : (Ljava/lang/String;)Ljava/lang/StringBuilder;
    //   473: pop
    //   474: aload #5
    //   476: aload_0
    //   477: getfield responseCode : I
    //   480: invokevirtual append : (I)Ljava/lang/StringBuilder;
    //   483: pop
    //   484: ldc 'Request Manager'
    //   486: ldc 'Error : '
    //   488: aload #5
    //   490: invokevirtual toString : ()Ljava/lang/String;
    //   493: invokestatic escribeArchivo : (Ljava/lang/String;Ljava/lang/String;Ljava/lang/String;)V
    //   496: aload_0
    //   497: getfield _onPostExecuteListener : Lcom/roadtrack/onstar/BO/RequestManager$OnPostExecuteListener;
    //   500: ifnull -> 520
    //   503: aload_0
    //   504: getfield _onPostExecuteListener : Lcom/roadtrack/onstar/BO/RequestManager$OnPostExecuteListener;
    //   507: aload_0
    //   508: getfield respuesta : Ljava/lang/String;
    //   511: aload_0
    //   512: getfield responseCode : I
    //   515: invokeinterface onPostExecuteListener : (Ljava/lang/String;I)V
    //   520: return
    //   521: aload_0
    //   522: getfield jsonRequestObject : Lcom/roadtrack/onstar/BO/JsonRequestObject;
    //   525: invokevirtual buildJsonRequest : ()Ljava/lang/String;
    //   528: astore #10
    //   530: aload #10
    //   532: ifnonnull -> 621
    //   535: aload_0
    //   536: ldc 'Error, missing argument'
    //   538: putfield respuesta : Ljava/lang/String;
    //   541: aload_0
    //   542: iconst_m1
    //   543: putfield responseCode : I
    //   546: new java/lang/StringBuilder
    //   549: astore #5
    //   551: aload #5
    //   553: invokespecial <init> : ()V
    //   556: aload #5
    //   558: aload_0
    //   559: getfield respuesta : Ljava/lang/String;
    //   562: invokevirtual append : (Ljava/lang/String;)Ljava/lang/StringBuilder;
    //   565: pop
    //   566: aload #5
    //   568: ldc ' code:'
    //   570: invokevirtual append : (Ljava/lang/String;)Ljava/lang/StringBuilder;
    //   573: pop
    //   574: aload #5
    //   576: aload_0
    //   577: getfield responseCode : I
    //   580: invokevirtual append : (I)Ljava/lang/StringBuilder;
    //   583: pop
    //   584: ldc 'Request Manager'
    //   586: ldc 'Error : '
    //   588: aload #5
    //   590: invokevirtual toString : ()Ljava/lang/String;
    //   593: invokestatic escribeArchivo : (Ljava/lang/String;Ljava/lang/String;Ljava/lang/String;)V
    //   596: aload_0
    //   597: getfield _onPostExecuteListener : Lcom/roadtrack/onstar/BO/RequestManager$OnPostExecuteListener;
    //   600: ifnull -> 620
    //   603: aload_0
    //   604: getfield _onPostExecuteListener : Lcom/roadtrack/onstar/BO/RequestManager$OnPostExecuteListener;
    //   607: aload_0
    //   608: getfield respuesta : Ljava/lang/String;
    //   611: aload_0
    //   612: getfield responseCode : I
    //   615: invokeinterface onPostExecuteListener : (Ljava/lang/String;I)V
    //   620: return
    //   621: aload_0
    //   622: getfield jsonRequestObject : Lcom/roadtrack/onstar/BO/JsonRequestObject;
    //   625: invokevirtual get_fullUrl : ()Ljava/lang/String;
    //   628: astore #6
    //   630: aload_0
    //   631: aload_0
    //   632: getfield jsonRequestObject : Lcom/roadtrack/onstar/BO/JsonRequestObject;
    //   635: invokevirtual getKeyStoreId : ()I
    //   638: aload_0
    //   639: getfield jsonRequestObject : Lcom/roadtrack/onstar/BO/JsonRequestObject;
    //   642: invokevirtual getNameKeyStore : ()Ljava/lang/String;
    //   645: invokespecial getSocketFactory : (ILjava/lang/String;)Ljavax/net/ssl/SSLSocketFactory;
    //   648: astore #5
    //   650: aload_0
    //   651: getfield jsonRequestObject : Lcom/roadtrack/onstar/BO/JsonRequestObject;
    //   654: invokevirtual getRequest_propertys : ()Ljava/util/LinkedHashMap;
    //   657: astore #7
    //   659: goto -> 1387
    //   662: aload_0
    //   663: getfield simpleObject : Lcom/roadtrack/onstar/BO/SimpleRequestObject;
    //   666: ifnonnull -> 755
    //   669: aload_0
    //   670: ldc 'Error, SoapRequestObject is null'
    //   672: putfield respuesta : Ljava/lang/String;
    //   675: aload_0
    //   676: iconst_m1
    //   677: putfield responseCode : I
    //   680: new java/lang/StringBuilder
    //   683: astore #5
    //   685: aload #5
    //   687: invokespecial <init> : ()V
    //   690: aload #5
    //   692: aload_0
    //   693: getfield respuesta : Ljava/lang/String;
    //   696: invokevirtual append : (Ljava/lang/String;)Ljava/lang/StringBuilder;
    //   699: pop
    //   700: aload #5
    //   702: ldc ' code:'
    //   704: invokevirtual append : (Ljava/lang/String;)Ljava/lang/StringBuilder;
    //   707: pop
    //   708: aload #5
    //   710: aload_0
    //   711: getfield responseCode : I
    //   714: invokevirtual append : (I)Ljava/lang/StringBuilder;
    //   717: pop
    //   718: ldc 'Request Manager'
    //   720: ldc 'Error : '
    //   722: aload #5
    //   724: invokevirtual toString : ()Ljava/lang/String;
    //   727: invokestatic escribeArchivo : (Ljava/lang/String;Ljava/lang/String;Ljava/lang/String;)V
    //   730: aload_0
    //   731: getfield _onPostExecuteListener : Lcom/roadtrack/onstar/BO/RequestManager$OnPostExecuteListener;
    //   734: ifnull -> 754
    //   737: aload_0
    //   738: getfield _onPostExecuteListener : Lcom/roadtrack/onstar/BO/RequestManager$OnPostExecuteListener;
    //   741: aload_0
    //   742: getfield respuesta : Ljava/lang/String;
    //   745: aload_0
    //   746: getfield responseCode : I
    //   749: invokeinterface onPostExecuteListener : (Ljava/lang/String;I)V
    //   754: return
    //   755: aload_0
    //   756: getfield simpleObject : Lcom/roadtrack/onstar/BO/SimpleRequestObject;
    //   759: invokevirtual buildSimpleRequest : ()Ljava/lang/String;
    //   762: astore #10
    //   764: aload_0
    //   765: getfield simpleObject : Lcom/roadtrack/onstar/BO/SimpleRequestObject;
    //   768: invokevirtual get_url : ()Ljava/lang/String;
    //   771: astore #6
    //   773: aload_0
    //   774: aload_0
    //   775: getfield simpleObject : Lcom/roadtrack/onstar/BO/SimpleRequestObject;
    //   778: invokevirtual get_keyStoreId : ()I
    //   781: aload_0
    //   782: getfield simpleObject : Lcom/roadtrack/onstar/BO/SimpleRequestObject;
    //   785: invokevirtual get_nameKeyStore : ()Ljava/lang/String;
    //   788: invokespecial getSocketFactory : (ILjava/lang/String;)Ljavax/net/ssl/SSLSocketFactory;
    //   791: astore #5
    //   793: aload_0
    //   794: getfield simpleObject : Lcom/roadtrack/onstar/BO/SimpleRequestObject;
    //   797: invokevirtual getRequest_propertys : ()Ljava/util/LinkedHashMap;
    //   800: astore #7
    //   802: goto -> 1387
    //   805: aload_0
    //   806: getfield simpleObject : Lcom/roadtrack/onstar/BO/SimpleRequestObject;
    //   809: ifnonnull -> 898
    //   812: aload_0
    //   813: ldc 'Error, SoapRequestObject is null'
    //   815: putfield respuesta : Ljava/lang/String;
    //   818: aload_0
    //   819: iconst_m1
    //   820: putfield responseCode : I
    //   823: new java/lang/StringBuilder
    //   826: astore #5
    //   828: aload #5
    //   830: invokespecial <init> : ()V
    //   833: aload #5
    //   835: aload_0
    //   836: getfield respuesta : Ljava/lang/String;
    //   839: invokevirtual append : (Ljava/lang/String;)Ljava/lang/StringBuilder;
    //   842: pop
    //   843: aload #5
    //   845: ldc ' code:'
    //   847: invokevirtual append : (Ljava/lang/String;)Ljava/lang/StringBuilder;
    //   850: pop
    //   851: aload #5
    //   853: aload_0
    //   854: getfield responseCode : I
    //   857: invokevirtual append : (I)Ljava/lang/StringBuilder;
    //   860: pop
    //   861: ldc 'Request Manager'
    //   863: ldc 'Error : '
    //   865: aload #5
    //   867: invokevirtual toString : ()Ljava/lang/String;
    //   870: invokestatic escribeArchivo : (Ljava/lang/String;Ljava/lang/String;Ljava/lang/String;)V
    //   873: aload_0
    //   874: getfield _onPostExecuteListener : Lcom/roadtrack/onstar/BO/RequestManager$OnPostExecuteListener;
    //   877: ifnull -> 897
    //   880: aload_0
    //   881: getfield _onPostExecuteListener : Lcom/roadtrack/onstar/BO/RequestManager$OnPostExecuteListener;
    //   884: aload_0
    //   885: getfield respuesta : Ljava/lang/String;
    //   888: aload_0
    //   889: getfield responseCode : I
    //   892: invokeinterface onPostExecuteListener : (Ljava/lang/String;I)V
    //   897: return
    //   898: aload_0
    //   899: getfield simpleObject : Lcom/roadtrack/onstar/BO/SimpleRequestObject;
    //   902: invokevirtual get_url : ()Ljava/lang/String;
    //   905: astore #6
    //   907: aload_0
    //   908: getfield simpleObject : Lcom/roadtrack/onstar/BO/SimpleRequestObject;
    //   911: invokevirtual getRequest_propertys : ()Ljava/util/LinkedHashMap;
    //   914: astore #7
    //   916: aconst_null
    //   917: astore #5
    //   919: goto -> 1387
    //   922: aload_0
    //   923: getfield simpleObject : Lcom/roadtrack/onstar/BO/SimpleRequestObject;
    //   926: ifnonnull -> 1015
    //   929: aload_0
    //   930: ldc 'Error, SoapRequestObject is null'
    //   932: putfield respuesta : Ljava/lang/String;
    //   935: aload_0
    //   936: iconst_m1
    //   937: putfield responseCode : I
    //   940: new java/lang/StringBuilder
    //   943: astore #5
    //   945: aload #5
    //   947: invokespecial <init> : ()V
    //   950: aload #5
    //   952: aload_0
    //   953: getfield respuesta : Ljava/lang/String;
    //   956: invokevirtual append : (Ljava/lang/String;)Ljava/lang/StringBuilder;
    //   959: pop
    //   960: aload #5
    //   962: ldc ' code:'
    //   964: invokevirtual append : (Ljava/lang/String;)Ljava/lang/StringBuilder;
    //   967: pop
    //   968: aload #5
    //   970: aload_0
    //   971: getfield responseCode : I
    //   974: invokevirtual append : (I)Ljava/lang/StringBuilder;
    //   977: pop
    //   978: ldc 'Request Manager'
    //   980: ldc 'Error : '
    //   982: aload #5
    //   984: invokevirtual toString : ()Ljava/lang/String;
    //   987: invokestatic escribeArchivo : (Ljava/lang/String;Ljava/lang/String;Ljava/lang/String;)V
    //   990: aload_0
    //   991: getfield _onPostExecuteListener : Lcom/roadtrack/onstar/BO/RequestManager$OnPostExecuteListener;
    //   994: ifnull -> 1014
    //   997: aload_0
    //   998: getfield _onPostExecuteListener : Lcom/roadtrack/onstar/BO/RequestManager$OnPostExecuteListener;
    //   1001: aload_0
    //   1002: getfield respuesta : Ljava/lang/String;
    //   1005: aload_0
    //   1006: getfield responseCode : I
    //   1009: invokeinterface onPostExecuteListener : (Ljava/lang/String;I)V
    //   1014: return
    //   1015: aload_0
    //   1016: getfield simpleObject : Lcom/roadtrack/onstar/BO/SimpleRequestObject;
    //   1019: invokevirtual buildSimpleRequest : ()Ljava/lang/String;
    //   1022: astore #10
    //   1024: aload #10
    //   1026: ifnonnull -> 1115
    //   1029: aload_0
    //   1030: ldc 'Error, missing argument'
    //   1032: putfield respuesta : Ljava/lang/String;
    //   1035: aload_0
    //   1036: iconst_m1
    //   1037: putfield responseCode : I
    //   1040: new java/lang/StringBuilder
    //   1043: astore #5
    //   1045: aload #5
    //   1047: invokespecial <init> : ()V
    //   1050: aload #5
    //   1052: aload_0
    //   1053: getfield respuesta : Ljava/lang/String;
    //   1056: invokevirtual append : (Ljava/lang/String;)Ljava/lang/StringBuilder;
    //   1059: pop
    //   1060: aload #5
    //   1062: ldc ' code:'
    //   1064: invokevirtual append : (Ljava/lang/String;)Ljava/lang/StringBuilder;
    //   1067: pop
    //   1068: aload #5
    //   1070: aload_0
    //   1071: getfield responseCode : I
    //   1074: invokevirtual append : (I)Ljava/lang/StringBuilder;
    //   1077: pop
    //   1078: ldc 'Request Manager'
    //   1080: ldc 'Error : '
    //   1082: aload #5
    //   1084: invokevirtual toString : ()Ljava/lang/String;
    //   1087: invokestatic escribeArchivo : (Ljava/lang/String;Ljava/lang/String;Ljava/lang/String;)V
    //   1090: aload_0
    //   1091: getfield _onPostExecuteListener : Lcom/roadtrack/onstar/BO/RequestManager$OnPostExecuteListener;
    //   1094: ifnull -> 1114
    //   1097: aload_0
    //   1098: getfield _onPostExecuteListener : Lcom/roadtrack/onstar/BO/RequestManager$OnPostExecuteListener;
    //   1101: aload_0
    //   1102: getfield respuesta : Ljava/lang/String;
    //   1105: aload_0
    //   1106: getfield responseCode : I
    //   1109: invokeinterface onPostExecuteListener : (Ljava/lang/String;I)V
    //   1114: return
    //   1115: aload_0
    //   1116: getfield simpleObject : Lcom/roadtrack/onstar/BO/SimpleRequestObject;
    //   1119: invokevirtual get_url : ()Ljava/lang/String;
    //   1122: astore #6
    //   1124: aload_0
    //   1125: aload_0
    //   1126: getfield simpleObject : Lcom/roadtrack/onstar/BO/SimpleRequestObject;
    //   1129: invokevirtual get_keyStoreId : ()I
    //   1132: aload_0
    //   1133: getfield simpleObject : Lcom/roadtrack/onstar/BO/SimpleRequestObject;
    //   1136: invokevirtual get_nameKeyStore : ()Ljava/lang/String;
    //   1139: invokespecial getSocketFactory : (ILjava/lang/String;)Ljavax/net/ssl/SSLSocketFactory;
    //   1142: astore #5
    //   1144: aload_0
    //   1145: getfield simpleObject : Lcom/roadtrack/onstar/BO/SimpleRequestObject;
    //   1148: invokevirtual getRequest_propertys : ()Ljava/util/LinkedHashMap;
    //   1151: astore #7
    //   1153: goto -> 1387
    //   1156: aload_0
    //   1157: getfield soapObject : Lcom/roadtrack/onstar/BO/SoapRequestObject;
    //   1160: ifnonnull -> 1249
    //   1163: aload_0
    //   1164: ldc 'Error, SoapRequestObject is null'
    //   1166: putfield respuesta : Ljava/lang/String;
    //   1169: aload_0
    //   1170: iconst_m1
    //   1171: putfield responseCode : I
    //   1174: new java/lang/StringBuilder
    //   1177: astore #5
    //   1179: aload #5
    //   1181: invokespecial <init> : ()V
    //   1184: aload #5
    //   1186: aload_0
    //   1187: getfield respuesta : Ljava/lang/String;
    //   1190: invokevirtual append : (Ljava/lang/String;)Ljava/lang/StringBuilder;
    //   1193: pop
    //   1194: aload #5
    //   1196: ldc ' code:'
    //   1198: invokevirtual append : (Ljava/lang/String;)Ljava/lang/StringBuilder;
    //   1201: pop
    //   1202: aload #5
    //   1204: aload_0
    //   1205: getfield responseCode : I
    //   1208: invokevirtual append : (I)Ljava/lang/StringBuilder;
    //   1211: pop
    //   1212: ldc 'Request Manager'
    //   1214: ldc 'Error : '
    //   1216: aload #5
    //   1218: invokevirtual toString : ()Ljava/lang/String;
    //   1221: invokestatic escribeArchivo : (Ljava/lang/String;Ljava/lang/String;Ljava/lang/String;)V
    //   1224: aload_0
    //   1225: getfield _onPostExecuteListener : Lcom/roadtrack/onstar/BO/RequestManager$OnPostExecuteListener;
    //   1228: ifnull -> 1248
    //   1231: aload_0
    //   1232: getfield _onPostExecuteListener : Lcom/roadtrack/onstar/BO/RequestManager$OnPostExecuteListener;
    //   1235: aload_0
    //   1236: getfield respuesta : Ljava/lang/String;
    //   1239: aload_0
    //   1240: getfield responseCode : I
    //   1243: invokeinterface onPostExecuteListener : (Ljava/lang/String;I)V
    //   1248: return
    //   1249: aload_0
    //   1250: getfield soapObject : Lcom/roadtrack/onstar/BO/SoapRequestObject;
    //   1253: invokevirtual buildSoapRequest : ()Ljava/lang/String;
    //   1256: astore #10
    //   1258: aload #10
    //   1260: ifnonnull -> 1349
    //   1263: aload_0
    //   1264: ldc 'Error, missing argument'
    //   1266: putfield respuesta : Ljava/lang/String;
    //   1269: aload_0
    //   1270: iconst_m1
    //   1271: putfield responseCode : I
    //   1274: new java/lang/StringBuilder
    //   1277: astore #5
    //   1279: aload #5
    //   1281: invokespecial <init> : ()V
    //   1284: aload #5
    //   1286: aload_0
    //   1287: getfield respuesta : Ljava/lang/String;
    //   1290: invokevirtual append : (Ljava/lang/String;)Ljava/lang/StringBuilder;
    //   1293: pop
    //   1294: aload #5
    //   1296: ldc ' code:'
    //   1298: invokevirtual append : (Ljava/lang/String;)Ljava/lang/StringBuilder;
    //   1301: pop
    //   1302: aload #5
    //   1304: aload_0
    //   1305: getfield responseCode : I
    //   1308: invokevirtual append : (I)Ljava/lang/StringBuilder;
    //   1311: pop
    //   1312: ldc 'Request Manager'
    //   1314: ldc 'Error : '
    //   1316: aload #5
    //   1318: invokevirtual toString : ()Ljava/lang/String;
    //   1321: invokestatic escribeArchivo : (Ljava/lang/String;Ljava/lang/String;Ljava/lang/String;)V
    //   1324: aload_0
    //   1325: getfield _onPostExecuteListener : Lcom/roadtrack/onstar/BO/RequestManager$OnPostExecuteListener;
    //   1328: ifnull -> 1348
    //   1331: aload_0
    //   1332: getfield _onPostExecuteListener : Lcom/roadtrack/onstar/BO/RequestManager$OnPostExecuteListener;
    //   1335: aload_0
    //   1336: getfield respuesta : Ljava/lang/String;
    //   1339: aload_0
    //   1340: getfield responseCode : I
    //   1343: invokeinterface onPostExecuteListener : (Ljava/lang/String;I)V
    //   1348: return
    //   1349: aload_0
    //   1350: getfield soapObject : Lcom/roadtrack/onstar/BO/SoapRequestObject;
    //   1353: invokevirtual get_url : ()Ljava/lang/String;
    //   1356: astore #6
    //   1358: aload_0
    //   1359: aload_0
    //   1360: getfield soapObject : Lcom/roadtrack/onstar/BO/SoapRequestObject;
    //   1363: invokevirtual getKeyStoreId : ()I
    //   1366: aload_0
    //   1367: getfield soapObject : Lcom/roadtrack/onstar/BO/SoapRequestObject;
    //   1370: invokevirtual getNameKeyStore : ()Ljava/lang/String;
    //   1373: invokespecial getSocketFactory : (ILjava/lang/String;)Ljavax/net/ssl/SSLSocketFactory;
    //   1376: astore #5
    //   1378: aload_0
    //   1379: getfield soapObject : Lcom/roadtrack/onstar/BO/SoapRequestObject;
    //   1382: invokevirtual getRequest_propertys : ()Ljava/util/LinkedHashMap;
    //   1385: astore #7
    //   1387: iload_1
    //   1388: iconst_3
    //   1389: if_icmpeq -> 1489
    //   1392: iload_1
    //   1393: bipush #6
    //   1395: if_icmpeq -> 1489
    //   1398: aload #5
    //   1400: ifnonnull -> 1489
    //   1403: aload_0
    //   1404: ldc 'Error, sending request'
    //   1406: putfield respuesta : Ljava/lang/String;
    //   1409: aload_0
    //   1410: iconst_m1
    //   1411: putfield responseCode : I
    //   1414: new java/lang/StringBuilder
    //   1417: astore #5
    //   1419: aload #5
    //   1421: invokespecial <init> : ()V
    //   1424: aload #5
    //   1426: aload_0
    //   1427: getfield respuesta : Ljava/lang/String;
    //   1430: invokevirtual append : (Ljava/lang/String;)Ljava/lang/StringBuilder;
    //   1433: pop
    //   1434: aload #5
    //   1436: ldc ' code:'
    //   1438: invokevirtual append : (Ljava/lang/String;)Ljava/lang/StringBuilder;
    //   1441: pop
    //   1442: aload #5
    //   1444: aload_0
    //   1445: getfield responseCode : I
    //   1448: invokevirtual append : (I)Ljava/lang/StringBuilder;
    //   1451: pop
    //   1452: ldc 'Request Manager'
    //   1454: ldc 'Error sendPost'
    //   1456: aload #5
    //   1458: invokevirtual toString : ()Ljava/lang/String;
    //   1461: invokestatic escribeArchivo : (Ljava/lang/String;Ljava/lang/String;Ljava/lang/String;)V
    //   1464: aload_0
    //   1465: getfield _onPostExecuteListener : Lcom/roadtrack/onstar/BO/RequestManager$OnPostExecuteListener;
    //   1468: ifnull -> 1488
    //   1471: aload_0
    //   1472: getfield _onPostExecuteListener : Lcom/roadtrack/onstar/BO/RequestManager$OnPostExecuteListener;
    //   1475: aload_0
    //   1476: getfield respuesta : Ljava/lang/String;
    //   1479: aload_0
    //   1480: getfield responseCode : I
    //   1483: invokeinterface onPostExecuteListener : (Ljava/lang/String;I)V
    //   1488: return
    //   1489: iload_1
    //   1490: bipush #6
    //   1492: if_icmpne -> 1524
    //   1495: new com/roadtrack/onstar/gson/UrlBuilderC
    //   1498: astore #9
    //   1500: aload #9
    //   1502: aload #6
    //   1504: aload_0
    //   1505: getfield simpleObject : Lcom/roadtrack/onstar/BO/SimpleRequestObject;
    //   1508: invokevirtual getProperties : ()Ljava/util/LinkedHashMap;
    //   1511: invokespecial <init> : (Ljava/lang/String;Ljava/util/HashMap;)V
    //   1514: aload #9
    //   1516: invokevirtual build : ()Ljava/net/URL;
    //   1519: astore #6
    //   1521: goto -> 1535
    //   1524: new java/net/URL
    //   1527: dup
    //   1528: aload #6
    //   1530: invokespecial <init> : (Ljava/lang/String;)V
    //   1533: astore #6
    //   1535: aload #6
    //   1537: invokevirtual openConnection : ()Ljava/net/URLConnection;
    //   1540: checkcast javax/net/ssl/HttpsURLConnection
    //   1543: astore #9
    //   1545: iload_1
    //   1546: iconst_4
    //   1547: if_icmpeq -> 1575
    //   1550: iload_1
    //   1551: bipush #7
    //   1553: if_icmpeq -> 1575
    //   1556: iload_3
    //   1557: istore_2
    //   1558: iload_1
    //   1559: iconst_5
    //   1560: if_icmpne -> 1577
    //   1563: iload_3
    //   1564: istore_2
    //   1565: aload_0
    //   1566: getfield jsonRequestObject : Lcom/roadtrack/onstar/BO/JsonRequestObject;
    //   1569: invokevirtual isPropertysAsSet : ()Z
    //   1572: ifeq -> 1577
    //   1575: iconst_1
    //   1576: istore_2
    //   1577: aload #7
    //   1579: invokevirtual keySet : ()Ljava/util/Set;
    //   1582: invokeinterface iterator : ()Ljava/util/Iterator;
    //   1587: astore #13
    //   1589: aload #13
    //   1591: invokeinterface hasNext : ()Z
    //   1596: ifeq -> 1655
    //   1599: aload #13
    //   1601: invokeinterface next : ()Ljava/lang/Object;
    //   1606: checkcast java/lang/String
    //   1609: astore #6
    //   1611: iload_2
    //   1612: ifeq -> 1635
    //   1615: aload #9
    //   1617: aload #6
    //   1619: aload #7
    //   1621: aload #6
    //   1623: invokevirtual get : (Ljava/lang/Object;)Ljava/lang/Object;
    //   1626: checkcast java/lang/String
    //   1629: invokevirtual addRequestProperty : (Ljava/lang/String;Ljava/lang/String;)V
    //   1632: goto -> 1589
    //   1635: aload #9
    //   1637: aload #6
    //   1639: aload #7
    //   1641: aload #6
    //   1643: invokevirtual get : (Ljava/lang/Object;)Ljava/lang/Object;
    //   1646: checkcast java/lang/String
    //   1649: invokevirtual setRequestProperty : (Ljava/lang/String;Ljava/lang/String;)V
    //   1652: goto -> 1589
    //   1655: ldc 'Request Manager'
    //   1657: ldc_w 'Request: '
    //   1660: aload #10
    //   1662: invokestatic escribeArchivo : (Ljava/lang/String;Ljava/lang/String;Ljava/lang/String;)V
    //   1665: iload_1
    //   1666: tableswitch default -> 1708, 1 -> 2171, 2 -> 2061, 3 -> 2026, 4 -> 1917, 5 -> 1820, 6 -> 2026, 7 -> 1711
    //   1708: goto -> 2301
    //   1711: aload #9
    //   1713: aload #5
    //   1715: invokevirtual setSSLSocketFactory : (Ljavax/net/ssl/SSLSocketFactory;)V
    //   1718: aload #9
    //   1720: aload_0
    //   1721: getfield simpleObject : Lcom/roadtrack/onstar/BO/SimpleRequestObject;
    //   1724: invokevirtual get_connection_time_out : ()I
    //   1727: invokevirtual setConnectTimeout : (I)V
    //   1730: aload #9
    //   1732: aload_0
    //   1733: getfield simpleObject : Lcom/roadtrack/onstar/BO/SimpleRequestObject;
    //   1736: invokevirtual get_read_time_out : ()I
    //   1739: invokevirtual setReadTimeout : (I)V
    //   1742: aload #9
    //   1744: iconst_1
    //   1745: invokevirtual setDoInput : (Z)V
    //   1748: aload #9
    //   1750: ldc_w 'POST'
    //   1753: invokevirtual setRequestMethod : (Ljava/lang/String;)V
    //   1756: aload #10
    //   1758: ifnull -> 2301
    //   1761: aload #9
    //   1763: iconst_1
    //   1764: invokevirtual setDoOutput : (Z)V
    //   1767: new java/io/DataOutputStream
    //   1770: dup
    //   1771: aload #9
    //   1773: invokevirtual getOutputStream : ()Ljava/io/OutputStream;
    //   1776: invokespecial <init> : (Ljava/io/OutputStream;)V
    //   1779: astore #5
    //   1781: aload #5
    //   1783: astore #6
    //   1785: aload #5
    //   1787: astore #7
    //   1789: aload #5
    //   1791: astore #8
    //   1793: aload #5
    //   1795: aload #10
    //   1797: invokevirtual writeBytes : (Ljava/lang/String;)V
    //   1800: aload #5
    //   1802: astore #6
    //   1804: aload #5
    //   1806: astore #7
    //   1808: aload #5
    //   1810: astore #8
    //   1812: aload #5
    //   1814: invokevirtual flush : ()V
    //   1817: goto -> 2304
    //   1820: aload #9
    //   1822: aload_0
    //   1823: getfield jsonRequestObject : Lcom/roadtrack/onstar/BO/JsonRequestObject;
    //   1826: invokevirtual get_connection_time_out : ()I
    //   1829: invokevirtual setConnectTimeout : (I)V
    //   1832: aload #9
    //   1834: aload_0
    //   1835: getfield jsonRequestObject : Lcom/roadtrack/onstar/BO/JsonRequestObject;
    //   1838: invokevirtual get_read_time_out : ()I
    //   1841: invokevirtual setReadTimeout : (I)V
    //   1844: aload #9
    //   1846: iconst_1
    //   1847: invokevirtual setDoInput : (Z)V
    //   1850: aload #9
    //   1852: ldc_w 'POST'
    //   1855: invokevirtual setRequestMethod : (Ljava/lang/String;)V
    //   1858: aload #9
    //   1860: iconst_1
    //   1861: invokevirtual setDoOutput : (Z)V
    //   1864: new java/io/DataOutputStream
    //   1867: dup
    //   1868: aload #9
    //   1870: invokevirtual getOutputStream : ()Ljava/io/OutputStream;
    //   1873: invokespecial <init> : (Ljava/io/OutputStream;)V
    //   1876: astore #5
    //   1878: aload #5
    //   1880: astore #6
    //   1882: aload #5
    //   1884: astore #7
    //   1886: aload #5
    //   1888: astore #8
    //   1890: aload #5
    //   1892: aload #10
    //   1894: invokevirtual writeBytes : (Ljava/lang/String;)V
    //   1897: aload #5
    //   1899: astore #6
    //   1901: aload #5
    //   1903: astore #7
    //   1905: aload #5
    //   1907: astore #8
    //   1909: aload #5
    //   1911: invokevirtual flush : ()V
    //   1914: goto -> 2304
    //   1917: aload #9
    //   1919: aload #5
    //   1921: invokevirtual setSSLSocketFactory : (Ljavax/net/ssl/SSLSocketFactory;)V
    //   1924: aload #9
    //   1926: aload_0
    //   1927: getfield simpleObject : Lcom/roadtrack/onstar/BO/SimpleRequestObject;
    //   1930: invokevirtual get_connection_time_out : ()I
    //   1933: invokevirtual setConnectTimeout : (I)V
    //   1936: aload #9
    //   1938: aload_0
    //   1939: getfield simpleObject : Lcom/roadtrack/onstar/BO/SimpleRequestObject;
    //   1942: invokevirtual get_read_time_out : ()I
    //   1945: invokevirtual setReadTimeout : (I)V
    //   1948: aload #9
    //   1950: iconst_1
    //   1951: invokevirtual setDoInput : (Z)V
    //   1954: aload #9
    //   1956: ldc_w 'GET'
    //   1959: invokevirtual setRequestMethod : (Ljava/lang/String;)V
    //   1962: aload #10
    //   1964: ifnull -> 2301
    //   1967: aload #9
    //   1969: iconst_1
    //   1970: invokevirtual setDoOutput : (Z)V
    //   1973: new java/io/DataOutputStream
    //   1976: dup
    //   1977: aload #9
    //   1979: invokevirtual getOutputStream : ()Ljava/io/OutputStream;
    //   1982: invokespecial <init> : (Ljava/io/OutputStream;)V
    //   1985: astore #5
    //   1987: aload #5
    //   1989: astore #6
    //   1991: aload #5
    //   1993: astore #7
    //   1995: aload #5
    //   1997: astore #8
    //   1999: aload #5
    //   2001: aload #10
    //   2003: invokevirtual writeBytes : (Ljava/lang/String;)V
    //   2006: aload #5
    //   2008: astore #6
    //   2010: aload #5
    //   2012: astore #7
    //   2014: aload #5
    //   2016: astore #8
    //   2018: aload #5
    //   2020: invokevirtual flush : ()V
    //   2023: goto -> 2304
    //   2026: aload #9
    //   2028: aload_0
    //   2029: getfield simpleObject : Lcom/roadtrack/onstar/BO/SimpleRequestObject;
    //   2032: invokevirtual get_connection_time_out : ()I
    //   2035: invokevirtual setConnectTimeout : (I)V
    //   2038: aload #9
    //   2040: aload_0
    //   2041: getfield simpleObject : Lcom/roadtrack/onstar/BO/SimpleRequestObject;
    //   2044: invokevirtual get_read_time_out : ()I
    //   2047: invokevirtual setReadTimeout : (I)V
    //   2050: aload #9
    //   2052: ldc_w 'GET'
    //   2055: invokevirtual setRequestMethod : (Ljava/lang/String;)V
    //   2058: goto -> 2301
    //   2061: aload #9
    //   2063: aload #5
    //   2065: invokevirtual setSSLSocketFactory : (Ljavax/net/ssl/SSLSocketFactory;)V
    //   2068: aload #9
    //   2070: aload_0
    //   2071: getfield simpleObject : Lcom/roadtrack/onstar/BO/SimpleRequestObject;
    //   2074: invokevirtual get_connection_time_out : ()I
    //   2077: invokevirtual setConnectTimeout : (I)V
    //   2080: aload #9
    //   2082: aload_0
    //   2083: getfield simpleObject : Lcom/roadtrack/onstar/BO/SimpleRequestObject;
    //   2086: invokevirtual get_read_time_out : ()I
    //   2089: invokevirtual setReadTimeout : (I)V
    //   2092: aload #9
    //   2094: iconst_1
    //   2095: invokevirtual setDoOutput : (Z)V
    //   2098: aload #9
    //   2100: iconst_1
    //   2101: invokevirtual setDoInput : (Z)V
    //   2104: aload #9
    //   2106: ldc_w 'POST'
    //   2109: invokevirtual setRequestMethod : (Ljava/lang/String;)V
    //   2112: aload #9
    //   2114: iconst_1
    //   2115: invokevirtual setDoOutput : (Z)V
    //   2118: new java/io/DataOutputStream
    //   2121: dup
    //   2122: aload #9
    //   2124: invokevirtual getOutputStream : ()Ljava/io/OutputStream;
    //   2127: invokespecial <init> : (Ljava/io/OutputStream;)V
    //   2130: astore #5
    //   2132: aload #5
    //   2134: astore #6
    //   2136: aload #5
    //   2138: astore #7
    //   2140: aload #5
    //   2142: astore #8
    //   2144: aload #5
    //   2146: aload #10
    //   2148: invokevirtual writeBytes : (Ljava/lang/String;)V
    //   2151: aload #5
    //   2153: astore #6
    //   2155: aload #5
    //   2157: astore #7
    //   2159: aload #5
    //   2161: astore #8
    //   2163: aload #5
    //   2165: invokevirtual flush : ()V
    //   2168: goto -> 2304
    //   2171: aload #9
    //   2173: aload #5
    //   2175: invokevirtual setSSLSocketFactory : (Ljavax/net/ssl/SSLSocketFactory;)V
    //   2178: aload #9
    //   2180: aload_0
    //   2181: getfield soapObject : Lcom/roadtrack/onstar/BO/SoapRequestObject;
    //   2184: invokevirtual get_connection_time_out : ()I
    //   2187: invokevirtual setConnectTimeout : (I)V
    //   2190: aload #9
    //   2192: aload_0
    //   2193: getfield soapObject : Lcom/roadtrack/onstar/BO/SoapRequestObject;
    //   2196: invokevirtual get_read_time_out : ()I
    //   2199: invokevirtual setReadTimeout : (I)V
    //   2202: aload #9
    //   2204: iconst_1
    //   2205: invokevirtual setDoOutput : (Z)V
    //   2208: aload #9
    //   2210: iconst_1
    //   2211: invokevirtual setDoInput : (Z)V
    //   2214: aload #9
    //   2216: ldc_w 'POST'
    //   2219: invokevirtual setRequestMethod : (Ljava/lang/String;)V
    //   2222: aload #9
    //   2224: ldc_w 'SOAPAction'
    //   2227: aload_0
    //   2228: getfield soapObject : Lcom/roadtrack/onstar/BO/SoapRequestObject;
    //   2231: invokevirtual get_soapAction : ()Ljava/lang/String;
    //   2234: invokevirtual setRequestProperty : (Ljava/lang/String;Ljava/lang/String;)V
    //   2237: aload #9
    //   2239: ldc_w 'Connection'
    //   2242: ldc_w 'close'
    //   2245: invokevirtual setRequestProperty : (Ljava/lang/String;Ljava/lang/String;)V
    //   2248: new java/io/DataOutputStream
    //   2251: dup
    //   2252: aload #9
    //   2254: invokevirtual getOutputStream : ()Ljava/io/OutputStream;
    //   2257: invokespecial <init> : (Ljava/io/OutputStream;)V
    //   2260: astore #5
    //   2262: aload #5
    //   2264: astore #6
    //   2266: aload #5
    //   2268: astore #7
    //   2270: aload #5
    //   2272: astore #8
    //   2274: aload #5
    //   2276: aload #10
    //   2278: invokevirtual writeBytes : (Ljava/lang/String;)V
    //   2281: aload #5
    //   2283: astore #6
    //   2285: aload #5
    //   2287: astore #7
    //   2289: aload #5
    //   2291: astore #8
    //   2293: aload #5
    //   2295: invokevirtual flush : ()V
    //   2298: goto -> 2304
    //   2301: aconst_null
    //   2302: astore #5
    //   2304: aload #5
    //   2306: astore #6
    //   2308: aload #5
    //   2310: astore #7
    //   2312: aload #5
    //   2314: astore #8
    //   2316: aload_0
    //   2317: aload #9
    //   2319: invokevirtual getResponseCode : ()I
    //   2322: putfield responseCode : I
    //   2325: aload #5
    //   2327: astore #6
    //   2329: aload #5
    //   2331: astore #7
    //   2333: aload #5
    //   2335: astore #8
    //   2337: new java/io/InputStreamReader
    //   2340: astore #10
    //   2342: aload #5
    //   2344: astore #6
    //   2346: aload #5
    //   2348: astore #7
    //   2350: aload #5
    //   2352: astore #8
    //   2354: aload #10
    //   2356: aload #9
    //   2358: invokevirtual getInputStream : ()Ljava/io/InputStream;
    //   2361: invokespecial <init> : (Ljava/io/InputStream;)V
    //   2364: new java/io/BufferedReader
    //   2367: astore #6
    //   2369: aload #6
    //   2371: aload #10
    //   2373: invokespecial <init> : (Ljava/io/Reader;)V
    //   2376: aload #6
    //   2378: invokevirtual readLine : ()Ljava/lang/String;
    //   2381: astore #7
    //   2383: aload #7
    //   2385: ifnull -> 2401
    //   2388: aload_0
    //   2389: getfield xml_builder : Ljava/lang/StringBuilder;
    //   2392: aload #7
    //   2394: invokevirtual append : (Ljava/lang/String;)Ljava/lang/StringBuilder;
    //   2397: pop
    //   2398: goto -> 2376
    //   2401: aload_0
    //   2402: getfield responseCode : I
    //   2405: sipush #200
    //   2408: if_icmplt -> 2458
    //   2411: aload_0
    //   2412: getfield responseCode : I
    //   2415: sipush #300
    //   2418: if_icmpgt -> 2458
    //   2421: iload_1
    //   2422: iconst_1
    //   2423: if_icmpne -> 2444
    //   2426: aload_0
    //   2427: aload_0
    //   2428: aload_0
    //   2429: getfield xml_builder : Ljava/lang/StringBuilder;
    //   2432: invokevirtual toString : ()Ljava/lang/String;
    //   2435: invokespecial GetResponseFromXML : (Ljava/lang/String;)Ljava/lang/String;
    //   2438: putfield respuesta : Ljava/lang/String;
    //   2441: goto -> 2516
    //   2444: aload_0
    //   2445: aload_0
    //   2446: getfield xml_builder : Ljava/lang/StringBuilder;
    //   2449: invokevirtual toString : ()Ljava/lang/String;
    //   2452: putfield respuesta : Ljava/lang/String;
    //   2455: goto -> 2516
    //   2458: aload_0
    //   2459: aload_0
    //   2460: getfield xml_builder : Ljava/lang/StringBuilder;
    //   2463: invokevirtual toString : ()Ljava/lang/String;
    //   2466: putfield respuesta : Ljava/lang/String;
    //   2469: goto -> 2516
    //   2472: astore #7
    //   2474: aload #5
    //   2476: astore #11
    //   2478: aload #10
    //   2480: astore #8
    //   2482: aload #6
    //   2484: astore #5
    //   2486: goto -> 2693
    //   2489: astore #7
    //   2491: aload_0
    //   2492: ldc_w 'Error parsing response'
    //   2495: putfield respuesta : Ljava/lang/String;
    //   2498: aload_0
    //   2499: iconst_m1
    //   2500: putfield responseCode : I
    //   2503: ldc 'Request Manager'
    //   2505: ldc_w 'Error parsing response'
    //   2508: aload #7
    //   2510: invokevirtual getMessage : ()Ljava/lang/String;
    //   2513: invokestatic escribeArchivo : (Ljava/lang/String;Ljava/lang/String;Ljava/lang/String;)V
    //   2516: aload #5
    //   2518: ifnull -> 2544
    //   2521: aload #5
    //   2523: invokevirtual close : ()V
    //   2526: goto -> 2544
    //   2529: astore #5
    //   2531: ldc 'Request Manager'
    //   2533: ldc_w 'error'
    //   2536: aload #5
    //   2538: invokevirtual getMessage : ()Ljava/lang/String;
    //   2541: invokestatic escribeArchivo : (Ljava/lang/String;Ljava/lang/String;Ljava/lang/String;)V
    //   2544: aload #6
    //   2546: invokevirtual close : ()V
    //   2549: goto -> 2567
    //   2552: astore #5
    //   2554: ldc 'Request Manager'
    //   2556: ldc_w 'error'
    //   2559: aload #5
    //   2561: invokevirtual getMessage : ()Ljava/lang/String;
    //   2564: invokestatic escribeArchivo : (Ljava/lang/String;Ljava/lang/String;Ljava/lang/String;)V
    //   2567: aload #10
    //   2569: invokevirtual close : ()V
    //   2572: goto -> 2590
    //   2575: astore #5
    //   2577: ldc 'Request Manager'
    //   2579: ldc_w 'error'
    //   2582: aload #5
    //   2584: invokevirtual getMessage : ()Ljava/lang/String;
    //   2587: invokestatic escribeArchivo : (Ljava/lang/String;Ljava/lang/String;Ljava/lang/String;)V
    //   2590: aload #9
    //   2592: ifnull -> 3366
    //   2595: aload #9
    //   2597: invokevirtual disconnect : ()V
    //   2600: goto -> 3366
    //   2603: astore #8
    //   2605: aload #5
    //   2607: astore #7
    //   2609: aload #8
    //   2611: astore #5
    //   2613: goto -> 2720
    //   2616: astore #7
    //   2618: aload #5
    //   2620: astore #8
    //   2622: aload #7
    //   2624: astore #5
    //   2626: goto -> 2743
    //   2629: astore #7
    //   2631: aconst_null
    //   2632: astore #6
    //   2634: aload #5
    //   2636: astore #11
    //   2638: aload #10
    //   2640: astore #8
    //   2642: aload #6
    //   2644: astore #5
    //   2646: goto -> 2693
    //   2649: astore #8
    //   2651: aconst_null
    //   2652: astore #6
    //   2654: aload #5
    //   2656: astore #7
    //   2658: aload #8
    //   2660: astore #5
    //   2662: goto -> 2720
    //   2665: astore #7
    //   2667: aconst_null
    //   2668: astore #6
    //   2670: aload #5
    //   2672: astore #8
    //   2674: aload #7
    //   2676: astore #5
    //   2678: goto -> 2743
    //   2681: astore #7
    //   2683: aconst_null
    //   2684: astore #8
    //   2686: aconst_null
    //   2687: astore #5
    //   2689: aload #6
    //   2691: astore #11
    //   2693: aload #11
    //   2695: astore #10
    //   2697: aload #9
    //   2699: astore #6
    //   2701: aload #5
    //   2703: astore #11
    //   2705: aload #7
    //   2707: astore #9
    //   2709: goto -> 3419
    //   2712: astore #5
    //   2714: aconst_null
    //   2715: astore #10
    //   2717: aconst_null
    //   2718: astore #6
    //   2720: aload #7
    //   2722: astore #12
    //   2724: aload #6
    //   2726: astore #11
    //   2728: aload #5
    //   2730: astore #13
    //   2732: goto -> 2993
    //   2735: astore #5
    //   2737: aconst_null
    //   2738: astore #10
    //   2740: aconst_null
    //   2741: astore #6
    //   2743: aload #8
    //   2745: astore #12
    //   2747: aload #6
    //   2749: astore #11
    //   2751: aload #5
    //   2753: astore #13
    //   2755: goto -> 3181
    //   2758: astore #5
    //   2760: aload #9
    //   2762: astore #6
    //   2764: aload #5
    //   2766: astore #9
    //   2768: goto -> 2961
    //   2771: astore #5
    //   2773: goto -> 2983
    //   2776: astore #5
    //   2778: goto -> 3167
    //   2781: astore #5
    //   2783: aload_0
    //   2784: ldc_w 'Error building url'
    //   2787: putfield respuesta : Ljava/lang/String;
    //   2790: aload_0
    //   2791: iconst_m1
    //   2792: putfield responseCode : I
    //   2795: new java/lang/StringBuilder
    //   2798: astore #5
    //   2800: aload #5
    //   2802: invokespecial <init> : ()V
    //   2805: aload #5
    //   2807: aload_0
    //   2808: getfield respuesta : Ljava/lang/String;
    //   2811: invokevirtual append : (Ljava/lang/String;)Ljava/lang/StringBuilder;
    //   2814: pop
    //   2815: aload #5
    //   2817: ldc ' code:'
    //   2819: invokevirtual append : (Ljava/lang/String;)Ljava/lang/StringBuilder;
    //   2822: pop
    //   2823: aload #5
    //   2825: aload_0
    //   2826: getfield responseCode : I
    //   2829: invokevirtual append : (I)Ljava/lang/StringBuilder;
    //   2832: pop
    //   2833: ldc 'Request Manager'
    //   2835: ldc 'Error sendPost'
    //   2837: aload #5
    //   2839: invokevirtual toString : ()Ljava/lang/String;
    //   2842: invokestatic escribeArchivo : (Ljava/lang/String;Ljava/lang/String;Ljava/lang/String;)V
    //   2845: aload_0
    //   2846: getfield _onPostExecuteListener : Lcom/roadtrack/onstar/BO/RequestManager$OnPostExecuteListener;
    //   2849: ifnull -> 2869
    //   2852: aload_0
    //   2853: getfield _onPostExecuteListener : Lcom/roadtrack/onstar/BO/RequestManager$OnPostExecuteListener;
    //   2856: aload_0
    //   2857: getfield respuesta : Ljava/lang/String;
    //   2860: aload_0
    //   2861: getfield responseCode : I
    //   2864: invokeinterface onPostExecuteListener : (Ljava/lang/String;I)V
    //   2869: return
    //   2870: aload_0
    //   2871: ldc 'Error, sending request'
    //   2873: putfield respuesta : Ljava/lang/String;
    //   2876: aload_0
    //   2877: iconst_m1
    //   2878: putfield responseCode : I
    //   2881: new java/lang/StringBuilder
    //   2884: astore #5
    //   2886: aload #5
    //   2888: invokespecial <init> : ()V
    //   2891: aload #5
    //   2893: aload_0
    //   2894: getfield respuesta : Ljava/lang/String;
    //   2897: invokevirtual append : (Ljava/lang/String;)Ljava/lang/StringBuilder;
    //   2900: pop
    //   2901: aload #5
    //   2903: ldc ' code:'
    //   2905: invokevirtual append : (Ljava/lang/String;)Ljava/lang/StringBuilder;
    //   2908: pop
    //   2909: aload #5
    //   2911: aload_0
    //   2912: getfield responseCode : I
    //   2915: invokevirtual append : (I)Ljava/lang/StringBuilder;
    //   2918: pop
    //   2919: ldc 'Request Manager'
    //   2921: ldc 'Error sendPost'
    //   2923: aload #5
    //   2925: invokevirtual toString : ()Ljava/lang/String;
    //   2928: invokestatic escribeArchivo : (Ljava/lang/String;Ljava/lang/String;Ljava/lang/String;)V
    //   2931: aload_0
    //   2932: getfield _onPostExecuteListener : Lcom/roadtrack/onstar/BO/RequestManager$OnPostExecuteListener;
    //   2935: ifnull -> 2955
    //   2938: aload_0
    //   2939: getfield _onPostExecuteListener : Lcom/roadtrack/onstar/BO/RequestManager$OnPostExecuteListener;
    //   2942: aload_0
    //   2943: getfield respuesta : Ljava/lang/String;
    //   2946: aload_0
    //   2947: getfield responseCode : I
    //   2950: invokeinterface onPostExecuteListener : (Ljava/lang/String;I)V
    //   2955: return
    //   2956: astore #9
    //   2958: aconst_null
    //   2959: astore #6
    //   2961: aconst_null
    //   2962: astore #8
    //   2964: aconst_null
    //   2965: astore #5
    //   2967: aload #11
    //   2969: astore #10
    //   2971: aload #5
    //   2973: astore #11
    //   2975: goto -> 3419
    //   2978: astore #5
    //   2980: aconst_null
    //   2981: astore #9
    //   2983: aconst_null
    //   2984: astore #10
    //   2986: aconst_null
    //   2987: astore #11
    //   2989: aload #5
    //   2991: astore #13
    //   2993: aload #12
    //   2995: astore #5
    //   2997: aload #9
    //   2999: astore #6
    //   3001: aload #10
    //   3003: astore #7
    //   3005: aload #11
    //   3007: astore #8
    //   3009: aload_0
    //   3010: ldc 'Error, sending request'
    //   3012: putfield respuesta : Ljava/lang/String;
    //   3015: aload #12
    //   3017: astore #5
    //   3019: aload #9
    //   3021: astore #6
    //   3023: aload #10
    //   3025: astore #7
    //   3027: aload #11
    //   3029: astore #8
    //   3031: aload_0
    //   3032: iconst_m1
    //   3033: putfield responseCode : I
    //   3036: aload #12
    //   3038: astore #5
    //   3040: aload #9
    //   3042: astore #6
    //   3044: aload #10
    //   3046: astore #7
    //   3048: aload #11
    //   3050: astore #8
    //   3052: ldc 'Request Manager'
    //   3054: ldc_w 'error'
    //   3057: aload #13
    //   3059: invokevirtual getMessage : ()Ljava/lang/String;
    //   3062: invokestatic escribeArchivo : (Ljava/lang/String;Ljava/lang/String;Ljava/lang/String;)V
    //   3065: aload #12
    //   3067: ifnull -> 3093
    //   3070: aload #12
    //   3072: invokevirtual close : ()V
    //   3075: goto -> 3093
    //   3078: astore #5
    //   3080: ldc 'Request Manager'
    //   3082: ldc_w 'error'
    //   3085: aload #5
    //   3087: invokevirtual getMessage : ()Ljava/lang/String;
    //   3090: invokestatic escribeArchivo : (Ljava/lang/String;Ljava/lang/String;Ljava/lang/String;)V
    //   3093: aload #11
    //   3095: ifnull -> 3121
    //   3098: aload #11
    //   3100: invokevirtual close : ()V
    //   3103: goto -> 3121
    //   3106: astore #5
    //   3108: ldc 'Request Manager'
    //   3110: ldc_w 'error'
    //   3113: aload #5
    //   3115: invokevirtual getMessage : ()Ljava/lang/String;
    //   3118: invokestatic escribeArchivo : (Ljava/lang/String;Ljava/lang/String;Ljava/lang/String;)V
    //   3121: aload #10
    //   3123: ifnull -> 3149
    //   3126: aload #10
    //   3128: invokevirtual close : ()V
    //   3131: goto -> 3149
    //   3134: astore #5
    //   3136: ldc 'Request Manager'
    //   3138: ldc_w 'error'
    //   3141: aload #5
    //   3143: invokevirtual getMessage : ()Ljava/lang/String;
    //   3146: invokestatic escribeArchivo : (Ljava/lang/String;Ljava/lang/String;Ljava/lang/String;)V
    //   3149: aload #9
    //   3151: ifnull -> 3366
    //   3154: aload #9
    //   3156: invokevirtual disconnect : ()V
    //   3159: goto -> 3366
    //   3162: astore #5
    //   3164: aconst_null
    //   3165: astore #9
    //   3167: aconst_null
    //   3168: astore #10
    //   3170: aconst_null
    //   3171: astore #11
    //   3173: aload #5
    //   3175: astore #13
    //   3177: aload #8
    //   3179: astore #12
    //   3181: aload #12
    //   3183: astore #5
    //   3185: aload #9
    //   3187: astore #6
    //   3189: aload #10
    //   3191: astore #7
    //   3193: aload #11
    //   3195: astore #8
    //   3197: aload_0
    //   3198: ldc_w 'Error, socket timeout exception'
    //   3201: putfield respuesta : Ljava/lang/String;
    //   3204: aload #12
    //   3206: astore #5
    //   3208: aload #9
    //   3210: astore #6
    //   3212: aload #10
    //   3214: astore #7
    //   3216: aload #11
    //   3218: astore #8
    //   3220: aload_0
    //   3221: iconst_m1
    //   3222: putfield responseCode : I
    //   3225: aload #12
    //   3227: astore #5
    //   3229: aload #9
    //   3231: astore #6
    //   3233: aload #10
    //   3235: astore #7
    //   3237: aload #11
    //   3239: astore #8
    //   3241: ldc 'Request Manager'
    //   3243: ldc_w 'error'
    //   3246: aload #13
    //   3248: invokevirtual getMessage : ()Ljava/lang/String;
    //   3251: invokestatic escribeArchivo : (Ljava/lang/String;Ljava/lang/String;Ljava/lang/String;)V
    //   3254: aload #12
    //   3256: ifnull -> 3282
    //   3259: aload #12
    //   3261: invokevirtual close : ()V
    //   3264: goto -> 3282
    //   3267: astore #5
    //   3269: ldc 'Request Manager'
    //   3271: ldc_w 'error'
    //   3274: aload #5
    //   3276: invokevirtual getMessage : ()Ljava/lang/String;
    //   3279: invokestatic escribeArchivo : (Ljava/lang/String;Ljava/lang/String;Ljava/lang/String;)V
    //   3282: aload #11
    //   3284: ifnull -> 3310
    //   3287: aload #11
    //   3289: invokevirtual close : ()V
    //   3292: goto -> 3310
    //   3295: astore #5
    //   3297: ldc 'Request Manager'
    //   3299: ldc_w 'error'
    //   3302: aload #5
    //   3304: invokevirtual getMessage : ()Ljava/lang/String;
    //   3307: invokestatic escribeArchivo : (Ljava/lang/String;Ljava/lang/String;Ljava/lang/String;)V
    //   3310: aload #10
    //   3312: ifnull -> 3338
    //   3315: aload #10
    //   3317: invokevirtual close : ()V
    //   3320: goto -> 3338
    //   3323: astore #5
    //   3325: ldc 'Request Manager'
    //   3327: ldc_w 'error'
    //   3330: aload #5
    //   3332: invokevirtual getMessage : ()Ljava/lang/String;
    //   3335: invokestatic escribeArchivo : (Ljava/lang/String;Ljava/lang/String;Ljava/lang/String;)V
    //   3338: aload #9
    //   3340: ifnull -> 3366
    //   3343: aload #9
    //   3345: invokevirtual disconnect : ()V
    //   3348: goto -> 3366
    //   3351: astore #5
    //   3353: ldc 'Request Manager'
    //   3355: ldc_w 'error'
    //   3358: aload #5
    //   3360: invokevirtual getMessage : ()Ljava/lang/String;
    //   3363: invokestatic escribeArchivo : (Ljava/lang/String;Ljava/lang/String;Ljava/lang/String;)V
    //   3366: ldc 'Request Manager'
    //   3368: ldc_w 'RESULTADO POST'
    //   3371: aload_0
    //   3372: getfield respuesta : Ljava/lang/String;
    //   3375: invokestatic escribeArchivo : (Ljava/lang/String;Ljava/lang/String;Ljava/lang/String;)V
    //   3378: aload_0
    //   3379: getfield _onPostExecuteListener : Lcom/roadtrack/onstar/BO/RequestManager$OnPostExecuteListener;
    //   3382: astore #5
    //   3384: aload #5
    //   3386: ifnull -> 3404
    //   3389: aload #5
    //   3391: aload_0
    //   3392: getfield respuesta : Ljava/lang/String;
    //   3395: aload_0
    //   3396: getfield responseCode : I
    //   3399: invokeinterface onPostExecuteListener : (Ljava/lang/String;I)V
    //   3404: return
    //   3405: astore #9
    //   3407: aload #8
    //   3409: astore #11
    //   3411: aload #7
    //   3413: astore #8
    //   3415: aload #5
    //   3417: astore #10
    //   3419: aload #10
    //   3421: ifnull -> 3447
    //   3424: aload #10
    //   3426: invokevirtual close : ()V
    //   3429: goto -> 3447
    //   3432: astore #5
    //   3434: ldc 'Request Manager'
    //   3436: ldc_w 'error'
    //   3439: aload #5
    //   3441: invokevirtual getMessage : ()Ljava/lang/String;
    //   3444: invokestatic escribeArchivo : (Ljava/lang/String;Ljava/lang/String;Ljava/lang/String;)V
    //   3447: aload #11
    //   3449: ifnull -> 3475
    //   3452: aload #11
    //   3454: invokevirtual close : ()V
    //   3457: goto -> 3475
    //   3460: astore #5
    //   3462: ldc 'Request Manager'
    //   3464: ldc_w 'error'
    //   3467: aload #5
    //   3469: invokevirtual getMessage : ()Ljava/lang/String;
    //   3472: invokestatic escribeArchivo : (Ljava/lang/String;Ljava/lang/String;Ljava/lang/String;)V
    //   3475: aload #8
    //   3477: ifnull -> 3503
    //   3480: aload #8
    //   3482: invokevirtual close : ()V
    //   3485: goto -> 3503
    //   3488: astore #5
    //   3490: ldc 'Request Manager'
    //   3492: ldc_w 'error'
    //   3495: aload #5
    //   3497: invokevirtual getMessage : ()Ljava/lang/String;
    //   3500: invokestatic escribeArchivo : (Ljava/lang/String;Ljava/lang/String;Ljava/lang/String;)V
    //   3503: aload #6
    //   3505: ifnull -> 3531
    //   3508: aload #6
    //   3510: invokevirtual disconnect : ()V
    //   3513: goto -> 3531
    //   3516: astore #5
    //   3518: ldc 'Request Manager'
    //   3520: ldc_w 'error'
    //   3523: aload #5
    //   3525: invokevirtual getMessage : ()Ljava/lang/String;
    //   3528: invokestatic escribeArchivo : (Ljava/lang/String;Ljava/lang/String;Ljava/lang/String;)V
    //   3531: aload #9
    //   3533: athrow
    // Exception table:
    //   from	to	target	type
    //   9	21	3162	java/net/SocketTimeoutException
    //   9	21	2978	java/lang/Exception
    //   9	21	2956	finally
    //   23	31	3162	java/net/SocketTimeoutException
    //   23	31	2978	java/lang/Exception
    //   23	31	2956	finally
    //   36	121	3162	java/net/SocketTimeoutException
    //   36	121	2978	java/lang/Exception
    //   36	121	2956	finally
    //   171	263	3162	java/net/SocketTimeoutException
    //   171	263	2978	java/lang/Exception
    //   171	263	2956	finally
    //   264	311	3162	java/net/SocketTimeoutException
    //   264	311	2978	java/lang/Exception
    //   264	311	2956	finally
    //   314	406	3162	java/net/SocketTimeoutException
    //   314	406	2978	java/lang/Exception
    //   314	406	2956	finally
    //   407	425	3162	java/net/SocketTimeoutException
    //   407	425	2978	java/lang/Exception
    //   407	425	2956	finally
    //   428	520	3162	java/net/SocketTimeoutException
    //   428	520	2978	java/lang/Exception
    //   428	520	2956	finally
    //   521	530	3162	java/net/SocketTimeoutException
    //   521	530	2978	java/lang/Exception
    //   521	530	2956	finally
    //   535	620	3162	java/net/SocketTimeoutException
    //   535	620	2978	java/lang/Exception
    //   535	620	2956	finally
    //   621	659	3162	java/net/SocketTimeoutException
    //   621	659	2978	java/lang/Exception
    //   621	659	2956	finally
    //   662	754	3162	java/net/SocketTimeoutException
    //   662	754	2978	java/lang/Exception
    //   662	754	2956	finally
    //   755	802	3162	java/net/SocketTimeoutException
    //   755	802	2978	java/lang/Exception
    //   755	802	2956	finally
    //   805	897	3162	java/net/SocketTimeoutException
    //   805	897	2978	java/lang/Exception
    //   805	897	2956	finally
    //   898	916	3162	java/net/SocketTimeoutException
    //   898	916	2978	java/lang/Exception
    //   898	916	2956	finally
    //   922	1014	3162	java/net/SocketTimeoutException
    //   922	1014	2978	java/lang/Exception
    //   922	1014	2956	finally
    //   1015	1024	3162	java/net/SocketTimeoutException
    //   1015	1024	2978	java/lang/Exception
    //   1015	1024	2956	finally
    //   1029	1114	3162	java/net/SocketTimeoutException
    //   1029	1114	2978	java/lang/Exception
    //   1029	1114	2956	finally
    //   1115	1153	3162	java/net/SocketTimeoutException
    //   1115	1153	2978	java/lang/Exception
    //   1115	1153	2956	finally
    //   1156	1248	3162	java/net/SocketTimeoutException
    //   1156	1248	2978	java/lang/Exception
    //   1156	1248	2956	finally
    //   1249	1258	3162	java/net/SocketTimeoutException
    //   1249	1258	2978	java/lang/Exception
    //   1249	1258	2956	finally
    //   1263	1348	3162	java/net/SocketTimeoutException
    //   1263	1348	2978	java/lang/Exception
    //   1263	1348	2956	finally
    //   1349	1387	3162	java/net/SocketTimeoutException
    //   1349	1387	2978	java/lang/Exception
    //   1349	1387	2956	finally
    //   1403	1488	3162	java/net/SocketTimeoutException
    //   1403	1488	2978	java/lang/Exception
    //   1403	1488	2956	finally
    //   1495	1521	2781	java/lang/Exception
    //   1495	1521	2956	finally
    //   1524	1535	2781	java/lang/Exception
    //   1524	1535	2956	finally
    //   1535	1545	3162	java/net/SocketTimeoutException
    //   1535	1545	2978	java/lang/Exception
    //   1535	1545	2956	finally
    //   1565	1575	2776	java/net/SocketTimeoutException
    //   1565	1575	2771	java/lang/Exception
    //   1565	1575	2758	finally
    //   1577	1589	2776	java/net/SocketTimeoutException
    //   1577	1589	2771	java/lang/Exception
    //   1577	1589	2758	finally
    //   1589	1611	2776	java/net/SocketTimeoutException
    //   1589	1611	2771	java/lang/Exception
    //   1589	1611	2758	finally
    //   1615	1632	2776	java/net/SocketTimeoutException
    //   1615	1632	2771	java/lang/Exception
    //   1615	1632	2758	finally
    //   1635	1652	2776	java/net/SocketTimeoutException
    //   1635	1652	2771	java/lang/Exception
    //   1635	1652	2758	finally
    //   1655	1665	2776	java/net/SocketTimeoutException
    //   1655	1665	2771	java/lang/Exception
    //   1655	1665	2758	finally
    //   1711	1756	2776	java/net/SocketTimeoutException
    //   1711	1756	2771	java/lang/Exception
    //   1711	1756	2758	finally
    //   1761	1781	2776	java/net/SocketTimeoutException
    //   1761	1781	2771	java/lang/Exception
    //   1761	1781	2758	finally
    //   1793	1800	2735	java/net/SocketTimeoutException
    //   1793	1800	2712	java/lang/Exception
    //   1793	1800	2681	finally
    //   1812	1817	2735	java/net/SocketTimeoutException
    //   1812	1817	2712	java/lang/Exception
    //   1812	1817	2681	finally
    //   1820	1878	2776	java/net/SocketTimeoutException
    //   1820	1878	2771	java/lang/Exception
    //   1820	1878	2758	finally
    //   1890	1897	2735	java/net/SocketTimeoutException
    //   1890	1897	2712	java/lang/Exception
    //   1890	1897	2681	finally
    //   1909	1914	2735	java/net/SocketTimeoutException
    //   1909	1914	2712	java/lang/Exception
    //   1909	1914	2681	finally
    //   1917	1962	2776	java/net/SocketTimeoutException
    //   1917	1962	2771	java/lang/Exception
    //   1917	1962	2758	finally
    //   1967	1987	2776	java/net/SocketTimeoutException
    //   1967	1987	2771	java/lang/Exception
    //   1967	1987	2758	finally
    //   1999	2006	2735	java/net/SocketTimeoutException
    //   1999	2006	2712	java/lang/Exception
    //   1999	2006	2681	finally
    //   2018	2023	2735	java/net/SocketTimeoutException
    //   2018	2023	2712	java/lang/Exception
    //   2018	2023	2681	finally
    //   2026	2058	2776	java/net/SocketTimeoutException
    //   2026	2058	2771	java/lang/Exception
    //   2026	2058	2758	finally
    //   2061	2132	2776	java/net/SocketTimeoutException
    //   2061	2132	2771	java/lang/Exception
    //   2061	2132	2758	finally
    //   2144	2151	2735	java/net/SocketTimeoutException
    //   2144	2151	2712	java/lang/Exception
    //   2144	2151	2681	finally
    //   2163	2168	2735	java/net/SocketTimeoutException
    //   2163	2168	2712	java/lang/Exception
    //   2163	2168	2681	finally
    //   2171	2262	2776	java/net/SocketTimeoutException
    //   2171	2262	2771	java/lang/Exception
    //   2171	2262	2758	finally
    //   2274	2281	2735	java/net/SocketTimeoutException
    //   2274	2281	2712	java/lang/Exception
    //   2274	2281	2681	finally
    //   2293	2298	2735	java/net/SocketTimeoutException
    //   2293	2298	2712	java/lang/Exception
    //   2293	2298	2681	finally
    //   2316	2325	2735	java/net/SocketTimeoutException
    //   2316	2325	2712	java/lang/Exception
    //   2316	2325	2681	finally
    //   2337	2342	2735	java/net/SocketTimeoutException
    //   2337	2342	2712	java/lang/Exception
    //   2337	2342	2681	finally
    //   2354	2364	2735	java/net/SocketTimeoutException
    //   2354	2364	2712	java/lang/Exception
    //   2354	2364	2681	finally
    //   2364	2376	2665	java/net/SocketTimeoutException
    //   2364	2376	2649	java/lang/Exception
    //   2364	2376	2629	finally
    //   2376	2383	2489	java/lang/Exception
    //   2376	2383	2472	finally
    //   2388	2398	2489	java/lang/Exception
    //   2388	2398	2472	finally
    //   2401	2421	2489	java/lang/Exception
    //   2401	2421	2472	finally
    //   2426	2441	2489	java/lang/Exception
    //   2426	2441	2472	finally
    //   2444	2455	2489	java/lang/Exception
    //   2444	2455	2472	finally
    //   2458	2469	2489	java/lang/Exception
    //   2458	2469	2472	finally
    //   2491	2516	2616	java/net/SocketTimeoutException
    //   2491	2516	2603	java/lang/Exception
    //   2491	2516	2472	finally
    //   2521	2526	2529	java/lang/Exception
    //   2544	2549	2552	java/lang/Exception
    //   2567	2572	2575	java/lang/Exception
    //   2595	2600	3351	java/lang/Exception
    //   2783	2869	3162	java/net/SocketTimeoutException
    //   2783	2869	2978	java/lang/Exception
    //   2783	2869	2956	finally
    //   2870	2955	3162	java/net/SocketTimeoutException
    //   2870	2955	2978	java/lang/Exception
    //   2870	2955	2956	finally
    //   3009	3015	3405	finally
    //   3031	3036	3405	finally
    //   3052	3065	3405	finally
    //   3070	3075	3078	java/lang/Exception
    //   3098	3103	3106	java/lang/Exception
    //   3126	3131	3134	java/lang/Exception
    //   3154	3159	3351	java/lang/Exception
    //   3197	3204	3405	finally
    //   3220	3225	3405	finally
    //   3241	3254	3405	finally
    //   3259	3264	3267	java/lang/Exception
    //   3287	3292	3295	java/lang/Exception
    //   3315	3320	3323	java/lang/Exception
    //   3343	3348	3351	java/lang/Exception
    //   3424	3429	3432	java/lang/Exception
    //   3452	3457	3460	java/lang/Exception
    //   3480	3485	3488	java/lang/Exception
    //   3508	3513	3516	java/lang/Exception
  }
  
  public void setOnExecuteHttpPostAsyncListener(OnExecuteHttpPostAsyncListenerURL paramOnExecuteHttpPostAsyncListenerURL) {}
  
  public void setOnPostExecuteListener(OnPostExecuteListener paramOnPostExecuteListener) {
    this._onPostExecuteListener = paramOnPostExecuteListener;
  }
  
  public static interface OnExecuteHttpPostAsyncListenerURL {}
  
  public static interface OnPostExecuteListener {
    void onPostExecuteListener(String param1String, int param1Int);
  }
}


/* Location:              /home/andrelcol/Desktop/securityDebt/onstar/meuProjeto.jar!/com/roadtrack/onstar/BO/RequestManager.class
 * Java compiler version: 6 (50.0)
 * JD-Core Version:       1.1.3
 */