package com.google.android.gms.measurement.internal;

import android.content.ServiceConnection;
import com.google.android.gms.internal.measurement.zzu;

final class zzbl implements Runnable {
  private final zzu zzaod;
  
  private final ServiceConnection zzaoe;
  
  private final zzbk zzaof;
  
  zzbl(zzbk paramzzbk, zzu paramzzu, ServiceConnection paramServiceConnection) {}
  
  public final void run() {
    // Byte code:
    //   0: aload_0
    //   1: getfield zzaof : Lcom/google/android/gms/measurement/internal/zzbk;
    //   4: astore #6
    //   6: aload #6
    //   8: getfield zzaoc : Lcom/google/android/gms/measurement/internal/zzbj;
    //   11: astore #7
    //   13: aload #6
    //   15: invokestatic zza : (Lcom/google/android/gms/measurement/internal/zzbk;)Ljava/lang/String;
    //   18: astore #6
    //   20: aload_0
    //   21: getfield zzaod : Lcom/google/android/gms/internal/measurement/zzu;
    //   24: astore #9
    //   26: aload_0
    //   27: getfield zzaoe : Landroid/content/ServiceConnection;
    //   30: astore #8
    //   32: aload #7
    //   34: aload #6
    //   36: aload #9
    //   38: invokevirtual zza : (Ljava/lang/String;Lcom/google/android/gms/internal/measurement/zzu;)Landroid/os/Bundle;
    //   41: astore #9
    //   43: aload #7
    //   45: getfield zzada : Lcom/google/android/gms/measurement/internal/zzbw;
    //   48: invokevirtual zzgs : ()Lcom/google/android/gms/measurement/internal/zzbr;
    //   51: invokevirtual zzaf : ()V
    //   54: aload #9
    //   56: ifnull -> 453
    //   59: aload #9
    //   61: ldc 'install_begin_timestamp_seconds'
    //   63: lconst_0
    //   64: invokevirtual getLong : (Ljava/lang/String;J)J
    //   67: ldc2_w 1000
    //   70: lmul
    //   71: lstore #4
    //   73: lload #4
    //   75: lconst_0
    //   76: lcmp
    //   77: ifne -> 99
    //   80: aload #7
    //   82: getfield zzada : Lcom/google/android/gms/measurement/internal/zzbw;
    //   85: invokevirtual zzgt : ()Lcom/google/android/gms/measurement/internal/zzas;
    //   88: invokevirtual zzjg : ()Lcom/google/android/gms/measurement/internal/zzau;
    //   91: ldc 'Service response is missing Install Referrer install timestamp'
    //   93: invokevirtual zzby : (Ljava/lang/String;)V
    //   96: goto -> 453
    //   99: aload #9
    //   101: ldc 'install_referrer'
    //   103: invokevirtual getString : (Ljava/lang/String;)Ljava/lang/String;
    //   106: astore #6
    //   108: aload #6
    //   110: ifnull -> 437
    //   113: aload #6
    //   115: invokevirtual isEmpty : ()Z
    //   118: ifeq -> 124
    //   121: goto -> 437
    //   124: aload #7
    //   126: getfield zzada : Lcom/google/android/gms/measurement/internal/zzbw;
    //   129: invokevirtual zzgt : ()Lcom/google/android/gms/measurement/internal/zzas;
    //   132: invokevirtual zzjo : ()Lcom/google/android/gms/measurement/internal/zzau;
    //   135: ldc 'InstallReferrer API result'
    //   137: aload #6
    //   139: invokevirtual zzg : (Ljava/lang/String;Ljava/lang/Object;)V
    //   142: aload #7
    //   144: getfield zzada : Lcom/google/android/gms/measurement/internal/zzbw;
    //   147: invokevirtual zzgr : ()Lcom/google/android/gms/measurement/internal/zzfx;
    //   150: astore #10
    //   152: aload #6
    //   154: invokestatic valueOf : (Ljava/lang/Object;)Ljava/lang/String;
    //   157: astore #6
    //   159: aload #6
    //   161: invokevirtual length : ()I
    //   164: ifeq -> 179
    //   167: ldc '?'
    //   169: aload #6
    //   171: invokevirtual concat : (Ljava/lang/String;)Ljava/lang/String;
    //   174: astore #6
    //   176: goto -> 190
    //   179: new java/lang/String
    //   182: dup
    //   183: ldc '?'
    //   185: invokespecial <init> : (Ljava/lang/String;)V
    //   188: astore #6
    //   190: aload #10
    //   192: aload #6
    //   194: invokestatic parse : (Ljava/lang/String;)Landroid/net/Uri;
    //   197: invokevirtual zza : (Landroid/net/Uri;)Landroid/os/Bundle;
    //   200: astore #6
    //   202: aload #6
    //   204: ifnonnull -> 226
    //   207: aload #7
    //   209: getfield zzada : Lcom/google/android/gms/measurement/internal/zzbw;
    //   212: invokevirtual zzgt : ()Lcom/google/android/gms/measurement/internal/zzas;
    //   215: invokevirtual zzjg : ()Lcom/google/android/gms/measurement/internal/zzau;
    //   218: ldc 'No campaign params defined in install referrer result'
    //   220: invokevirtual zzby : (Ljava/lang/String;)V
    //   223: goto -> 453
    //   226: aload #6
    //   228: ldc 'medium'
    //   230: invokevirtual getString : (Ljava/lang/String;)Ljava/lang/String;
    //   233: astore #10
    //   235: aload #10
    //   237: ifnull -> 265
    //   240: ldc '(not set)'
    //   242: aload #10
    //   244: invokevirtual equalsIgnoreCase : (Ljava/lang/String;)Z
    //   247: ifne -> 265
    //   250: ldc 'organic'
    //   252: aload #10
    //   254: invokevirtual equalsIgnoreCase : (Ljava/lang/String;)Z
    //   257: ifne -> 265
    //   260: iconst_1
    //   261: istore_1
    //   262: goto -> 267
    //   265: iconst_0
    //   266: istore_1
    //   267: iload_1
    //   268: ifeq -> 317
    //   271: aload #9
    //   273: ldc 'referrer_click_timestamp_seconds'
    //   275: lconst_0
    //   276: invokevirtual getLong : (Ljava/lang/String;J)J
    //   279: ldc2_w 1000
    //   282: lmul
    //   283: lstore_2
    //   284: lload_2
    //   285: lconst_0
    //   286: lcmp
    //   287: ifne -> 309
    //   290: aload #7
    //   292: getfield zzada : Lcom/google/android/gms/measurement/internal/zzbw;
    //   295: invokevirtual zzgt : ()Lcom/google/android/gms/measurement/internal/zzas;
    //   298: invokevirtual zzjg : ()Lcom/google/android/gms/measurement/internal/zzau;
    //   301: ldc 'Install Referrer is missing click timestamp for ad campaign'
    //   303: invokevirtual zzby : (Ljava/lang/String;)V
    //   306: goto -> 453
    //   309: aload #6
    //   311: ldc 'click_timestamp'
    //   313: lload_2
    //   314: invokevirtual putLong : (Ljava/lang/String;J)V
    //   317: lload #4
    //   319: aload #7
    //   321: getfield zzada : Lcom/google/android/gms/measurement/internal/zzbw;
    //   324: invokevirtual zzgu : ()Lcom/google/android/gms/measurement/internal/zzbd;
    //   327: getfield zzani : Lcom/google/android/gms/measurement/internal/zzbg;
    //   330: invokevirtual get : ()J
    //   333: lcmp
    //   334: ifne -> 365
    //   337: aload #7
    //   339: getfield zzada : Lcom/google/android/gms/measurement/internal/zzbw;
    //   342: invokevirtual zzgw : ()Lcom/google/android/gms/measurement/internal/zzn;
    //   345: pop
    //   346: aload #7
    //   348: getfield zzada : Lcom/google/android/gms/measurement/internal/zzbw;
    //   351: invokevirtual zzgt : ()Lcom/google/android/gms/measurement/internal/zzas;
    //   354: invokevirtual zzjo : ()Lcom/google/android/gms/measurement/internal/zzau;
    //   357: ldc 'Campaign has already been logged'
    //   359: invokevirtual zzby : (Ljava/lang/String;)V
    //   362: goto -> 453
    //   365: aload #7
    //   367: getfield zzada : Lcom/google/android/gms/measurement/internal/zzbw;
    //   370: invokevirtual zzgu : ()Lcom/google/android/gms/measurement/internal/zzbd;
    //   373: getfield zzani : Lcom/google/android/gms/measurement/internal/zzbg;
    //   376: lload #4
    //   378: invokevirtual set : (J)V
    //   381: aload #7
    //   383: getfield zzada : Lcom/google/android/gms/measurement/internal/zzbw;
    //   386: invokevirtual zzgw : ()Lcom/google/android/gms/measurement/internal/zzn;
    //   389: pop
    //   390: aload #7
    //   392: getfield zzada : Lcom/google/android/gms/measurement/internal/zzbw;
    //   395: invokevirtual zzgt : ()Lcom/google/android/gms/measurement/internal/zzas;
    //   398: invokevirtual zzjo : ()Lcom/google/android/gms/measurement/internal/zzau;
    //   401: ldc 'Logging Install Referrer campaign from sdk with '
    //   403: ldc 'referrer API'
    //   405: invokevirtual zzg : (Ljava/lang/String;Ljava/lang/Object;)V
    //   408: aload #6
    //   410: ldc '_cis'
    //   412: ldc 'referrer API'
    //   414: invokevirtual putString : (Ljava/lang/String;Ljava/lang/String;)V
    //   417: aload #7
    //   419: getfield zzada : Lcom/google/android/gms/measurement/internal/zzbw;
    //   422: invokevirtual zzgj : ()Lcom/google/android/gms/measurement/internal/zzda;
    //   425: ldc 'auto'
    //   427: ldc '_cmp'
    //   429: aload #6
    //   431: invokevirtual logEvent : (Ljava/lang/String;Ljava/lang/String;Landroid/os/Bundle;)V
    //   434: goto -> 453
    //   437: aload #7
    //   439: getfield zzada : Lcom/google/android/gms/measurement/internal/zzbw;
    //   442: invokevirtual zzgt : ()Lcom/google/android/gms/measurement/internal/zzas;
    //   445: invokevirtual zzjg : ()Lcom/google/android/gms/measurement/internal/zzau;
    //   448: ldc 'No referrer defined in install referrer response'
    //   450: invokevirtual zzby : (Ljava/lang/String;)V
    //   453: aload #8
    //   455: ifnull -> 474
    //   458: invokestatic getInstance : ()Lcom/google/android/gms/common/stats/ConnectionTracker;
    //   461: aload #7
    //   463: getfield zzada : Lcom/google/android/gms/measurement/internal/zzbw;
    //   466: invokevirtual getContext : ()Landroid/content/Context;
    //   469: aload #8
    //   471: invokevirtual unbindService : (Landroid/content/Context;Landroid/content/ServiceConnection;)V
    //   474: return
  }
}


/* Location:              /home/andrelcol/Desktop/securityDebt/onstar/meuProjeto.jar!/com/google/android/gms/measurement/internal/zzbl.class
 * Java compiler version: 6 (50.0)
 * JD-Core Version:       1.1.3
 */