package com.google.android.gms.measurement.internal;

final class zzdz implements Runnable {
  private final boolean zzarz;
  
  private final zzdx zzasa;
  
  private final zzdx zzasb;
  
  private final zzdy zzasc;
  
  zzdz(zzdy paramzzdy, boolean paramBoolean, zzdx paramzzdx1, zzdx paramzzdx2) {}
  
  public final void run() {
    // Byte code:
    //   0: aload_0
    //   1: getfield zzasc : Lcom/google/android/gms/measurement/internal/zzdy;
    //   4: invokevirtual zzgv : ()Lcom/google/android/gms/measurement/internal/zzq;
    //   7: aload_0
    //   8: getfield zzasc : Lcom/google/android/gms/measurement/internal/zzdy;
    //   11: invokevirtual zzgk : ()Lcom/google/android/gms/measurement/internal/zzam;
    //   14: invokevirtual zzal : ()Ljava/lang/String;
    //   17: invokevirtual zzbk : (Ljava/lang/String;)Z
    //   20: istore #6
    //   22: iconst_0
    //   23: istore_3
    //   24: iload #6
    //   26: ifeq -> 81
    //   29: aload_0
    //   30: getfield zzarz : Z
    //   33: ifeq -> 51
    //   36: aload_0
    //   37: getfield zzasc : Lcom/google/android/gms/measurement/internal/zzdy;
    //   40: getfield zzart : Lcom/google/android/gms/measurement/internal/zzdx;
    //   43: ifnull -> 51
    //   46: iconst_1
    //   47: istore_1
    //   48: goto -> 53
    //   51: iconst_0
    //   52: istore_1
    //   53: iload_1
    //   54: istore_2
    //   55: iload_1
    //   56: ifeq -> 116
    //   59: aload_0
    //   60: getfield zzasc : Lcom/google/android/gms/measurement/internal/zzdy;
    //   63: astore #7
    //   65: aload #7
    //   67: aload #7
    //   69: getfield zzart : Lcom/google/android/gms/measurement/internal/zzdx;
    //   72: iconst_1
    //   73: invokestatic zza : (Lcom/google/android/gms/measurement/internal/zzdy;Lcom/google/android/gms/measurement/internal/zzdx;Z)V
    //   76: iload_1
    //   77: istore_2
    //   78: goto -> 116
    //   81: aload_0
    //   82: getfield zzarz : Z
    //   85: ifeq -> 114
    //   88: aload_0
    //   89: getfield zzasc : Lcom/google/android/gms/measurement/internal/zzdy;
    //   92: astore #7
    //   94: aload #7
    //   96: getfield zzart : Lcom/google/android/gms/measurement/internal/zzdx;
    //   99: astore #8
    //   101: aload #8
    //   103: ifnull -> 114
    //   106: aload #7
    //   108: aload #8
    //   110: iconst_1
    //   111: invokestatic zza : (Lcom/google/android/gms/measurement/internal/zzdy;Lcom/google/android/gms/measurement/internal/zzdx;Z)V
    //   114: iconst_0
    //   115: istore_2
    //   116: aload_0
    //   117: getfield zzasa : Lcom/google/android/gms/measurement/internal/zzdx;
    //   120: astore #8
    //   122: aload #8
    //   124: ifnull -> 189
    //   127: aload #8
    //   129: getfield zzarr : J
    //   132: lstore #4
    //   134: aload_0
    //   135: getfield zzasb : Lcom/google/android/gms/measurement/internal/zzdx;
    //   138: astore #7
    //   140: lload #4
    //   142: aload #7
    //   144: getfield zzarr : J
    //   147: lcmp
    //   148: ifne -> 189
    //   151: aload #8
    //   153: getfield zzarq : Ljava/lang/String;
    //   156: aload #7
    //   158: getfield zzarq : Ljava/lang/String;
    //   161: invokestatic zzv : (Ljava/lang/String;Ljava/lang/String;)Z
    //   164: ifeq -> 189
    //   167: iload_3
    //   168: istore_1
    //   169: aload_0
    //   170: getfield zzasa : Lcom/google/android/gms/measurement/internal/zzdx;
    //   173: getfield zzuw : Ljava/lang/String;
    //   176: aload_0
    //   177: getfield zzasb : Lcom/google/android/gms/measurement/internal/zzdx;
    //   180: getfield zzuw : Ljava/lang/String;
    //   183: invokestatic zzv : (Ljava/lang/String;Ljava/lang/String;)Z
    //   186: ifne -> 191
    //   189: iconst_1
    //   190: istore_1
    //   191: iload_1
    //   192: ifeq -> 350
    //   195: new android/os/Bundle
    //   198: dup
    //   199: invokespecial <init> : ()V
    //   202: astore #7
    //   204: aload_0
    //   205: getfield zzasb : Lcom/google/android/gms/measurement/internal/zzdx;
    //   208: aload #7
    //   210: iconst_1
    //   211: invokestatic zza : (Lcom/google/android/gms/measurement/internal/zzdx;Landroid/os/Bundle;Z)V
    //   214: aload_0
    //   215: getfield zzasa : Lcom/google/android/gms/measurement/internal/zzdx;
    //   218: astore #8
    //   220: aload #8
    //   222: ifnull -> 274
    //   225: aload #8
    //   227: getfield zzuw : Ljava/lang/String;
    //   230: astore #8
    //   232: aload #8
    //   234: ifnull -> 246
    //   237: aload #7
    //   239: ldc '_pn'
    //   241: aload #8
    //   243: invokevirtual putString : (Ljava/lang/String;Ljava/lang/String;)V
    //   246: aload #7
    //   248: ldc '_pc'
    //   250: aload_0
    //   251: getfield zzasa : Lcom/google/android/gms/measurement/internal/zzdx;
    //   254: getfield zzarq : Ljava/lang/String;
    //   257: invokevirtual putString : (Ljava/lang/String;Ljava/lang/String;)V
    //   260: aload #7
    //   262: ldc '_pi'
    //   264: aload_0
    //   265: getfield zzasa : Lcom/google/android/gms/measurement/internal/zzdx;
    //   268: getfield zzarr : J
    //   271: invokevirtual putLong : (Ljava/lang/String;J)V
    //   274: aload_0
    //   275: getfield zzasc : Lcom/google/android/gms/measurement/internal/zzdy;
    //   278: invokevirtual zzgv : ()Lcom/google/android/gms/measurement/internal/zzq;
    //   281: aload_0
    //   282: getfield zzasc : Lcom/google/android/gms/measurement/internal/zzdy;
    //   285: invokevirtual zzgk : ()Lcom/google/android/gms/measurement/internal/zzam;
    //   288: invokevirtual zzal : ()Ljava/lang/String;
    //   291: invokevirtual zzbk : (Ljava/lang/String;)Z
    //   294: ifeq -> 334
    //   297: iload_2
    //   298: ifeq -> 334
    //   301: aload_0
    //   302: getfield zzasc : Lcom/google/android/gms/measurement/internal/zzdy;
    //   305: invokevirtual zzgo : ()Lcom/google/android/gms/measurement/internal/zzfd;
    //   308: invokevirtual zzlp : ()J
    //   311: lstore #4
    //   313: lload #4
    //   315: lconst_0
    //   316: lcmp
    //   317: ifle -> 334
    //   320: aload_0
    //   321: getfield zzasc : Lcom/google/android/gms/measurement/internal/zzdy;
    //   324: invokevirtual zzgr : ()Lcom/google/android/gms/measurement/internal/zzfx;
    //   327: aload #7
    //   329: lload #4
    //   331: invokevirtual zza : (Landroid/os/Bundle;J)V
    //   334: aload_0
    //   335: getfield zzasc : Lcom/google/android/gms/measurement/internal/zzdy;
    //   338: invokevirtual zzgj : ()Lcom/google/android/gms/measurement/internal/zzda;
    //   341: ldc 'auto'
    //   343: ldc '_vs'
    //   345: aload #7
    //   347: invokevirtual zza : (Ljava/lang/String;Ljava/lang/String;Landroid/os/Bundle;)V
    //   350: aload_0
    //   351: getfield zzasc : Lcom/google/android/gms/measurement/internal/zzdy;
    //   354: astore #7
    //   356: aload #7
    //   358: aload_0
    //   359: getfield zzasb : Lcom/google/android/gms/measurement/internal/zzdx;
    //   362: putfield zzart : Lcom/google/android/gms/measurement/internal/zzdx;
    //   365: aload #7
    //   367: invokevirtual zzgl : ()Lcom/google/android/gms/measurement/internal/zzeb;
    //   370: aload_0
    //   371: getfield zzasb : Lcom/google/android/gms/measurement/internal/zzdx;
    //   374: invokevirtual zza : (Lcom/google/android/gms/measurement/internal/zzdx;)V
    //   377: return
  }
}


/* Location:              /home/andrelcol/Desktop/securityDebt/onstar/meuProjeto.jar!/com/google/android/gms/measurement/internal/zzdz.class
 * Java compiler version: 6 (50.0)
 * JD-Core Version:       1.1.3
 */