package com.google.android.gms.measurement.internal;

import android.text.TextUtils;
import androidx.collection.ArrayMap;
import com.google.android.gms.common.internal.Preconditions;
import com.google.android.gms.internal.measurement.zzfj;
import com.google.android.gms.internal.measurement.zzfk;
import com.google.android.gms.internal.measurement.zzfl;
import com.google.android.gms.internal.measurement.zzfm;
import com.google.android.gms.internal.measurement.zzfn;
import com.google.android.gms.internal.measurement.zzfr;
import com.google.android.gms.internal.measurement.zzfs;
import com.google.android.gms.internal.measurement.zzft;
import com.google.android.gms.internal.measurement.zzfu;
import com.google.android.gms.internal.measurement.zzfz;
import java.math.BigDecimal;
import java.util.ArrayList;
import java.util.Arrays;
import java.util.HashSet;
import java.util.List;
import java.util.Locale;
import java.util.Map;
import java.util.regex.Pattern;
import java.util.regex.PatternSyntaxException;

final class zzm extends zzfm {
  zzm(zzfn paramzzfn) {
    super(paramzzfn);
  }
  
  private final Boolean zza(double paramDouble, zzfl paramzzfl) {
    try {
      BigDecimal bigDecimal = new BigDecimal();
      this(paramDouble);
      return zza(bigDecimal, paramzzfl, Math.ulp(paramDouble));
    } catch (NumberFormatException numberFormatException) {
      return null;
    } 
  }
  
  private final Boolean zza(long paramLong, zzfl paramzzfl) {
    try {
      BigDecimal bigDecimal = new BigDecimal();
      this(paramLong);
      return zza(bigDecimal, paramzzfl, 0.0D);
    } catch (NumberFormatException numberFormatException) {
      return null;
    } 
  }
  
  private final Boolean zza(zzfj paramzzfj, String paramString, zzfu[] paramArrayOfzzfu, long paramLong) {
    zzfl zzfl = paramzzfj.zzavq;
    boolean bool = false;
    Boolean bool1 = Boolean.valueOf(false);
    if (zzfl != null) {
      Boolean bool2 = zza(paramLong, zzfl);
      if (bool2 == null)
        return null; 
      if (!bool2.booleanValue())
        return bool1; 
    } 
    HashSet<String> hashSet = new HashSet();
    for (zzfk zzfk : paramzzfj.zzavo) {
      if (TextUtils.isEmpty(zzfk.zzavv)) {
        zzgt().zzjj().zzg("null or empty param name in filter. event", zzgq().zzbt(paramString));
        return null;
      } 
      hashSet.add(zzfk.zzavv);
    } 
    ArrayMap<String, Long> arrayMap = new ArrayMap();
    int i = paramArrayOfzzfu.length;
    byte b;
    for (b = 0; b < i; b++) {
      zzfu zzfu1 = paramArrayOfzzfu[b];
      if (hashSet.contains(zzfu1.name)) {
        Long long_ = zzfu1.zzaxg;
        if (long_ != null) {
          arrayMap.put(zzfu1.name, long_);
        } else {
          Double double_ = zzfu1.zzaup;
          if (double_ != null) {
            arrayMap.put(zzfu1.name, double_);
          } else {
            String str = zzfu1.zzamn;
            if (str != null) {
              arrayMap.put(zzfu1.name, str);
            } else {
              zzgt().zzjj().zze("Unknown value for param. event, param", zzgq().zzbt(paramString), zzgq().zzbu(zzfu1.name));
              return null;
            } 
          } 
        } 
      } 
    } 
    zzfk[] arrayOfZzfk = paramzzfj.zzavo;
    i = arrayOfZzfk.length;
    for (b = bool; b < i; b++) {
      Boolean bool2;
      zzfk zzfk = arrayOfZzfk[b];
      boolean bool3 = Boolean.TRUE.equals(zzfk.zzavu);
      String str = zzfk.zzavv;
      if (TextUtils.isEmpty(str)) {
        zzgt().zzjj().zzg("Event has empty param name. event", zzgq().zzbt(paramString));
        return null;
      } 
      Long long_ = (Long)arrayMap.get(str);
      if (long_ instanceof Long) {
        if (zzfk.zzavt == null) {
          zzgt().zzjj().zze("No number filter for long param. event, param", zzgq().zzbt(paramString), zzgq().zzbu(str));
          return null;
        } 
        bool2 = zza(((Long)long_).longValue(), zzfk.zzavt);
        if (bool2 == null)
          return null; 
        if ((true ^ bool2.booleanValue() ^ bool3) != 0)
          return bool1; 
      } else if (long_ instanceof Double) {
        if (((zzfk)bool2).zzavt == null) {
          zzgt().zzjj().zze("No number filter for double param. event, param", zzgq().zzbt(paramString), zzgq().zzbu(str));
          return null;
        } 
        bool2 = zza(((Double)long_).doubleValue(), ((zzfk)bool2).zzavt);
        if (bool2 == null)
          return null; 
        if ((true ^ bool2.booleanValue() ^ bool3) != 0)
          return bool1; 
      } else if (long_ instanceof String) {
        zzfn zzfn = ((zzfk)bool2).zzavs;
        if (zzfn != null) {
          bool2 = zza((String)long_, zzfn);
        } else if (((zzfk)bool2).zzavt != null) {
          String str1 = (String)long_;
          if (zzft.zzcs(str1)) {
            bool2 = zza(str1, ((zzfk)bool2).zzavt);
          } else {
            zzgt().zzjj().zze("Invalid param value for number filter. event, param", zzgq().zzbt(paramString), zzgq().zzbu(str));
            return null;
          } 
        } else {
          zzgt().zzjj().zze("No filter for String param. event, param", zzgq().zzbt(paramString), zzgq().zzbu(str));
          return null;
        } 
        if (bool2 == null)
          return null; 
        if ((true ^ bool2.booleanValue() ^ bool3) != 0)
          return bool1; 
      } else {
        if (long_ == null) {
          zzgt().zzjo().zze("Missing param for filter. event, param", zzgq().zzbt(paramString), zzgq().zzbu(str));
          return bool1;
        } 
        zzgt().zzjj().zze("Unknown param type. event, param", zzgq().zzbt(paramString), zzgq().zzbu(str));
        return null;
      } 
    } 
    return Boolean.valueOf(true);
  }
  
  private final Boolean zza(zzfm paramzzfm, zzfz paramzzfz) {
    zzfk zzfk = paramzzfm.zzawd;
    if (zzfk == null) {
      zzgt().zzjj().zzg("Missing property filter. property", zzgq().zzbv(paramzzfz.name));
      return null;
    } 
    boolean bool = Boolean.TRUE.equals(zzfk.zzavu);
    Long long_ = paramzzfz.zzaxg;
    if (long_ != null) {
      if (zzfk.zzavt == null) {
        zzgt().zzjj().zzg("No number filter for long property. property", zzgq().zzbv(paramzzfz.name));
        return null;
      } 
      return zza(zza(long_.longValue(), zzfk.zzavt), bool);
    } 
    Double double_ = paramzzfz.zzaup;
    if (double_ != null) {
      if (zzfk.zzavt == null) {
        zzgt().zzjj().zzg("No number filter for double property. property", zzgq().zzbv(paramzzfz.name));
        return null;
      } 
      return zza(zza(double_.doubleValue(), zzfk.zzavt), bool);
    } 
    String str = paramzzfz.zzamn;
    if (str != null) {
      zzfn zzfn = zzfk.zzavs;
      if (zzfn == null) {
        if (zzfk.zzavt == null) {
          zzgt().zzjj().zzg("No string or number filter defined. property", zzgq().zzbv(paramzzfz.name));
        } else {
          if (zzft.zzcs(str))
            return zza(zza(paramzzfz.zzamn, zzfk.zzavt), bool); 
          zzgt().zzjj().zze("Invalid user property value for Numeric number filter. property, value", zzgq().zzbv(paramzzfz.name), paramzzfz.zzamn);
        } 
        return null;
      } 
      return zza(zza(str, zzfn), bool);
    } 
    zzgt().zzjj().zzg("User property has no value, property", zzgq().zzbv(paramzzfz.name));
    return null;
  }
  
  private static Boolean zza(Boolean paramBoolean, boolean paramBoolean1) {
    return (paramBoolean == null) ? null : Boolean.valueOf(paramBoolean.booleanValue() ^ paramBoolean1);
  }
  
  private final Boolean zza(String paramString1, int paramInt, boolean paramBoolean, String paramString2, List<String> paramList, String paramString3) {
    if (paramString1 == null)
      return null; 
    if (paramInt == 6) {
      if (paramList == null || paramList.size() == 0)
        return null; 
    } else if (paramString2 == null) {
      return null;
    } 
    String str = paramString1;
    if (!paramBoolean)
      if (paramInt == 1) {
        str = paramString1;
      } else {
        str = paramString1.toUpperCase(Locale.ENGLISH);
      }  
    switch (paramInt) {
      default:
        return null;
      case 6:
        return Boolean.valueOf(paramList.contains(str));
      case 5:
        return Boolean.valueOf(str.equals(paramString2));
      case 4:
        return Boolean.valueOf(str.contains(paramString2));
      case 3:
        return Boolean.valueOf(str.endsWith(paramString2));
      case 2:
        return Boolean.valueOf(str.startsWith(paramString2));
      case 1:
        break;
    } 
    if (paramBoolean) {
      paramInt = 0;
    } else {
      paramInt = 66;
    } 
    try {
      paramBoolean = Pattern.compile(paramString3, paramInt).matcher(str).matches();
      return Boolean.valueOf(paramBoolean);
    } catch (PatternSyntaxException patternSyntaxException) {
      zzgt().zzjj().zzg("Invalid regular expression in REGEXP audience filter. expression", paramString3);
      return null;
    } 
  }
  
  private final Boolean zza(String paramString, zzfl paramzzfl) {
    if (!zzft.zzcs(paramString))
      return null; 
    try {
      BigDecimal bigDecimal = new BigDecimal();
      this(paramString);
      return zza(bigDecimal, paramzzfl, 0.0D);
    } catch (NumberFormatException numberFormatException) {
      return null;
    } 
  }
  
  private final Boolean zza(String paramString, zzfn paramzzfn) {
    List<String> list;
    boolean bool;
    String str;
    Preconditions.checkNotNull(paramzzfn);
    if (paramString == null)
      return null; 
    Integer integer = paramzzfn.zzawe;
    if (integer == null || integer.intValue() == 0)
      return null; 
    if (paramzzfn.zzawe.intValue() == 6) {
      String[] arrayOfString1 = paramzzfn.zzawh;
      if (arrayOfString1 == null || arrayOfString1.length == 0)
        return null; 
    } else if (paramzzfn.zzawf == null) {
      return null;
    } 
    int i = paramzzfn.zzawe.intValue();
    Boolean bool1 = paramzzfn.zzawg;
    byte b = 0;
    if (bool1 != null && bool1.booleanValue()) {
      bool = true;
    } else {
      bool = false;
    } 
    if (bool || i == 1 || i == 6) {
      str = paramzzfn.zzawf;
    } else {
      str = paramzzfn.zzawf.toUpperCase(Locale.ENGLISH);
    } 
    String[] arrayOfString = paramzzfn.zzawh;
    if (arrayOfString == null) {
      paramzzfn = null;
    } else if (bool) {
      list = Arrays.asList(arrayOfString);
    } else {
      list = new ArrayList();
      int j = arrayOfString.length;
      while (b < j) {
        list.add(arrayOfString[b].toUpperCase(Locale.ENGLISH));
        b++;
      } 
    } 
    if (i == 1) {
      String str1 = str;
    } else {
      arrayOfString = null;
    } 
    return zza(paramString, i, bool, str, list, (String)arrayOfString);
  }
  
  private static Boolean zza(BigDecimal paramBigDecimal, zzfl paramzzfl, double paramDouble) {
    // Byte code:
    //   0: aload_1
    //   1: invokestatic checkNotNull : (Ljava/lang/Object;)Ljava/lang/Object;
    //   4: pop
    //   5: aload_1
    //   6: getfield zzavw : Ljava/lang/Integer;
    //   9: astore #10
    //   11: aload #10
    //   13: ifnull -> 412
    //   16: aload #10
    //   18: invokevirtual intValue : ()I
    //   21: ifne -> 27
    //   24: goto -> 412
    //   27: aload_1
    //   28: getfield zzavw : Ljava/lang/Integer;
    //   31: invokevirtual intValue : ()I
    //   34: iconst_4
    //   35: if_icmpne -> 54
    //   38: aload_1
    //   39: getfield zzavz : Ljava/lang/String;
    //   42: ifnull -> 52
    //   45: aload_1
    //   46: getfield zzawa : Ljava/lang/String;
    //   49: ifnonnull -> 63
    //   52: aconst_null
    //   53: areturn
    //   54: aload_1
    //   55: getfield zzavy : Ljava/lang/String;
    //   58: ifnonnull -> 63
    //   61: aconst_null
    //   62: areturn
    //   63: aload_1
    //   64: getfield zzavw : Ljava/lang/Integer;
    //   67: invokevirtual intValue : ()I
    //   70: istore #4
    //   72: aload_1
    //   73: getfield zzavw : Ljava/lang/Integer;
    //   76: invokevirtual intValue : ()I
    //   79: iconst_4
    //   80: if_icmpne -> 140
    //   83: aload_1
    //   84: getfield zzavz : Ljava/lang/String;
    //   87: invokestatic zzcs : (Ljava/lang/String;)Z
    //   90: ifeq -> 138
    //   93: aload_1
    //   94: getfield zzawa : Ljava/lang/String;
    //   97: invokestatic zzcs : (Ljava/lang/String;)Z
    //   100: ifne -> 106
    //   103: goto -> 138
    //   106: new java/math/BigDecimal
    //   109: astore #10
    //   111: aload #10
    //   113: aload_1
    //   114: getfield zzavz : Ljava/lang/String;
    //   117: invokespecial <init> : (Ljava/lang/String;)V
    //   120: new java/math/BigDecimal
    //   123: dup
    //   124: aload_1
    //   125: getfield zzawa : Ljava/lang/String;
    //   128: invokespecial <init> : (Ljava/lang/String;)V
    //   131: astore #11
    //   133: aconst_null
    //   134: astore_1
    //   135: goto -> 170
    //   138: aconst_null
    //   139: areturn
    //   140: aload_1
    //   141: getfield zzavy : Ljava/lang/String;
    //   144: invokestatic zzcs : (Ljava/lang/String;)Z
    //   147: ifne -> 152
    //   150: aconst_null
    //   151: areturn
    //   152: new java/math/BigDecimal
    //   155: dup
    //   156: aload_1
    //   157: getfield zzavy : Ljava/lang/String;
    //   160: invokespecial <init> : (Ljava/lang/String;)V
    //   163: astore_1
    //   164: aconst_null
    //   165: astore #10
    //   167: aconst_null
    //   168: astore #11
    //   170: iload #4
    //   172: iconst_4
    //   173: if_icmpne -> 183
    //   176: aload #10
    //   178: ifnonnull -> 187
    //   181: aconst_null
    //   182: areturn
    //   183: aload_1
    //   184: ifnull -> 412
    //   187: iconst_0
    //   188: istore #6
    //   190: iconst_0
    //   191: istore #5
    //   193: iconst_0
    //   194: istore #8
    //   196: iconst_0
    //   197: istore #9
    //   199: iconst_0
    //   200: istore #7
    //   202: iload #4
    //   204: iconst_1
    //   205: if_icmpeq -> 390
    //   208: iload #4
    //   210: iconst_2
    //   211: if_icmpeq -> 368
    //   214: iload #4
    //   216: iconst_3
    //   217: if_icmpeq -> 266
    //   220: iload #4
    //   222: iconst_4
    //   223: if_icmpeq -> 229
    //   226: goto -> 412
    //   229: iload #7
    //   231: istore #5
    //   233: aload_0
    //   234: aload #10
    //   236: invokevirtual compareTo : (Ljava/math/BigDecimal;)I
    //   239: iconst_m1
    //   240: if_icmpeq -> 260
    //   243: iload #7
    //   245: istore #5
    //   247: aload_0
    //   248: aload #11
    //   250: invokevirtual compareTo : (Ljava/math/BigDecimal;)I
    //   253: iconst_1
    //   254: if_icmpeq -> 260
    //   257: iconst_1
    //   258: istore #5
    //   260: iload #5
    //   262: invokestatic valueOf : (Z)Ljava/lang/Boolean;
    //   265: areturn
    //   266: dload_2
    //   267: dconst_0
    //   268: dcmpl
    //   269: ifeq -> 351
    //   272: iload #6
    //   274: istore #5
    //   276: aload_0
    //   277: aload_1
    //   278: new java/math/BigDecimal
    //   281: dup
    //   282: dload_2
    //   283: invokespecial <init> : (D)V
    //   286: new java/math/BigDecimal
    //   289: dup
    //   290: iconst_2
    //   291: invokespecial <init> : (I)V
    //   294: invokevirtual multiply : (Ljava/math/BigDecimal;)Ljava/math/BigDecimal;
    //   297: invokevirtual subtract : (Ljava/math/BigDecimal;)Ljava/math/BigDecimal;
    //   300: invokevirtual compareTo : (Ljava/math/BigDecimal;)I
    //   303: iconst_1
    //   304: if_icmpne -> 345
    //   307: iload #6
    //   309: istore #5
    //   311: aload_0
    //   312: aload_1
    //   313: new java/math/BigDecimal
    //   316: dup
    //   317: dload_2
    //   318: invokespecial <init> : (D)V
    //   321: new java/math/BigDecimal
    //   324: dup
    //   325: iconst_2
    //   326: invokespecial <init> : (I)V
    //   329: invokevirtual multiply : (Ljava/math/BigDecimal;)Ljava/math/BigDecimal;
    //   332: invokevirtual add : (Ljava/math/BigDecimal;)Ljava/math/BigDecimal;
    //   335: invokevirtual compareTo : (Ljava/math/BigDecimal;)I
    //   338: iconst_m1
    //   339: if_icmpne -> 345
    //   342: iconst_1
    //   343: istore #5
    //   345: iload #5
    //   347: invokestatic valueOf : (Z)Ljava/lang/Boolean;
    //   350: areturn
    //   351: aload_0
    //   352: aload_1
    //   353: invokevirtual compareTo : (Ljava/math/BigDecimal;)I
    //   356: ifne -> 362
    //   359: iconst_1
    //   360: istore #5
    //   362: iload #5
    //   364: invokestatic valueOf : (Z)Ljava/lang/Boolean;
    //   367: areturn
    //   368: iload #8
    //   370: istore #5
    //   372: aload_0
    //   373: aload_1
    //   374: invokevirtual compareTo : (Ljava/math/BigDecimal;)I
    //   377: iconst_1
    //   378: if_icmpne -> 384
    //   381: iconst_1
    //   382: istore #5
    //   384: iload #5
    //   386: invokestatic valueOf : (Z)Ljava/lang/Boolean;
    //   389: areturn
    //   390: iload #9
    //   392: istore #5
    //   394: aload_0
    //   395: aload_1
    //   396: invokevirtual compareTo : (Ljava/math/BigDecimal;)I
    //   399: iconst_m1
    //   400: if_icmpne -> 406
    //   403: iconst_1
    //   404: istore #5
    //   406: iload #5
    //   408: invokestatic valueOf : (Z)Ljava/lang/Boolean;
    //   411: areturn
    //   412: aconst_null
    //   413: areturn
    //   414: astore_0
    //   415: goto -> 138
    //   418: astore_0
    //   419: goto -> 412
    // Exception table:
    //   from	to	target	type
    //   106	133	414	java/lang/NumberFormatException
    //   152	164	418	java/lang/NumberFormatException
  }
  
  private static void zza(Map<Integer, Long> paramMap, int paramInt, long paramLong) {
    Long long_ = paramMap.get(Integer.valueOf(paramInt));
    paramLong /= 1000L;
    if (long_ == null || paramLong > long_.longValue())
      paramMap.put(Integer.valueOf(paramInt), Long.valueOf(paramLong)); 
  }
  
  private static void zzb(Map<Integer, List<Long>> paramMap, int paramInt, long paramLong) {
    List<Long> list2 = paramMap.get(Integer.valueOf(paramInt));
    List<Long> list1 = list2;
    if (list2 == null) {
      list1 = new ArrayList();
      paramMap.put(Integer.valueOf(paramInt), list1);
    } 
    list1.add(Long.valueOf(paramLong / 1000L));
  }
  
  private static zzfs[] zzb(Map<Integer, Long> paramMap) {
    if (paramMap == null)
      return null; 
    byte b = 0;
    zzfs[] arrayOfZzfs = new zzfs[paramMap.size()];
    for (Integer integer : paramMap.keySet()) {
      zzfs zzfs = new zzfs();
      zzfs.zzawz = integer;
      zzfs.zzaxa = paramMap.get(integer);
      arrayOfZzfs[b] = zzfs;
      b++;
    } 
    return arrayOfZzfs;
  }
  
  final zzfr[] zza(String paramString, zzft[] paramArrayOfzzft, zzfz[] paramArrayOfzzfz) {
    // Byte code:
    //   0: aload_1
    //   1: invokestatic checkNotEmpty : (Ljava/lang/String;)Ljava/lang/String;
    //   4: pop
    //   5: new java/util/HashSet
    //   8: dup
    //   9: invokespecial <init> : ()V
    //   12: astore #24
    //   14: new androidx/collection/ArrayMap
    //   17: dup
    //   18: invokespecial <init> : ()V
    //   21: astore #26
    //   23: new androidx/collection/ArrayMap
    //   26: dup
    //   27: invokespecial <init> : ()V
    //   30: astore #17
    //   32: new androidx/collection/ArrayMap
    //   35: dup
    //   36: invokespecial <init> : ()V
    //   39: astore #16
    //   41: new androidx/collection/ArrayMap
    //   44: dup
    //   45: invokespecial <init> : ()V
    //   48: astore #15
    //   50: new androidx/collection/ArrayMap
    //   53: dup
    //   54: invokespecial <init> : ()V
    //   57: astore #23
    //   59: aload_0
    //   60: invokevirtual zzgv : ()Lcom/google/android/gms/measurement/internal/zzq;
    //   63: aload_1
    //   64: invokevirtual zzbb : (Ljava/lang/String;)Z
    //   67: istore #14
    //   69: aload_0
    //   70: invokevirtual zzjt : ()Lcom/google/android/gms/measurement/internal/zzt;
    //   73: aload_1
    //   74: invokevirtual zzbp : (Ljava/lang/String;)Ljava/util/Map;
    //   77: astore #27
    //   79: iconst_1
    //   80: invokestatic valueOf : (Z)Ljava/lang/Boolean;
    //   83: astore #18
    //   85: aload #18
    //   87: astore #19
    //   89: aload #15
    //   91: astore #22
    //   93: aload #16
    //   95: astore #21
    //   97: aload #17
    //   99: astore #20
    //   101: aload #27
    //   103: ifnull -> 620
    //   106: aload #27
    //   108: invokeinterface keySet : ()Ljava/util/Set;
    //   113: invokeinterface iterator : ()Ljava/util/Iterator;
    //   118: astore #25
    //   120: aload #18
    //   122: astore #19
    //   124: aload #15
    //   126: astore #22
    //   128: aload #16
    //   130: astore #21
    //   132: aload #17
    //   134: astore #20
    //   136: aload #25
    //   138: invokeinterface hasNext : ()Z
    //   143: ifeq -> 620
    //   146: aload #25
    //   148: invokeinterface next : ()Ljava/lang/Object;
    //   153: checkcast java/lang/Integer
    //   156: invokevirtual intValue : ()I
    //   159: istore #6
    //   161: aload #27
    //   163: iload #6
    //   165: invokestatic valueOf : (I)Ljava/lang/Integer;
    //   168: invokeinterface get : (Ljava/lang/Object;)Ljava/lang/Object;
    //   173: checkcast com/google/android/gms/internal/measurement/zzfx
    //   176: astore #28
    //   178: aload #17
    //   180: iload #6
    //   182: invokestatic valueOf : (I)Ljava/lang/Integer;
    //   185: invokeinterface get : (Ljava/lang/Object;)Ljava/lang/Object;
    //   190: checkcast java/util/BitSet
    //   193: astore #21
    //   195: aload #16
    //   197: iload #6
    //   199: invokestatic valueOf : (I)Ljava/lang/Integer;
    //   202: invokeinterface get : (Ljava/lang/Object;)Ljava/lang/Object;
    //   207: checkcast java/util/BitSet
    //   210: astore #20
    //   212: iload #14
    //   214: ifeq -> 323
    //   217: new androidx/collection/ArrayMap
    //   220: dup
    //   221: invokespecial <init> : ()V
    //   224: astore #22
    //   226: aload #28
    //   228: ifnull -> 301
    //   231: aload #28
    //   233: getfield zzayr : [Lcom/google/android/gms/internal/measurement/zzfs;
    //   236: astore #19
    //   238: aload #19
    //   240: ifnonnull -> 246
    //   243: goto -> 301
    //   246: aload #19
    //   248: arraylength
    //   249: istore #4
    //   251: iconst_0
    //   252: istore #5
    //   254: iload #5
    //   256: iload #4
    //   258: if_icmpge -> 301
    //   261: aload #19
    //   263: iload #5
    //   265: aaload
    //   266: astore #30
    //   268: aload #30
    //   270: getfield zzawz : Ljava/lang/Integer;
    //   273: astore #29
    //   275: aload #29
    //   277: ifnull -> 295
    //   280: aload #22
    //   282: aload #29
    //   284: aload #30
    //   286: getfield zzaxa : Ljava/lang/Long;
    //   289: invokeinterface put : (Ljava/lang/Object;Ljava/lang/Object;)Ljava/lang/Object;
    //   294: pop
    //   295: iinc #5, 1
    //   298: goto -> 254
    //   301: aload #15
    //   303: iload #6
    //   305: invokestatic valueOf : (I)Ljava/lang/Integer;
    //   308: aload #22
    //   310: invokeinterface put : (Ljava/lang/Object;Ljava/lang/Object;)Ljava/lang/Object;
    //   315: pop
    //   316: aload #22
    //   318: astore #19
    //   320: goto -> 326
    //   323: aconst_null
    //   324: astore #19
    //   326: aload #21
    //   328: ifnonnull -> 382
    //   331: new java/util/BitSet
    //   334: dup
    //   335: invokespecial <init> : ()V
    //   338: astore #21
    //   340: aload #17
    //   342: iload #6
    //   344: invokestatic valueOf : (I)Ljava/lang/Integer;
    //   347: aload #21
    //   349: invokeinterface put : (Ljava/lang/Object;Ljava/lang/Object;)Ljava/lang/Object;
    //   354: pop
    //   355: new java/util/BitSet
    //   358: dup
    //   359: invokespecial <init> : ()V
    //   362: astore #20
    //   364: aload #16
    //   366: iload #6
    //   368: invokestatic valueOf : (I)Ljava/lang/Integer;
    //   371: aload #20
    //   373: invokeinterface put : (Ljava/lang/Object;Ljava/lang/Object;)Ljava/lang/Object;
    //   378: pop
    //   379: goto -> 382
    //   382: iconst_0
    //   383: istore #4
    //   385: aload #28
    //   387: getfield zzayp : [J
    //   390: astore #22
    //   392: iload #4
    //   394: aload #22
    //   396: arraylength
    //   397: bipush #6
    //   399: ishl
    //   400: if_icmpge -> 501
    //   403: aload #22
    //   405: iload #4
    //   407: invokestatic zza : ([JI)Z
    //   410: ifeq -> 469
    //   413: aload_0
    //   414: invokevirtual zzgt : ()Lcom/google/android/gms/measurement/internal/zzas;
    //   417: invokevirtual zzjo : ()Lcom/google/android/gms/measurement/internal/zzau;
    //   420: ldc_w 'Filter already evaluated. audience ID, filter ID'
    //   423: iload #6
    //   425: invokestatic valueOf : (I)Ljava/lang/Integer;
    //   428: iload #4
    //   430: invokestatic valueOf : (I)Ljava/lang/Integer;
    //   433: invokevirtual zze : (Ljava/lang/String;Ljava/lang/Object;Ljava/lang/Object;)V
    //   436: aload #20
    //   438: iload #4
    //   440: invokevirtual set : (I)V
    //   443: aload #28
    //   445: getfield zzayq : [J
    //   448: iload #4
    //   450: invokestatic zza : ([JI)Z
    //   453: ifeq -> 469
    //   456: aload #21
    //   458: iload #4
    //   460: invokevirtual set : (I)V
    //   463: iconst_1
    //   464: istore #5
    //   466: goto -> 472
    //   469: iconst_0
    //   470: istore #5
    //   472: aload #19
    //   474: ifnull -> 495
    //   477: iload #5
    //   479: ifne -> 495
    //   482: aload #19
    //   484: iload #4
    //   486: invokestatic valueOf : (I)Ljava/lang/Integer;
    //   489: invokeinterface remove : (Ljava/lang/Object;)Ljava/lang/Object;
    //   494: pop
    //   495: iinc #4, 1
    //   498: goto -> 385
    //   501: new com/google/android/gms/internal/measurement/zzfr
    //   504: dup
    //   505: invokespecial <init> : ()V
    //   508: astore #22
    //   510: aload #26
    //   512: iload #6
    //   514: invokestatic valueOf : (I)Ljava/lang/Integer;
    //   517: aload #22
    //   519: invokeinterface put : (Ljava/lang/Object;Ljava/lang/Object;)Ljava/lang/Object;
    //   524: pop
    //   525: aload #22
    //   527: iconst_0
    //   528: invokestatic valueOf : (Z)Ljava/lang/Boolean;
    //   531: putfield zzawx : Ljava/lang/Boolean;
    //   534: aload #22
    //   536: aload #28
    //   538: putfield zzaww : Lcom/google/android/gms/internal/measurement/zzfx;
    //   541: aload #22
    //   543: new com/google/android/gms/internal/measurement/zzfx
    //   546: dup
    //   547: invokespecial <init> : ()V
    //   550: putfield zzawv : Lcom/google/android/gms/internal/measurement/zzfx;
    //   553: aload #22
    //   555: getfield zzawv : Lcom/google/android/gms/internal/measurement/zzfx;
    //   558: aload #21
    //   560: invokestatic zza : (Ljava/util/BitSet;)[J
    //   563: putfield zzayq : [J
    //   566: aload #22
    //   568: getfield zzawv : Lcom/google/android/gms/internal/measurement/zzfx;
    //   571: aload #20
    //   573: invokestatic zza : (Ljava/util/BitSet;)[J
    //   576: putfield zzayp : [J
    //   579: iload #14
    //   581: ifeq -> 617
    //   584: aload #22
    //   586: getfield zzawv : Lcom/google/android/gms/internal/measurement/zzfx;
    //   589: aload #19
    //   591: invokestatic zzb : (Ljava/util/Map;)[Lcom/google/android/gms/internal/measurement/zzfs;
    //   594: putfield zzayr : [Lcom/google/android/gms/internal/measurement/zzfs;
    //   597: aload #23
    //   599: iload #6
    //   601: invokestatic valueOf : (I)Ljava/lang/Integer;
    //   604: new androidx/collection/ArrayMap
    //   607: dup
    //   608: invokespecial <init> : ()V
    //   611: invokeinterface put : (Ljava/lang/Object;Ljava/lang/Object;)Ljava/lang/Object;
    //   616: pop
    //   617: goto -> 120
    //   620: aload #22
    //   622: astore #16
    //   624: aload #21
    //   626: astore #15
    //   628: aload #20
    //   630: astore #17
    //   632: ldc_w 'Filter definition'
    //   635: astore #18
    //   637: ldc_w 'Skipping failed audience ID'
    //   640: astore #22
    //   642: aload #22
    //   644: astore #34
    //   646: aload #23
    //   648: astore #33
    //   650: aload #18
    //   652: astore #32
    //   654: aload #24
    //   656: astore #35
    //   658: aload #26
    //   660: astore #31
    //   662: aload #16
    //   664: astore #30
    //   666: aload #19
    //   668: astore #29
    //   670: aload #15
    //   672: astore #28
    //   674: aload #17
    //   676: astore #25
    //   678: aload_2
    //   679: ifnull -> 2993
    //   682: new androidx/collection/ArrayMap
    //   685: dup
    //   686: invokespecial <init> : ()V
    //   689: astore #28
    //   691: aload_2
    //   692: arraylength
    //   693: istore #5
    //   695: lconst_0
    //   696: lstore #10
    //   698: aconst_null
    //   699: astore #25
    //   701: aconst_null
    //   702: astore #27
    //   704: iconst_0
    //   705: istore #6
    //   707: aload #26
    //   709: astore #20
    //   711: aload #24
    //   713: astore #21
    //   715: aload #28
    //   717: astore #26
    //   719: aload #25
    //   721: astore #24
    //   723: aload #22
    //   725: astore #34
    //   727: aload #23
    //   729: astore #33
    //   731: aload #18
    //   733: astore #32
    //   735: aload #21
    //   737: astore #35
    //   739: aload #20
    //   741: astore #31
    //   743: aload #16
    //   745: astore #30
    //   747: aload #19
    //   749: astore #29
    //   751: aload #15
    //   753: astore #28
    //   755: aload #17
    //   757: astore #25
    //   759: iload #6
    //   761: iload #5
    //   763: if_icmpge -> 2993
    //   766: aload_2
    //   767: iload #6
    //   769: aaload
    //   770: astore #31
    //   772: aload #31
    //   774: getfield name : Ljava/lang/String;
    //   777: astore #28
    //   779: aload #31
    //   781: getfield zzaxc : [Lcom/google/android/gms/internal/measurement/zzfu;
    //   784: astore #29
    //   786: aload_0
    //   787: invokevirtual zzgv : ()Lcom/google/android/gms/measurement/internal/zzq;
    //   790: aload_1
    //   791: getstatic com/google/android/gms/measurement/internal/zzai.zzaki : Lcom/google/android/gms/measurement/internal/zzai$zza;
    //   794: invokevirtual zzd : (Ljava/lang/String;Lcom/google/android/gms/measurement/internal/zzai$zza;)Z
    //   797: ifeq -> 1514
    //   800: aload_0
    //   801: invokevirtual zzjr : ()Lcom/google/android/gms/measurement/internal/zzft;
    //   804: pop
    //   805: aload #31
    //   807: ldc_w '_eid'
    //   810: invokestatic zzb : (Lcom/google/android/gms/internal/measurement/zzft;Ljava/lang/String;)Ljava/lang/Object;
    //   813: checkcast java/lang/Long
    //   816: astore #32
    //   818: aload #32
    //   820: ifnull -> 829
    //   823: iconst_1
    //   824: istore #4
    //   826: goto -> 832
    //   829: iconst_0
    //   830: istore #4
    //   832: iload #4
    //   834: ifeq -> 854
    //   837: aload #28
    //   839: ldc_w '_ep'
    //   842: invokevirtual equals : (Ljava/lang/Object;)Z
    //   845: ifeq -> 854
    //   848: iconst_1
    //   849: istore #7
    //   851: goto -> 857
    //   854: iconst_0
    //   855: istore #7
    //   857: iload #7
    //   859: ifeq -> 1411
    //   862: aload_0
    //   863: invokevirtual zzjr : ()Lcom/google/android/gms/measurement/internal/zzft;
    //   866: pop
    //   867: aload #31
    //   869: ldc_w '_en'
    //   872: invokestatic zzb : (Lcom/google/android/gms/internal/measurement/zzft;Ljava/lang/String;)Ljava/lang/Object;
    //   875: checkcast java/lang/String
    //   878: astore #30
    //   880: aload #30
    //   882: invokestatic isEmpty : (Ljava/lang/CharSequence;)Z
    //   885: ifeq -> 906
    //   888: aload_0
    //   889: invokevirtual zzgt : ()Lcom/google/android/gms/measurement/internal/zzas;
    //   892: invokevirtual zzjg : ()Lcom/google/android/gms/measurement/internal/zzau;
    //   895: ldc_w 'Extra parameter without an event name. eventId'
    //   898: aload #32
    //   900: invokevirtual zzg : (Ljava/lang/String;Ljava/lang/Object;)V
    //   903: goto -> 1348
    //   906: aload #24
    //   908: ifnull -> 952
    //   911: aload #27
    //   913: ifnull -> 952
    //   916: aload #24
    //   918: astore #25
    //   920: aload #27
    //   922: astore #28
    //   924: lload #10
    //   926: lstore #12
    //   928: aload #32
    //   930: invokevirtual longValue : ()J
    //   933: aload #27
    //   935: invokevirtual longValue : ()J
    //   938: lcmp
    //   939: ifeq -> 945
    //   942: goto -> 952
    //   945: aload #28
    //   947: astore #24
    //   949: goto -> 1025
    //   952: aload_0
    //   953: invokevirtual zzjt : ()Lcom/google/android/gms/measurement/internal/zzt;
    //   956: aload_1
    //   957: aload #32
    //   959: invokevirtual zza : (Ljava/lang/String;Ljava/lang/Long;)Landroid/util/Pair;
    //   962: astore #28
    //   964: aload #28
    //   966: ifnull -> 1331
    //   969: aload #28
    //   971: getfield first : Ljava/lang/Object;
    //   974: astore #25
    //   976: aload #25
    //   978: ifnonnull -> 984
    //   981: goto -> 1331
    //   984: aload #25
    //   986: checkcast com/google/android/gms/internal/measurement/zzft
    //   989: astore #25
    //   991: aload #28
    //   993: getfield second : Ljava/lang/Object;
    //   996: checkcast java/lang/Long
    //   999: invokevirtual longValue : ()J
    //   1002: lstore #12
    //   1004: aload_0
    //   1005: invokevirtual zzjr : ()Lcom/google/android/gms/measurement/internal/zzft;
    //   1008: pop
    //   1009: aload #25
    //   1011: ldc_w '_eid'
    //   1014: invokestatic zzb : (Lcom/google/android/gms/internal/measurement/zzft;Ljava/lang/String;)Ljava/lang/Object;
    //   1017: checkcast java/lang/Long
    //   1020: astore #28
    //   1022: goto -> 945
    //   1025: lload #12
    //   1027: lconst_1
    //   1028: lsub
    //   1029: lstore #10
    //   1031: lload #10
    //   1033: lconst_0
    //   1034: lcmp
    //   1035: ifgt -> 1120
    //   1038: aload_0
    //   1039: invokevirtual zzjt : ()Lcom/google/android/gms/measurement/internal/zzt;
    //   1042: astore #28
    //   1044: aload #28
    //   1046: invokevirtual zzaf : ()V
    //   1049: aload #28
    //   1051: invokevirtual zzgt : ()Lcom/google/android/gms/measurement/internal/zzas;
    //   1054: invokevirtual zzjo : ()Lcom/google/android/gms/measurement/internal/zzau;
    //   1057: ldc_w 'Clearing complex main event info. appId'
    //   1060: aload_1
    //   1061: invokevirtual zzg : (Ljava/lang/String;Ljava/lang/Object;)V
    //   1064: aload #28
    //   1066: invokevirtual getWritableDatabase : ()Landroid/database/sqlite/SQLiteDatabase;
    //   1069: astore #27
    //   1071: aload #27
    //   1073: ldc_w 'delete from main_event_params where app_id=?'
    //   1076: iconst_1
    //   1077: anewarray java/lang/String
    //   1080: dup
    //   1081: iconst_0
    //   1082: aload_1
    //   1083: aastore
    //   1084: invokevirtual execSQL : (Ljava/lang/String;[Ljava/lang/Object;)V
    //   1087: goto -> 1113
    //   1090: astore #27
    //   1092: goto -> 1097
    //   1095: astore #27
    //   1097: aload #28
    //   1099: invokevirtual zzgt : ()Lcom/google/android/gms/measurement/internal/zzas;
    //   1102: invokevirtual zzjg : ()Lcom/google/android/gms/measurement/internal/zzau;
    //   1105: ldc_w 'Error clearing complex main event'
    //   1108: aload #27
    //   1110: invokevirtual zzg : (Ljava/lang/String;Ljava/lang/Object;)V
    //   1113: aload #25
    //   1115: astore #27
    //   1117: goto -> 1139
    //   1120: aload_0
    //   1121: invokevirtual zzjt : ()Lcom/google/android/gms/measurement/internal/zzt;
    //   1124: aload_1
    //   1125: aload #32
    //   1127: lload #10
    //   1129: aload #25
    //   1131: invokevirtual zza : (Ljava/lang/String;Ljava/lang/Long;JLcom/google/android/gms/internal/measurement/zzft;)Z
    //   1134: pop
    //   1135: aload #25
    //   1137: astore #27
    //   1139: aload #25
    //   1141: getfield zzaxc : [Lcom/google/android/gms/internal/measurement/zzfu;
    //   1144: astore #27
    //   1146: aload #27
    //   1148: arraylength
    //   1149: aload #29
    //   1151: arraylength
    //   1152: iadd
    //   1153: anewarray com/google/android/gms/internal/measurement/zzfu
    //   1156: astore #28
    //   1158: aload #27
    //   1160: arraylength
    //   1161: istore #9
    //   1163: iconst_0
    //   1164: istore #8
    //   1166: iconst_0
    //   1167: istore #4
    //   1169: iload #8
    //   1171: iload #9
    //   1173: if_icmpge -> 1228
    //   1176: aload #27
    //   1178: iload #8
    //   1180: aaload
    //   1181: astore #32
    //   1183: aload_0
    //   1184: invokevirtual zzjr : ()Lcom/google/android/gms/measurement/internal/zzft;
    //   1187: pop
    //   1188: iload #4
    //   1190: istore #7
    //   1192: aload #31
    //   1194: aload #32
    //   1196: getfield name : Ljava/lang/String;
    //   1199: invokestatic zza : (Lcom/google/android/gms/internal/measurement/zzft;Ljava/lang/String;)Lcom/google/android/gms/internal/measurement/zzfu;
    //   1202: ifnonnull -> 1218
    //   1205: aload #28
    //   1207: iload #4
    //   1209: aload #32
    //   1211: aastore
    //   1212: iload #4
    //   1214: iconst_1
    //   1215: iadd
    //   1216: istore #7
    //   1218: iinc #8, 1
    //   1221: iload #7
    //   1223: istore #4
    //   1225: goto -> 1169
    //   1228: iload #4
    //   1230: ifle -> 1309
    //   1233: aload #29
    //   1235: arraylength
    //   1236: istore #8
    //   1238: iconst_0
    //   1239: istore #7
    //   1241: iload #7
    //   1243: iload #8
    //   1245: if_icmpge -> 1267
    //   1248: aload #28
    //   1250: iload #4
    //   1252: aload #29
    //   1254: iload #7
    //   1256: aaload
    //   1257: aastore
    //   1258: iinc #7, 1
    //   1261: iinc #4, 1
    //   1264: goto -> 1241
    //   1267: iload #4
    //   1269: aload #28
    //   1271: arraylength
    //   1272: if_icmpne -> 1282
    //   1275: aload #28
    //   1277: astore #27
    //   1279: goto -> 1294
    //   1282: aload #28
    //   1284: iload #4
    //   1286: invokestatic copyOf : ([Ljava/lang/Object;I)[Ljava/lang/Object;
    //   1289: checkcast [Lcom/google/android/gms/internal/measurement/zzfu;
    //   1292: astore #27
    //   1294: aload #25
    //   1296: astore #29
    //   1298: aload #30
    //   1300: astore #28
    //   1302: aload #24
    //   1304: astore #25
    //   1306: goto -> 1542
    //   1309: aload_0
    //   1310: invokevirtual zzgt : ()Lcom/google/android/gms/measurement/internal/zzas;
    //   1313: invokevirtual zzjj : ()Lcom/google/android/gms/measurement/internal/zzau;
    //   1316: ldc_w 'No unique parameters in main event. eventName'
    //   1319: aload #30
    //   1321: invokevirtual zzg : (Ljava/lang/String;Ljava/lang/Object;)V
    //   1324: aload #30
    //   1326: astore #27
    //   1328: goto -> 1526
    //   1331: aload_0
    //   1332: invokevirtual zzgt : ()Lcom/google/android/gms/measurement/internal/zzas;
    //   1335: invokevirtual zzjg : ()Lcom/google/android/gms/measurement/internal/zzau;
    //   1338: ldc_w 'Extra parameter without existing main event. eventName, eventId'
    //   1341: aload #30
    //   1343: aload #32
    //   1345: invokevirtual zze : (Ljava/lang/String;Ljava/lang/Object;Ljava/lang/Object;)V
    //   1348: aload #23
    //   1350: astore #28
    //   1352: aload #26
    //   1354: astore #29
    //   1356: aload #20
    //   1358: astore #26
    //   1360: aload #15
    //   1362: astore #30
    //   1364: aload #19
    //   1366: astore #15
    //   1368: aload #27
    //   1370: astore #25
    //   1372: aload #21
    //   1374: astore #23
    //   1376: aload #29
    //   1378: astore #19
    //   1380: aload #22
    //   1382: astore #27
    //   1384: aload #28
    //   1386: astore #20
    //   1388: aload #16
    //   1390: astore #21
    //   1392: aload #30
    //   1394: astore #16
    //   1396: aload #18
    //   1398: astore #22
    //   1400: aload #15
    //   1402: astore #18
    //   1404: aload #26
    //   1406: astore #15
    //   1408: goto -> 2923
    //   1411: iload #4
    //   1413: ifeq -> 1514
    //   1416: aload_0
    //   1417: invokevirtual zzjr : ()Lcom/google/android/gms/measurement/internal/zzft;
    //   1420: pop
    //   1421: lconst_0
    //   1422: invokestatic valueOf : (J)Ljava/lang/Long;
    //   1425: astore #25
    //   1427: aload #31
    //   1429: ldc_w '_epc'
    //   1432: invokestatic zzb : (Lcom/google/android/gms/internal/measurement/zzft;Ljava/lang/String;)Ljava/lang/Object;
    //   1435: astore #24
    //   1437: aload #24
    //   1439: ifnonnull -> 1449
    //   1442: aload #25
    //   1444: astore #24
    //   1446: goto -> 1449
    //   1449: aload #24
    //   1451: checkcast java/lang/Long
    //   1454: invokevirtual longValue : ()J
    //   1457: lstore #10
    //   1459: lload #10
    //   1461: lconst_0
    //   1462: lcmp
    //   1463: ifgt -> 1484
    //   1466: aload_0
    //   1467: invokevirtual zzgt : ()Lcom/google/android/gms/measurement/internal/zzas;
    //   1470: invokevirtual zzjj : ()Lcom/google/android/gms/measurement/internal/zzau;
    //   1473: ldc_w 'Complex event with zero extra param count. eventName'
    //   1476: aload #28
    //   1478: invokevirtual zzg : (Ljava/lang/String;Ljava/lang/Object;)V
    //   1481: goto -> 1499
    //   1484: aload_0
    //   1485: invokevirtual zzjt : ()Lcom/google/android/gms/measurement/internal/zzt;
    //   1488: aload_1
    //   1489: aload #32
    //   1491: lload #10
    //   1493: aload #31
    //   1495: invokevirtual zza : (Ljava/lang/String;Ljava/lang/Long;JLcom/google/android/gms/internal/measurement/zzft;)Z
    //   1498: pop
    //   1499: aload #32
    //   1501: astore #25
    //   1503: aload #31
    //   1505: astore #24
    //   1507: aload #29
    //   1509: astore #30
    //   1511: goto -> 1550
    //   1514: aload #24
    //   1516: astore #25
    //   1518: aload #27
    //   1520: astore #24
    //   1522: aload #28
    //   1524: astore #27
    //   1526: aload #27
    //   1528: astore #28
    //   1530: aload #29
    //   1532: astore #27
    //   1534: aload #25
    //   1536: astore #29
    //   1538: aload #24
    //   1540: astore #25
    //   1542: aload #29
    //   1544: astore #24
    //   1546: aload #27
    //   1548: astore #30
    //   1550: aload #22
    //   1552: astore #27
    //   1554: aload #19
    //   1556: astore #29
    //   1558: aload_0
    //   1559: invokevirtual zzjt : ()Lcom/google/android/gms/measurement/internal/zzt;
    //   1562: aload_1
    //   1563: aload #31
    //   1565: getfield name : Ljava/lang/String;
    //   1568: invokevirtual zzg : (Ljava/lang/String;Ljava/lang/String;)Lcom/google/android/gms/measurement/internal/zzac;
    //   1571: astore #19
    //   1573: aload #19
    //   1575: ifnonnull -> 1637
    //   1578: aload_0
    //   1579: invokevirtual zzgt : ()Lcom/google/android/gms/measurement/internal/zzas;
    //   1582: invokevirtual zzjj : ()Lcom/google/android/gms/measurement/internal/zzau;
    //   1585: ldc_w 'Event aggregate wasn't created during raw event logging. appId, event'
    //   1588: aload_1
    //   1589: invokestatic zzbw : (Ljava/lang/String;)Ljava/lang/Object;
    //   1592: aload_0
    //   1593: invokevirtual zzgq : ()Lcom/google/android/gms/measurement/internal/zzaq;
    //   1596: aload #28
    //   1598: invokevirtual zzbt : (Ljava/lang/String;)Ljava/lang/String;
    //   1601: invokevirtual zze : (Ljava/lang/String;Ljava/lang/Object;Ljava/lang/Object;)V
    //   1604: new com/google/android/gms/measurement/internal/zzac
    //   1607: dup
    //   1608: aload_1
    //   1609: aload #31
    //   1611: getfield name : Ljava/lang/String;
    //   1614: lconst_1
    //   1615: lconst_1
    //   1616: aload #31
    //   1618: getfield zzaxd : Ljava/lang/Long;
    //   1621: invokevirtual longValue : ()J
    //   1624: lconst_0
    //   1625: aconst_null
    //   1626: aconst_null
    //   1627: aconst_null
    //   1628: aconst_null
    //   1629: invokespecial <init> : (Ljava/lang/String;Ljava/lang/String;JJJJLjava/lang/Long;Ljava/lang/Long;Ljava/lang/Long;Ljava/lang/Boolean;)V
    //   1632: astore #33
    //   1634: goto -> 1700
    //   1637: new com/google/android/gms/measurement/internal/zzac
    //   1640: dup
    //   1641: aload #19
    //   1643: getfield zztt : Ljava/lang/String;
    //   1646: aload #19
    //   1648: getfield name : Ljava/lang/String;
    //   1651: aload #19
    //   1653: getfield zzahv : J
    //   1656: lconst_1
    //   1657: ladd
    //   1658: aload #19
    //   1660: getfield zzahw : J
    //   1663: lconst_1
    //   1664: ladd
    //   1665: aload #19
    //   1667: getfield zzahx : J
    //   1670: aload #19
    //   1672: getfield zzahy : J
    //   1675: aload #19
    //   1677: getfield zzahz : Ljava/lang/Long;
    //   1680: aload #19
    //   1682: getfield zzaia : Ljava/lang/Long;
    //   1685: aload #19
    //   1687: getfield zzaib : Ljava/lang/Long;
    //   1690: aload #19
    //   1692: getfield zzaic : Ljava/lang/Boolean;
    //   1695: invokespecial <init> : (Ljava/lang/String;Ljava/lang/String;JJJJLjava/lang/Long;Ljava/lang/Long;Ljava/lang/Long;Ljava/lang/Boolean;)V
    //   1698: astore #33
    //   1700: aload #20
    //   1702: astore #19
    //   1704: aload #21
    //   1706: astore #20
    //   1708: aload #18
    //   1710: astore #22
    //   1712: aload #15
    //   1714: astore #34
    //   1716: aload #16
    //   1718: astore #21
    //   1720: aload #31
    //   1722: astore #32
    //   1724: aload_0
    //   1725: invokevirtual zzjt : ()Lcom/google/android/gms/measurement/internal/zzt;
    //   1728: aload #33
    //   1730: invokevirtual zza : (Lcom/google/android/gms/measurement/internal/zzac;)V
    //   1733: aload #33
    //   1735: getfield zzahv : J
    //   1738: lstore #12
    //   1740: aload #26
    //   1742: astore #33
    //   1744: aload #33
    //   1746: aload #28
    //   1748: invokeinterface get : (Ljava/lang/Object;)Ljava/lang/Object;
    //   1753: checkcast java/util/Map
    //   1756: astore #16
    //   1758: aload #16
    //   1760: astore #15
    //   1762: aload #16
    //   1764: ifnonnull -> 1809
    //   1767: aload_0
    //   1768: invokevirtual zzjt : ()Lcom/google/android/gms/measurement/internal/zzt;
    //   1771: aload_1
    //   1772: aload #28
    //   1774: invokevirtual zzl : (Ljava/lang/String;Ljava/lang/String;)Ljava/util/Map;
    //   1777: astore #16
    //   1779: aload #16
    //   1781: astore #15
    //   1783: aload #16
    //   1785: ifnonnull -> 1797
    //   1788: new androidx/collection/ArrayMap
    //   1791: dup
    //   1792: invokespecial <init> : ()V
    //   1795: astore #15
    //   1797: aload #33
    //   1799: aload #28
    //   1801: aload #15
    //   1803: invokeinterface put : (Ljava/lang/Object;Ljava/lang/Object;)Ljava/lang/Object;
    //   1808: pop
    //   1809: aload #15
    //   1811: astore #26
    //   1813: aload #26
    //   1815: invokeinterface keySet : ()Ljava/util/Set;
    //   1820: invokeinterface iterator : ()Ljava/util/Iterator;
    //   1825: astore #31
    //   1827: aload #20
    //   1829: astore #18
    //   1831: aload #34
    //   1833: astore #16
    //   1835: aload #23
    //   1837: astore #20
    //   1839: aload #29
    //   1841: astore #15
    //   1843: aload #33
    //   1845: astore #23
    //   1847: aload #32
    //   1849: astore #29
    //   1851: aload #28
    //   1853: astore #33
    //   1855: aload #31
    //   1857: invokeinterface hasNext : ()Z
    //   1862: ifeq -> 2899
    //   1865: aload #31
    //   1867: invokeinterface next : ()Ljava/lang/Object;
    //   1872: checkcast java/lang/Integer
    //   1875: invokevirtual intValue : ()I
    //   1878: istore #8
    //   1880: aload #18
    //   1882: iload #8
    //   1884: invokestatic valueOf : (I)Ljava/lang/Integer;
    //   1887: invokeinterface contains : (Ljava/lang/Object;)Z
    //   1892: ifeq -> 1915
    //   1895: aload_0
    //   1896: invokevirtual zzgt : ()Lcom/google/android/gms/measurement/internal/zzas;
    //   1899: invokevirtual zzjo : ()Lcom/google/android/gms/measurement/internal/zzau;
    //   1902: aload #27
    //   1904: iload #8
    //   1906: invokestatic valueOf : (I)Ljava/lang/Integer;
    //   1909: invokevirtual zzg : (Ljava/lang/String;Ljava/lang/Object;)V
    //   1912: goto -> 1855
    //   1915: aload #19
    //   1917: astore #34
    //   1919: aload #34
    //   1921: iload #8
    //   1923: invokestatic valueOf : (I)Ljava/lang/Integer;
    //   1926: invokeinterface get : (Ljava/lang/Object;)Ljava/lang/Object;
    //   1931: checkcast com/google/android/gms/internal/measurement/zzfr
    //   1934: astore #32
    //   1936: aload #17
    //   1938: astore #35
    //   1940: aload #35
    //   1942: iload #8
    //   1944: invokestatic valueOf : (I)Ljava/lang/Integer;
    //   1947: invokeinterface get : (Ljava/lang/Object;)Ljava/lang/Object;
    //   1952: checkcast java/util/BitSet
    //   1955: astore #28
    //   1957: aload #29
    //   1959: astore #19
    //   1961: aload #16
    //   1963: astore #36
    //   1965: aload #36
    //   1967: iload #8
    //   1969: invokestatic valueOf : (I)Ljava/lang/Integer;
    //   1972: invokeinterface get : (Ljava/lang/Object;)Ljava/lang/Object;
    //   1977: checkcast java/util/BitSet
    //   1980: astore #29
    //   1982: iload #14
    //   1984: ifeq -> 2024
    //   1987: aload #21
    //   1989: iload #8
    //   1991: invokestatic valueOf : (I)Ljava/lang/Integer;
    //   1994: invokeinterface get : (Ljava/lang/Object;)Ljava/lang/Object;
    //   1999: checkcast java/util/Map
    //   2002: astore #17
    //   2004: aload #20
    //   2006: iload #8
    //   2008: invokestatic valueOf : (I)Ljava/lang/Integer;
    //   2011: invokeinterface get : (Ljava/lang/Object;)Ljava/lang/Object;
    //   2016: checkcast java/util/Map
    //   2019: astore #16
    //   2021: goto -> 2030
    //   2024: aconst_null
    //   2025: astore #16
    //   2027: aconst_null
    //   2028: astore #17
    //   2030: aload #27
    //   2032: astore #37
    //   2034: aload #32
    //   2036: ifnonnull -> 2185
    //   2039: new com/google/android/gms/internal/measurement/zzfr
    //   2042: dup
    //   2043: invokespecial <init> : ()V
    //   2046: astore #27
    //   2048: aload #34
    //   2050: iload #8
    //   2052: invokestatic valueOf : (I)Ljava/lang/Integer;
    //   2055: aload #27
    //   2057: invokeinterface put : (Ljava/lang/Object;Ljava/lang/Object;)Ljava/lang/Object;
    //   2062: pop
    //   2063: aload #27
    //   2065: aload #15
    //   2067: putfield zzawx : Ljava/lang/Boolean;
    //   2070: new java/util/BitSet
    //   2073: dup
    //   2074: invokespecial <init> : ()V
    //   2077: astore #28
    //   2079: aload #35
    //   2081: iload #8
    //   2083: invokestatic valueOf : (I)Ljava/lang/Integer;
    //   2086: aload #28
    //   2088: invokeinterface put : (Ljava/lang/Object;Ljava/lang/Object;)Ljava/lang/Object;
    //   2093: pop
    //   2094: new java/util/BitSet
    //   2097: dup
    //   2098: invokespecial <init> : ()V
    //   2101: astore #27
    //   2103: aload #36
    //   2105: iload #8
    //   2107: invokestatic valueOf : (I)Ljava/lang/Integer;
    //   2110: aload #27
    //   2112: invokeinterface put : (Ljava/lang/Object;Ljava/lang/Object;)Ljava/lang/Object;
    //   2117: pop
    //   2118: iload #14
    //   2120: ifeq -> 2174
    //   2123: new androidx/collection/ArrayMap
    //   2126: dup
    //   2127: invokespecial <init> : ()V
    //   2130: astore #29
    //   2132: aload #21
    //   2134: iload #8
    //   2136: invokestatic valueOf : (I)Ljava/lang/Integer;
    //   2139: aload #29
    //   2141: invokeinterface put : (Ljava/lang/Object;Ljava/lang/Object;)Ljava/lang/Object;
    //   2146: pop
    //   2147: new androidx/collection/ArrayMap
    //   2150: dup
    //   2151: invokespecial <init> : ()V
    //   2154: astore #16
    //   2156: aload #20
    //   2158: iload #8
    //   2160: invokestatic valueOf : (I)Ljava/lang/Integer;
    //   2163: aload #16
    //   2165: invokeinterface put : (Ljava/lang/Object;Ljava/lang/Object;)Ljava/lang/Object;
    //   2170: pop
    //   2171: goto -> 2178
    //   2174: aload #17
    //   2176: astore #29
    //   2178: aload #16
    //   2180: astore #32
    //   2182: goto -> 2197
    //   2185: aload #29
    //   2187: astore #27
    //   2189: aload #17
    //   2191: astore #29
    //   2193: aload #16
    //   2195: astore #32
    //   2197: aload #21
    //   2199: astore #38
    //   2201: aload #20
    //   2203: astore #39
    //   2205: aload #15
    //   2207: astore #17
    //   2209: aload #26
    //   2211: iload #8
    //   2213: invokestatic valueOf : (I)Ljava/lang/Integer;
    //   2216: invokeinterface get : (Ljava/lang/Object;)Ljava/lang/Object;
    //   2221: checkcast java/util/List
    //   2224: invokeinterface iterator : ()Ljava/util/Iterator;
    //   2229: astore #40
    //   2231: aload #36
    //   2233: astore #20
    //   2235: aload #26
    //   2237: astore #15
    //   2239: aload #35
    //   2241: astore #21
    //   2243: aload #34
    //   2245: astore #16
    //   2247: aload #33
    //   2249: astore #26
    //   2251: aload #40
    //   2253: invokeinterface hasNext : ()Z
    //   2258: ifeq -> 2848
    //   2261: aload #40
    //   2263: invokeinterface next : ()Ljava/lang/Object;
    //   2268: checkcast com/google/android/gms/internal/measurement/zzfj
    //   2271: astore #35
    //   2273: aload_0
    //   2274: invokevirtual zzgt : ()Lcom/google/android/gms/measurement/internal/zzas;
    //   2277: iconst_2
    //   2278: invokevirtual isLoggable : (I)Z
    //   2281: ifeq -> 2343
    //   2284: aload_0
    //   2285: invokevirtual zzgt : ()Lcom/google/android/gms/measurement/internal/zzas;
    //   2288: invokevirtual zzjo : ()Lcom/google/android/gms/measurement/internal/zzau;
    //   2291: ldc_w 'Evaluating filter. audience, filter, event'
    //   2294: iload #8
    //   2296: invokestatic valueOf : (I)Ljava/lang/Integer;
    //   2299: aload #35
    //   2301: getfield zzavm : Ljava/lang/Integer;
    //   2304: aload_0
    //   2305: invokevirtual zzgq : ()Lcom/google/android/gms/measurement/internal/zzaq;
    //   2308: aload #35
    //   2310: getfield zzavn : Ljava/lang/String;
    //   2313: invokevirtual zzbt : (Ljava/lang/String;)Ljava/lang/String;
    //   2316: invokevirtual zzd : (Ljava/lang/String;Ljava/lang/Object;Ljava/lang/Object;Ljava/lang/Object;)V
    //   2319: aload_0
    //   2320: invokevirtual zzgt : ()Lcom/google/android/gms/measurement/internal/zzas;
    //   2323: invokevirtual zzjo : ()Lcom/google/android/gms/measurement/internal/zzau;
    //   2326: aload #22
    //   2328: aload_0
    //   2329: invokevirtual zzjr : ()Lcom/google/android/gms/measurement/internal/zzft;
    //   2332: aload #35
    //   2334: invokevirtual zza : (Lcom/google/android/gms/internal/measurement/zzfj;)Ljava/lang/String;
    //   2337: invokevirtual zzg : (Ljava/lang/String;Ljava/lang/Object;)V
    //   2340: goto -> 2343
    //   2343: aload #35
    //   2345: getfield zzavm : Ljava/lang/Integer;
    //   2348: astore #33
    //   2350: aload #33
    //   2352: ifnull -> 2820
    //   2355: aload #33
    //   2357: invokevirtual intValue : ()I
    //   2360: sipush #256
    //   2363: if_icmple -> 2369
    //   2366: goto -> 2820
    //   2369: iload #14
    //   2371: ifeq -> 2670
    //   2374: aload #35
    //   2376: ifnull -> 2405
    //   2379: aload #35
    //   2381: getfield zzavj : Ljava/lang/Boolean;
    //   2384: astore #33
    //   2386: aload #33
    //   2388: ifnull -> 2405
    //   2391: aload #33
    //   2393: invokevirtual booleanValue : ()Z
    //   2396: ifeq -> 2405
    //   2399: iconst_1
    //   2400: istore #4
    //   2402: goto -> 2408
    //   2405: iconst_0
    //   2406: istore #4
    //   2408: aload #35
    //   2410: ifnull -> 2439
    //   2413: aload #35
    //   2415: getfield zzavk : Ljava/lang/Boolean;
    //   2418: astore #33
    //   2420: aload #33
    //   2422: ifnull -> 2439
    //   2425: aload #33
    //   2427: invokevirtual booleanValue : ()Z
    //   2430: ifeq -> 2439
    //   2433: iconst_1
    //   2434: istore #7
    //   2436: goto -> 2442
    //   2439: iconst_0
    //   2440: istore #7
    //   2442: aload #28
    //   2444: aload #35
    //   2446: getfield zzavm : Ljava/lang/Integer;
    //   2449: invokevirtual intValue : ()I
    //   2452: invokevirtual get : (I)Z
    //   2455: ifeq -> 2494
    //   2458: iload #4
    //   2460: ifne -> 2494
    //   2463: iload #7
    //   2465: ifne -> 2494
    //   2468: aload_0
    //   2469: invokevirtual zzgt : ()Lcom/google/android/gms/measurement/internal/zzas;
    //   2472: invokevirtual zzjo : ()Lcom/google/android/gms/measurement/internal/zzau;
    //   2475: ldc_w 'Event filter already evaluated true and it is not associated with a dynamic audience. audience ID, filter ID'
    //   2478: iload #8
    //   2480: invokestatic valueOf : (I)Ljava/lang/Integer;
    //   2483: aload #35
    //   2485: getfield zzavm : Ljava/lang/Integer;
    //   2488: invokevirtual zze : (Ljava/lang/String;Ljava/lang/Object;Ljava/lang/Object;)V
    //   2491: goto -> 2251
    //   2494: aload_0
    //   2495: aload #35
    //   2497: aload #26
    //   2499: aload #30
    //   2501: lload #12
    //   2503: invokespecial zza : (Lcom/google/android/gms/internal/measurement/zzfj;Ljava/lang/String;[Lcom/google/android/gms/internal/measurement/zzfu;J)Ljava/lang/Boolean;
    //   2506: astore #34
    //   2508: aload_0
    //   2509: invokevirtual zzgt : ()Lcom/google/android/gms/measurement/internal/zzas;
    //   2512: invokevirtual zzjo : ()Lcom/google/android/gms/measurement/internal/zzau;
    //   2515: astore #36
    //   2517: aload #34
    //   2519: ifnonnull -> 2530
    //   2522: ldc_w 'null'
    //   2525: astore #33
    //   2527: goto -> 2534
    //   2530: aload #34
    //   2532: astore #33
    //   2534: aload #36
    //   2536: ldc_w 'Event filter result'
    //   2539: aload #33
    //   2541: invokevirtual zzg : (Ljava/lang/String;Ljava/lang/Object;)V
    //   2544: aload #34
    //   2546: ifnonnull -> 2565
    //   2549: aload #18
    //   2551: iload #8
    //   2553: invokestatic valueOf : (I)Ljava/lang/Integer;
    //   2556: invokeinterface add : (Ljava/lang/Object;)Z
    //   2561: pop
    //   2562: goto -> 2845
    //   2565: aload #27
    //   2567: aload #35
    //   2569: getfield zzavm : Ljava/lang/Integer;
    //   2572: invokevirtual intValue : ()I
    //   2575: invokevirtual set : (I)V
    //   2578: aload #34
    //   2580: invokevirtual booleanValue : ()Z
    //   2583: ifeq -> 2845
    //   2586: aload #28
    //   2588: aload #35
    //   2590: getfield zzavm : Ljava/lang/Integer;
    //   2593: invokevirtual intValue : ()I
    //   2596: invokevirtual set : (I)V
    //   2599: iload #4
    //   2601: ifne -> 2609
    //   2604: iload #7
    //   2606: ifeq -> 2845
    //   2609: aload #19
    //   2611: getfield zzaxd : Ljava/lang/Long;
    //   2614: ifnull -> 2845
    //   2617: iload #7
    //   2619: ifeq -> 2646
    //   2622: aload #32
    //   2624: aload #35
    //   2626: getfield zzavm : Ljava/lang/Integer;
    //   2629: invokevirtual intValue : ()I
    //   2632: aload #19
    //   2634: getfield zzaxd : Ljava/lang/Long;
    //   2637: invokevirtual longValue : ()J
    //   2640: invokestatic zzb : (Ljava/util/Map;IJ)V
    //   2643: goto -> 2845
    //   2646: aload #29
    //   2648: aload #35
    //   2650: getfield zzavm : Ljava/lang/Integer;
    //   2653: invokevirtual intValue : ()I
    //   2656: aload #19
    //   2658: getfield zzaxd : Ljava/lang/Long;
    //   2661: invokevirtual longValue : ()J
    //   2664: invokestatic zza : (Ljava/util/Map;IJ)V
    //   2667: goto -> 2709
    //   2670: aload #28
    //   2672: aload #35
    //   2674: getfield zzavm : Ljava/lang/Integer;
    //   2677: invokevirtual intValue : ()I
    //   2680: invokevirtual get : (I)Z
    //   2683: ifeq -> 2712
    //   2686: aload_0
    //   2687: invokevirtual zzgt : ()Lcom/google/android/gms/measurement/internal/zzas;
    //   2690: invokevirtual zzjo : ()Lcom/google/android/gms/measurement/internal/zzau;
    //   2693: ldc_w 'Event filter already evaluated true. audience ID, filter ID'
    //   2696: iload #8
    //   2698: invokestatic valueOf : (I)Ljava/lang/Integer;
    //   2701: aload #35
    //   2703: getfield zzavm : Ljava/lang/Integer;
    //   2706: invokevirtual zze : (Ljava/lang/String;Ljava/lang/Object;Ljava/lang/Object;)V
    //   2709: goto -> 2251
    //   2712: aload_0
    //   2713: aload #35
    //   2715: aload #26
    //   2717: aload #30
    //   2719: lload #12
    //   2721: invokespecial zza : (Lcom/google/android/gms/internal/measurement/zzfj;Ljava/lang/String;[Lcom/google/android/gms/internal/measurement/zzfu;J)Ljava/lang/Boolean;
    //   2724: astore #34
    //   2726: aload_0
    //   2727: invokevirtual zzgt : ()Lcom/google/android/gms/measurement/internal/zzas;
    //   2730: invokevirtual zzjo : ()Lcom/google/android/gms/measurement/internal/zzau;
    //   2733: astore #36
    //   2735: aload #34
    //   2737: ifnonnull -> 2748
    //   2740: ldc_w 'null'
    //   2743: astore #33
    //   2745: goto -> 2752
    //   2748: aload #34
    //   2750: astore #33
    //   2752: aload #36
    //   2754: ldc_w 'Event filter result'
    //   2757: aload #33
    //   2759: invokevirtual zzg : (Ljava/lang/String;Ljava/lang/Object;)V
    //   2762: aload #34
    //   2764: ifnonnull -> 2783
    //   2767: aload #18
    //   2769: iload #8
    //   2771: invokestatic valueOf : (I)Ljava/lang/Integer;
    //   2774: invokeinterface add : (Ljava/lang/Object;)Z
    //   2779: pop
    //   2780: goto -> 2845
    //   2783: aload #27
    //   2785: aload #35
    //   2787: getfield zzavm : Ljava/lang/Integer;
    //   2790: invokevirtual intValue : ()I
    //   2793: invokevirtual set : (I)V
    //   2796: aload #34
    //   2798: invokevirtual booleanValue : ()Z
    //   2801: ifeq -> 2845
    //   2804: aload #28
    //   2806: aload #35
    //   2808: getfield zzavm : Ljava/lang/Integer;
    //   2811: invokevirtual intValue : ()I
    //   2814: invokevirtual set : (I)V
    //   2817: goto -> 2845
    //   2820: aload_0
    //   2821: invokevirtual zzgt : ()Lcom/google/android/gms/measurement/internal/zzas;
    //   2824: invokevirtual zzjj : ()Lcom/google/android/gms/measurement/internal/zzau;
    //   2827: ldc_w 'Invalid event filter ID. appId, id'
    //   2830: aload_1
    //   2831: invokestatic zzbw : (Ljava/lang/String;)Ljava/lang/Object;
    //   2834: aload #35
    //   2836: getfield zzavm : Ljava/lang/Integer;
    //   2839: invokestatic valueOf : (Ljava/lang/Object;)Ljava/lang/String;
    //   2842: invokevirtual zze : (Ljava/lang/String;Ljava/lang/Object;Ljava/lang/Object;)V
    //   2845: goto -> 2251
    //   2848: aload #17
    //   2850: astore #27
    //   2852: aload #16
    //   2854: astore #28
    //   2856: aload #21
    //   2858: astore #17
    //   2860: aload #20
    //   2862: astore #16
    //   2864: aload #26
    //   2866: astore #33
    //   2868: aload #19
    //   2870: astore #29
    //   2872: aload #15
    //   2874: astore #26
    //   2876: aload #27
    //   2878: astore #15
    //   2880: aload #37
    //   2882: astore #27
    //   2884: aload #39
    //   2886: astore #20
    //   2888: aload #38
    //   2890: astore #21
    //   2892: aload #28
    //   2894: astore #19
    //   2896: goto -> 1855
    //   2899: aload #15
    //   2901: astore #28
    //   2903: aload #18
    //   2905: astore #26
    //   2907: aload #19
    //   2909: astore #15
    //   2911: aload #28
    //   2913: astore #18
    //   2915: aload #23
    //   2917: astore #19
    //   2919: aload #26
    //   2921: astore #23
    //   2923: iinc #6, 1
    //   2926: aload #23
    //   2928: astore #28
    //   2930: aload #19
    //   2932: astore #26
    //   2934: aload #27
    //   2936: astore #23
    //   2938: aload #21
    //   2940: astore #19
    //   2942: aload #16
    //   2944: astore #29
    //   2946: aload #22
    //   2948: astore #16
    //   2950: aload #18
    //   2952: astore #30
    //   2954: aload #25
    //   2956: astore #27
    //   2958: aload #23
    //   2960: astore #22
    //   2962: aload #20
    //   2964: astore #23
    //   2966: aload #16
    //   2968: astore #18
    //   2970: aload #28
    //   2972: astore #21
    //   2974: aload #15
    //   2976: astore #20
    //   2978: aload #19
    //   2980: astore #16
    //   2982: aload #30
    //   2984: astore #19
    //   2986: aload #29
    //   2988: astore #15
    //   2990: goto -> 723
    //   2993: aload #33
    //   2995: astore #15
    //   2997: aload #32
    //   2999: astore #26
    //   3001: aload #31
    //   3003: astore #17
    //   3005: aload #30
    //   3007: astore #18
    //   3009: aload #29
    //   3011: astore #27
    //   3013: aload #28
    //   3015: astore_2
    //   3016: aload #25
    //   3018: astore #22
    //   3020: aload #15
    //   3022: astore #16
    //   3024: aload #18
    //   3026: astore #19
    //   3028: aload_2
    //   3029: astore #20
    //   3031: aload #22
    //   3033: astore #23
    //   3035: aload #17
    //   3037: astore #21
    //   3039: aload_3
    //   3040: ifnull -> 4236
    //   3043: new androidx/collection/ArrayMap
    //   3046: dup
    //   3047: invokespecial <init> : ()V
    //   3050: astore #24
    //   3052: aload_3
    //   3053: arraylength
    //   3054: istore #4
    //   3056: iconst_0
    //   3057: istore #5
    //   3059: aload #34
    //   3061: astore #25
    //   3063: aload #15
    //   3065: astore #16
    //   3067: aload #18
    //   3069: astore #19
    //   3071: aload_2
    //   3072: astore #20
    //   3074: aload #22
    //   3076: astore #23
    //   3078: aload #17
    //   3080: astore #21
    //   3082: iload #5
    //   3084: iload #4
    //   3086: if_icmpge -> 4236
    //   3089: aload_3
    //   3090: iload #5
    //   3092: aaload
    //   3093: astore #32
    //   3095: aload #24
    //   3097: aload #32
    //   3099: getfield name : Ljava/lang/String;
    //   3102: invokeinterface get : (Ljava/lang/Object;)Ljava/lang/Object;
    //   3107: checkcast java/util/Map
    //   3110: astore #19
    //   3112: aload #19
    //   3114: ifnonnull -> 3168
    //   3117: aload_0
    //   3118: invokevirtual zzjt : ()Lcom/google/android/gms/measurement/internal/zzt;
    //   3121: aload_1
    //   3122: aload #32
    //   3124: getfield name : Ljava/lang/String;
    //   3127: invokevirtual zzm : (Ljava/lang/String;Ljava/lang/String;)Ljava/util/Map;
    //   3130: astore #16
    //   3132: aload #16
    //   3134: astore #19
    //   3136: aload #16
    //   3138: ifnonnull -> 3150
    //   3141: new androidx/collection/ArrayMap
    //   3144: dup
    //   3145: invokespecial <init> : ()V
    //   3148: astore #19
    //   3150: aload #24
    //   3152: aload #32
    //   3154: getfield name : Ljava/lang/String;
    //   3157: aload #19
    //   3159: invokeinterface put : (Ljava/lang/Object;Ljava/lang/Object;)Ljava/lang/Object;
    //   3164: pop
    //   3165: goto -> 3168
    //   3168: aload #19
    //   3170: invokeinterface keySet : ()Ljava/util/Set;
    //   3175: invokeinterface iterator : ()Ljava/util/Iterator;
    //   3180: astore #23
    //   3182: aload #27
    //   3184: astore #21
    //   3186: aload #26
    //   3188: astore #20
    //   3190: aload #25
    //   3192: astore #16
    //   3194: aload #23
    //   3196: invokeinterface hasNext : ()Z
    //   3201: ifeq -> 4218
    //   3204: aload #23
    //   3206: invokeinterface next : ()Ljava/lang/Object;
    //   3211: checkcast java/lang/Integer
    //   3214: invokevirtual intValue : ()I
    //   3217: istore #8
    //   3219: aload #35
    //   3221: iload #8
    //   3223: invokestatic valueOf : (I)Ljava/lang/Integer;
    //   3226: invokeinterface contains : (Ljava/lang/Object;)Z
    //   3231: ifeq -> 3254
    //   3234: aload_0
    //   3235: invokevirtual zzgt : ()Lcom/google/android/gms/measurement/internal/zzas;
    //   3238: invokevirtual zzjo : ()Lcom/google/android/gms/measurement/internal/zzau;
    //   3241: aload #16
    //   3243: iload #8
    //   3245: invokestatic valueOf : (I)Ljava/lang/Integer;
    //   3248: invokevirtual zzg : (Ljava/lang/String;Ljava/lang/Object;)V
    //   3251: goto -> 3194
    //   3254: aload #16
    //   3256: astore #25
    //   3258: aload #17
    //   3260: iload #8
    //   3262: invokestatic valueOf : (I)Ljava/lang/Integer;
    //   3265: invokeinterface get : (Ljava/lang/Object;)Ljava/lang/Object;
    //   3270: checkcast com/google/android/gms/internal/measurement/zzfr
    //   3273: astore #27
    //   3275: aload #22
    //   3277: iload #8
    //   3279: invokestatic valueOf : (I)Ljava/lang/Integer;
    //   3282: invokeinterface get : (Ljava/lang/Object;)Ljava/lang/Object;
    //   3287: checkcast java/util/BitSet
    //   3290: astore #29
    //   3292: aload_2
    //   3293: astore #30
    //   3295: aload #30
    //   3297: iload #8
    //   3299: invokestatic valueOf : (I)Ljava/lang/Integer;
    //   3302: invokeinterface get : (Ljava/lang/Object;)Ljava/lang/Object;
    //   3307: checkcast java/util/BitSet
    //   3310: astore #26
    //   3312: iload #14
    //   3314: ifeq -> 3353
    //   3317: aload #18
    //   3319: iload #8
    //   3321: invokestatic valueOf : (I)Ljava/lang/Integer;
    //   3324: invokeinterface get : (Ljava/lang/Object;)Ljava/lang/Object;
    //   3329: checkcast java/util/Map
    //   3332: astore #16
    //   3334: aload #15
    //   3336: iload #8
    //   3338: invokestatic valueOf : (I)Ljava/lang/Integer;
    //   3341: invokeinterface get : (Ljava/lang/Object;)Ljava/lang/Object;
    //   3346: checkcast java/util/Map
    //   3349: astore_2
    //   3350: goto -> 3358
    //   3353: aconst_null
    //   3354: astore_2
    //   3355: aconst_null
    //   3356: astore #16
    //   3358: aload #15
    //   3360: astore #31
    //   3362: aload #27
    //   3364: ifnonnull -> 3514
    //   3367: new com/google/android/gms/internal/measurement/zzfr
    //   3370: dup
    //   3371: invokespecial <init> : ()V
    //   3374: astore #15
    //   3376: aload #17
    //   3378: iload #8
    //   3380: invokestatic valueOf : (I)Ljava/lang/Integer;
    //   3383: aload #15
    //   3385: invokeinterface put : (Ljava/lang/Object;Ljava/lang/Object;)Ljava/lang/Object;
    //   3390: pop
    //   3391: aload #15
    //   3393: aload #21
    //   3395: putfield zzawx : Ljava/lang/Boolean;
    //   3398: new java/util/BitSet
    //   3401: dup
    //   3402: invokespecial <init> : ()V
    //   3405: astore #29
    //   3407: aload #22
    //   3409: iload #8
    //   3411: invokestatic valueOf : (I)Ljava/lang/Integer;
    //   3414: aload #29
    //   3416: invokeinterface put : (Ljava/lang/Object;Ljava/lang/Object;)Ljava/lang/Object;
    //   3421: pop
    //   3422: new java/util/BitSet
    //   3425: dup
    //   3426: invokespecial <init> : ()V
    //   3429: astore #26
    //   3431: aload #30
    //   3433: iload #8
    //   3435: invokestatic valueOf : (I)Ljava/lang/Integer;
    //   3438: aload #26
    //   3440: invokeinterface put : (Ljava/lang/Object;Ljava/lang/Object;)Ljava/lang/Object;
    //   3445: pop
    //   3446: iload #14
    //   3448: ifeq -> 3500
    //   3451: new androidx/collection/ArrayMap
    //   3454: dup
    //   3455: invokespecial <init> : ()V
    //   3458: astore #15
    //   3460: aload #18
    //   3462: iload #8
    //   3464: invokestatic valueOf : (I)Ljava/lang/Integer;
    //   3467: aload #15
    //   3469: invokeinterface put : (Ljava/lang/Object;Ljava/lang/Object;)Ljava/lang/Object;
    //   3474: pop
    //   3475: new androidx/collection/ArrayMap
    //   3478: dup
    //   3479: invokespecial <init> : ()V
    //   3482: astore_2
    //   3483: aload #31
    //   3485: iload #8
    //   3487: invokestatic valueOf : (I)Ljava/lang/Integer;
    //   3490: aload_2
    //   3491: invokeinterface put : (Ljava/lang/Object;Ljava/lang/Object;)Ljava/lang/Object;
    //   3496: pop
    //   3497: goto -> 3504
    //   3500: aload #16
    //   3502: astore #15
    //   3504: aload #15
    //   3506: astore #28
    //   3508: aload_2
    //   3509: astore #27
    //   3511: goto -> 3521
    //   3514: aload_2
    //   3515: astore #27
    //   3517: aload #16
    //   3519: astore #28
    //   3521: aload #19
    //   3523: iload #8
    //   3525: invokestatic valueOf : (I)Ljava/lang/Integer;
    //   3528: invokeinterface get : (Ljava/lang/Object;)Ljava/lang/Object;
    //   3533: checkcast java/util/List
    //   3536: invokeinterface iterator : ()Ljava/util/Iterator;
    //   3541: astore_2
    //   3542: aload #25
    //   3544: astore #16
    //   3546: aload_2
    //   3547: astore #25
    //   3549: aload #31
    //   3551: astore #15
    //   3553: aload #30
    //   3555: astore_2
    //   3556: aload #25
    //   3558: invokeinterface hasNext : ()Z
    //   3563: ifeq -> 4215
    //   3566: aload #25
    //   3568: invokeinterface next : ()Ljava/lang/Object;
    //   3573: checkcast com/google/android/gms/internal/measurement/zzfm
    //   3576: astore #33
    //   3578: aload_0
    //   3579: invokevirtual zzgt : ()Lcom/google/android/gms/measurement/internal/zzas;
    //   3582: astore #30
    //   3584: aload #30
    //   3586: iconst_2
    //   3587: invokevirtual isLoggable : (I)Z
    //   3590: ifeq -> 3652
    //   3593: aload_0
    //   3594: invokevirtual zzgt : ()Lcom/google/android/gms/measurement/internal/zzas;
    //   3597: invokevirtual zzjo : ()Lcom/google/android/gms/measurement/internal/zzau;
    //   3600: ldc_w 'Evaluating filter. audience, filter, property'
    //   3603: iload #8
    //   3605: invokestatic valueOf : (I)Ljava/lang/Integer;
    //   3608: aload #33
    //   3610: getfield zzavm : Ljava/lang/Integer;
    //   3613: aload_0
    //   3614: invokevirtual zzgq : ()Lcom/google/android/gms/measurement/internal/zzaq;
    //   3617: aload #33
    //   3619: getfield zzawc : Ljava/lang/String;
    //   3622: invokevirtual zzbv : (Ljava/lang/String;)Ljava/lang/String;
    //   3625: invokevirtual zzd : (Ljava/lang/String;Ljava/lang/Object;Ljava/lang/Object;Ljava/lang/Object;)V
    //   3628: aload_0
    //   3629: invokevirtual zzgt : ()Lcom/google/android/gms/measurement/internal/zzas;
    //   3632: invokevirtual zzjo : ()Lcom/google/android/gms/measurement/internal/zzau;
    //   3635: aload #20
    //   3637: aload_0
    //   3638: invokevirtual zzjr : ()Lcom/google/android/gms/measurement/internal/zzft;
    //   3641: aload #33
    //   3643: invokevirtual zza : (Lcom/google/android/gms/internal/measurement/zzfm;)Ljava/lang/String;
    //   3646: invokevirtual zzg : (Ljava/lang/String;Ljava/lang/Object;)V
    //   3649: goto -> 3652
    //   3652: aload #33
    //   3654: getfield zzavm : Ljava/lang/Integer;
    //   3657: astore #30
    //   3659: aload #30
    //   3661: ifnull -> 4174
    //   3664: aload #30
    //   3666: invokevirtual intValue : ()I
    //   3669: sipush #256
    //   3672: if_icmple -> 3678
    //   3675: goto -> 4174
    //   3678: iload #14
    //   3680: ifeq -> 4008
    //   3683: aload #33
    //   3685: ifnull -> 3714
    //   3688: aload #33
    //   3690: getfield zzavj : Ljava/lang/Boolean;
    //   3693: astore #30
    //   3695: aload #30
    //   3697: ifnull -> 3714
    //   3700: aload #30
    //   3702: invokevirtual booleanValue : ()Z
    //   3705: ifeq -> 3714
    //   3708: iconst_1
    //   3709: istore #6
    //   3711: goto -> 3717
    //   3714: iconst_0
    //   3715: istore #6
    //   3717: aload #33
    //   3719: ifnull -> 3748
    //   3722: aload #33
    //   3724: getfield zzavk : Ljava/lang/Boolean;
    //   3727: astore #30
    //   3729: aload #30
    //   3731: ifnull -> 3748
    //   3734: aload #30
    //   3736: invokevirtual booleanValue : ()Z
    //   3739: ifeq -> 3748
    //   3742: iconst_1
    //   3743: istore #7
    //   3745: goto -> 3751
    //   3748: iconst_0
    //   3749: istore #7
    //   3751: aload #29
    //   3753: aload #33
    //   3755: getfield zzavm : Ljava/lang/Integer;
    //   3758: invokevirtual intValue : ()I
    //   3761: invokevirtual get : (I)Z
    //   3764: ifeq -> 3803
    //   3767: iload #6
    //   3769: ifne -> 3803
    //   3772: iload #7
    //   3774: ifne -> 3803
    //   3777: aload_0
    //   3778: invokevirtual zzgt : ()Lcom/google/android/gms/measurement/internal/zzas;
    //   3781: invokevirtual zzjo : ()Lcom/google/android/gms/measurement/internal/zzau;
    //   3784: ldc_w 'Property filter already evaluated true and it is not associated with a dynamic audience. audience ID, filter ID'
    //   3787: iload #8
    //   3789: invokestatic valueOf : (I)Ljava/lang/Integer;
    //   3792: aload #33
    //   3794: getfield zzavm : Ljava/lang/Integer;
    //   3797: invokevirtual zze : (Ljava/lang/String;Ljava/lang/Object;Ljava/lang/Object;)V
    //   3800: goto -> 3556
    //   3803: aload_0
    //   3804: aload #33
    //   3806: aload #32
    //   3808: invokespecial zza : (Lcom/google/android/gms/internal/measurement/zzfm;Lcom/google/android/gms/internal/measurement/zzfz;)Ljava/lang/Boolean;
    //   3811: astore #31
    //   3813: aload_0
    //   3814: invokevirtual zzgt : ()Lcom/google/android/gms/measurement/internal/zzas;
    //   3817: astore #30
    //   3819: aload #30
    //   3821: invokevirtual zzjo : ()Lcom/google/android/gms/measurement/internal/zzau;
    //   3824: astore #34
    //   3826: aload #31
    //   3828: ifnonnull -> 3839
    //   3831: ldc_w 'null'
    //   3834: astore #30
    //   3836: goto -> 3843
    //   3839: aload #31
    //   3841: astore #30
    //   3843: aload #34
    //   3845: ldc_w 'Property filter result'
    //   3848: aload #30
    //   3850: invokevirtual zzg : (Ljava/lang/String;Ljava/lang/Object;)V
    //   3853: aload #31
    //   3855: ifnonnull -> 3878
    //   3858: aload #35
    //   3860: iload #8
    //   3862: invokestatic valueOf : (I)Ljava/lang/Integer;
    //   3865: invokeinterface add : (Ljava/lang/Object;)Z
    //   3870: pop
    //   3871: aload #18
    //   3873: astore #30
    //   3875: goto -> 4051
    //   3878: aload #26
    //   3880: aload #33
    //   3882: getfield zzavm : Ljava/lang/Integer;
    //   3885: invokevirtual intValue : ()I
    //   3888: invokevirtual set : (I)V
    //   3891: aload #29
    //   3893: aload #33
    //   3895: getfield zzavm : Ljava/lang/Integer;
    //   3898: invokevirtual intValue : ()I
    //   3901: aload #31
    //   3903: invokevirtual booleanValue : ()Z
    //   3906: invokevirtual set : (IZ)V
    //   3909: aload #18
    //   3911: astore #30
    //   3913: aload #31
    //   3915: invokevirtual booleanValue : ()Z
    //   3918: ifeq -> 4051
    //   3921: iload #6
    //   3923: ifne -> 3935
    //   3926: aload #18
    //   3928: astore #30
    //   3930: iload #7
    //   3932: ifeq -> 4051
    //   3935: aload #18
    //   3937: astore #30
    //   3939: aload #32
    //   3941: getfield zzayw : Ljava/lang/Long;
    //   3944: ifnull -> 4051
    //   3947: iload #7
    //   3949: ifeq -> 3980
    //   3952: aload #27
    //   3954: aload #33
    //   3956: getfield zzavm : Ljava/lang/Integer;
    //   3959: invokevirtual intValue : ()I
    //   3962: aload #32
    //   3964: getfield zzayw : Ljava/lang/Long;
    //   3967: invokevirtual longValue : ()J
    //   3970: invokestatic zzb : (Ljava/util/Map;IJ)V
    //   3973: aload #18
    //   3975: astore #30
    //   3977: goto -> 4051
    //   3980: aload #28
    //   3982: aload #33
    //   3984: getfield zzavm : Ljava/lang/Integer;
    //   3987: invokevirtual intValue : ()I
    //   3990: aload #32
    //   3992: getfield zzayw : Ljava/lang/Long;
    //   3995: invokevirtual longValue : ()J
    //   3998: invokestatic zza : (Ljava/util/Map;IJ)V
    //   4001: aload #18
    //   4003: astore #30
    //   4005: goto -> 4051
    //   4008: aload #29
    //   4010: aload #33
    //   4012: getfield zzavm : Ljava/lang/Integer;
    //   4015: invokevirtual intValue : ()I
    //   4018: invokevirtual get : (I)Z
    //   4021: ifeq -> 4058
    //   4024: aload_0
    //   4025: invokevirtual zzgt : ()Lcom/google/android/gms/measurement/internal/zzas;
    //   4028: invokevirtual zzjo : ()Lcom/google/android/gms/measurement/internal/zzau;
    //   4031: ldc_w 'Property filter already evaluated true. audience ID, filter ID'
    //   4034: iload #8
    //   4036: invokestatic valueOf : (I)Ljava/lang/Integer;
    //   4039: aload #33
    //   4041: getfield zzavm : Ljava/lang/Integer;
    //   4044: invokevirtual zze : (Ljava/lang/String;Ljava/lang/Object;Ljava/lang/Object;)V
    //   4047: aload #18
    //   4049: astore #30
    //   4051: aload #30
    //   4053: astore #18
    //   4055: goto -> 3556
    //   4058: aload_0
    //   4059: aload #33
    //   4061: aload #32
    //   4063: invokespecial zza : (Lcom/google/android/gms/internal/measurement/zzfm;Lcom/google/android/gms/internal/measurement/zzfz;)Ljava/lang/Boolean;
    //   4066: astore #31
    //   4068: aload_0
    //   4069: invokevirtual zzgt : ()Lcom/google/android/gms/measurement/internal/zzas;
    //   4072: invokevirtual zzjo : ()Lcom/google/android/gms/measurement/internal/zzau;
    //   4075: astore #34
    //   4077: aload #31
    //   4079: ifnonnull -> 4090
    //   4082: ldc_w 'null'
    //   4085: astore #30
    //   4087: goto -> 4094
    //   4090: aload #31
    //   4092: astore #30
    //   4094: aload #34
    //   4096: ldc_w 'Property filter result'
    //   4099: aload #30
    //   4101: invokevirtual zzg : (Ljava/lang/String;Ljava/lang/Object;)V
    //   4104: aload #31
    //   4106: ifnonnull -> 4129
    //   4109: aload #35
    //   4111: iload #8
    //   4113: invokestatic valueOf : (I)Ljava/lang/Integer;
    //   4116: invokeinterface add : (Ljava/lang/Object;)Z
    //   4121: pop
    //   4122: aload #18
    //   4124: astore #30
    //   4126: goto -> 4051
    //   4129: aload #26
    //   4131: aload #33
    //   4133: getfield zzavm : Ljava/lang/Integer;
    //   4136: invokevirtual intValue : ()I
    //   4139: invokevirtual set : (I)V
    //   4142: aload #18
    //   4144: astore #30
    //   4146: aload #31
    //   4148: invokevirtual booleanValue : ()Z
    //   4151: ifeq -> 4051
    //   4154: aload #29
    //   4156: aload #33
    //   4158: getfield zzavm : Ljava/lang/Integer;
    //   4161: invokevirtual intValue : ()I
    //   4164: invokevirtual set : (I)V
    //   4167: aload #18
    //   4169: astore #30
    //   4171: goto -> 4051
    //   4174: aload_0
    //   4175: invokevirtual zzgt : ()Lcom/google/android/gms/measurement/internal/zzas;
    //   4178: invokevirtual zzjj : ()Lcom/google/android/gms/measurement/internal/zzau;
    //   4181: ldc_w 'Invalid property filter ID. appId, id'
    //   4184: aload_1
    //   4185: invokestatic zzbw : (Ljava/lang/String;)Ljava/lang/Object;
    //   4188: aload #33
    //   4190: getfield zzavm : Ljava/lang/Integer;
    //   4193: invokestatic valueOf : (Ljava/lang/Object;)Ljava/lang/String;
    //   4196: invokevirtual zze : (Ljava/lang/String;Ljava/lang/Object;Ljava/lang/Object;)V
    //   4199: aload #35
    //   4201: iload #8
    //   4203: invokestatic valueOf : (I)Ljava/lang/Integer;
    //   4206: invokeinterface add : (Ljava/lang/Object;)Z
    //   4211: pop
    //   4212: goto -> 3194
    //   4215: goto -> 3194
    //   4218: iinc #5, 1
    //   4221: aload #16
    //   4223: astore #25
    //   4225: aload #20
    //   4227: astore #26
    //   4229: aload #21
    //   4231: astore #27
    //   4233: goto -> 3063
    //   4236: aload #21
    //   4238: astore_3
    //   4239: aload #23
    //   4241: invokeinterface size : ()I
    //   4246: anewarray com/google/android/gms/internal/measurement/zzfr
    //   4249: astore #18
    //   4251: aload #23
    //   4253: invokeinterface keySet : ()Ljava/util/Set;
    //   4258: invokeinterface iterator : ()Ljava/util/Iterator;
    //   4263: astore_2
    //   4264: iconst_0
    //   4265: istore #4
    //   4267: aload_2
    //   4268: invokeinterface hasNext : ()Z
    //   4273: ifeq -> 4894
    //   4276: aload_2
    //   4277: invokeinterface next : ()Ljava/lang/Object;
    //   4282: checkcast java/lang/Integer
    //   4285: invokevirtual intValue : ()I
    //   4288: istore #7
    //   4290: aload #35
    //   4292: iload #7
    //   4294: invokestatic valueOf : (I)Ljava/lang/Integer;
    //   4297: invokeinterface contains : (Ljava/lang/Object;)Z
    //   4302: ifne -> 4891
    //   4305: aload_3
    //   4306: iload #7
    //   4308: invokestatic valueOf : (I)Ljava/lang/Integer;
    //   4311: invokeinterface get : (Ljava/lang/Object;)Ljava/lang/Object;
    //   4316: checkcast com/google/android/gms/internal/measurement/zzfr
    //   4319: astore #17
    //   4321: aload #17
    //   4323: astore #15
    //   4325: aload #17
    //   4327: ifnonnull -> 4339
    //   4330: new com/google/android/gms/internal/measurement/zzfr
    //   4333: dup
    //   4334: invokespecial <init> : ()V
    //   4337: astore #15
    //   4339: aload #18
    //   4341: iload #4
    //   4343: aload #15
    //   4345: aastore
    //   4346: aload #15
    //   4348: iload #7
    //   4350: invokestatic valueOf : (I)Ljava/lang/Integer;
    //   4353: putfield zzavg : Ljava/lang/Integer;
    //   4356: aload #15
    //   4358: new com/google/android/gms/internal/measurement/zzfx
    //   4361: dup
    //   4362: invokespecial <init> : ()V
    //   4365: putfield zzawv : Lcom/google/android/gms/internal/measurement/zzfx;
    //   4368: aload #15
    //   4370: getfield zzawv : Lcom/google/android/gms/internal/measurement/zzfx;
    //   4373: aload #23
    //   4375: iload #7
    //   4377: invokestatic valueOf : (I)Ljava/lang/Integer;
    //   4380: invokeinterface get : (Ljava/lang/Object;)Ljava/lang/Object;
    //   4385: checkcast java/util/BitSet
    //   4388: invokestatic zza : (Ljava/util/BitSet;)[J
    //   4391: putfield zzayq : [J
    //   4394: aload #15
    //   4396: getfield zzawv : Lcom/google/android/gms/internal/measurement/zzfx;
    //   4399: aload #20
    //   4401: iload #7
    //   4403: invokestatic valueOf : (I)Ljava/lang/Integer;
    //   4406: invokeinterface get : (Ljava/lang/Object;)Ljava/lang/Object;
    //   4411: checkcast java/util/BitSet
    //   4414: invokestatic zza : (Ljava/util/BitSet;)[J
    //   4417: putfield zzayp : [J
    //   4420: iload #14
    //   4422: ifeq -> 4670
    //   4425: aload #15
    //   4427: getfield zzawv : Lcom/google/android/gms/internal/measurement/zzfx;
    //   4430: aload #19
    //   4432: iload #7
    //   4434: invokestatic valueOf : (I)Ljava/lang/Integer;
    //   4437: invokeinterface get : (Ljava/lang/Object;)Ljava/lang/Object;
    //   4442: checkcast java/util/Map
    //   4445: invokestatic zzb : (Ljava/util/Map;)[Lcom/google/android/gms/internal/measurement/zzfs;
    //   4448: putfield zzayr : [Lcom/google/android/gms/internal/measurement/zzfs;
    //   4451: aload #15
    //   4453: getfield zzawv : Lcom/google/android/gms/internal/measurement/zzfx;
    //   4456: astore #21
    //   4458: aload #16
    //   4460: iload #7
    //   4462: invokestatic valueOf : (I)Ljava/lang/Integer;
    //   4465: invokeinterface get : (Ljava/lang/Object;)Ljava/lang/Object;
    //   4470: checkcast java/util/Map
    //   4473: astore #22
    //   4475: aload #22
    //   4477: ifnonnull -> 4489
    //   4480: iconst_0
    //   4481: anewarray com/google/android/gms/internal/measurement/zzfy
    //   4484: astore #17
    //   4486: goto -> 4660
    //   4489: aload #22
    //   4491: invokeinterface size : ()I
    //   4496: anewarray com/google/android/gms/internal/measurement/zzfy
    //   4499: astore #17
    //   4501: aload #22
    //   4503: invokeinterface keySet : ()Ljava/util/Set;
    //   4508: invokeinterface iterator : ()Ljava/util/Iterator;
    //   4513: astore #24
    //   4515: iconst_0
    //   4516: istore #5
    //   4518: aload #24
    //   4520: invokeinterface hasNext : ()Z
    //   4525: ifeq -> 4660
    //   4528: aload #24
    //   4530: invokeinterface next : ()Ljava/lang/Object;
    //   4535: checkcast java/lang/Integer
    //   4538: astore #26
    //   4540: new com/google/android/gms/internal/measurement/zzfy
    //   4543: dup
    //   4544: invokespecial <init> : ()V
    //   4547: astore #25
    //   4549: aload #25
    //   4551: aload #26
    //   4553: putfield zzawz : Ljava/lang/Integer;
    //   4556: aload #22
    //   4558: aload #26
    //   4560: invokeinterface get : (Ljava/lang/Object;)Ljava/lang/Object;
    //   4565: checkcast java/util/List
    //   4568: astore #27
    //   4570: aload #27
    //   4572: ifnull -> 4647
    //   4575: aload #27
    //   4577: invokestatic sort : (Ljava/util/List;)V
    //   4580: aload #27
    //   4582: invokeinterface size : ()I
    //   4587: newarray long
    //   4589: astore #26
    //   4591: aload #27
    //   4593: invokeinterface iterator : ()Ljava/util/Iterator;
    //   4598: astore #27
    //   4600: iconst_0
    //   4601: istore #6
    //   4603: aload #27
    //   4605: invokeinterface hasNext : ()Z
    //   4610: ifeq -> 4637
    //   4613: aload #26
    //   4615: iload #6
    //   4617: aload #27
    //   4619: invokeinterface next : ()Ljava/lang/Object;
    //   4624: checkcast java/lang/Long
    //   4627: invokevirtual longValue : ()J
    //   4630: lastore
    //   4631: iinc #6, 1
    //   4634: goto -> 4603
    //   4637: aload #25
    //   4639: aload #26
    //   4641: putfield zzayu : [J
    //   4644: goto -> 4647
    //   4647: aload #17
    //   4649: iload #5
    //   4651: aload #25
    //   4653: aastore
    //   4654: iinc #5, 1
    //   4657: goto -> 4518
    //   4660: aload #21
    //   4662: aload #17
    //   4664: putfield zzays : [Lcom/google/android/gms/internal/measurement/zzfy;
    //   4667: goto -> 4670
    //   4670: aload_0
    //   4671: invokevirtual zzjt : ()Lcom/google/android/gms/measurement/internal/zzt;
    //   4674: astore #17
    //   4676: aload #15
    //   4678: getfield zzawv : Lcom/google/android/gms/internal/measurement/zzfx;
    //   4681: astore #22
    //   4683: aload #17
    //   4685: invokevirtual zzcl : ()V
    //   4688: aload #17
    //   4690: invokevirtual zzaf : ()V
    //   4693: aload_1
    //   4694: invokestatic checkNotEmpty : (Ljava/lang/String;)Ljava/lang/String;
    //   4697: pop
    //   4698: aload #22
    //   4700: invokestatic checkNotNull : (Ljava/lang/Object;)Ljava/lang/Object;
    //   4703: pop
    //   4704: aload #22
    //   4706: invokevirtual zzvx : ()I
    //   4709: newarray byte
    //   4711: astore #15
    //   4713: aload #15
    //   4715: arraylength
    //   4716: istore #5
    //   4718: aload #15
    //   4720: iconst_0
    //   4721: iload #5
    //   4723: invokestatic zzk : ([BII)Lcom/google/android/gms/internal/measurement/zzya;
    //   4726: astore #21
    //   4728: aload #22
    //   4730: aload #21
    //   4732: invokevirtual zza : (Lcom/google/android/gms/internal/measurement/zzya;)V
    //   4735: aload #21
    //   4737: invokevirtual zzza : ()V
    //   4740: new android/content/ContentValues
    //   4743: dup
    //   4744: invokespecial <init> : ()V
    //   4747: astore #21
    //   4749: aload #21
    //   4751: ldc_w 'app_id'
    //   4754: aload_1
    //   4755: invokevirtual put : (Ljava/lang/String;Ljava/lang/String;)V
    //   4758: aload #21
    //   4760: ldc_w 'audience_id'
    //   4763: iload #7
    //   4765: invokestatic valueOf : (I)Ljava/lang/Integer;
    //   4768: invokevirtual put : (Ljava/lang/String;Ljava/lang/Integer;)V
    //   4771: aload #21
    //   4773: ldc_w 'current_results'
    //   4776: aload #15
    //   4778: invokevirtual put : (Ljava/lang/String;[B)V
    //   4781: aload #17
    //   4783: invokevirtual getWritableDatabase : ()Landroid/database/sqlite/SQLiteDatabase;
    //   4786: astore #15
    //   4788: aload #15
    //   4790: ldc_w 'audience_filter_values'
    //   4793: aconst_null
    //   4794: aload #21
    //   4796: iconst_5
    //   4797: invokevirtual insertWithOnConflict : (Ljava/lang/String;Ljava/lang/String;Landroid/content/ContentValues;I)J
    //   4800: ldc2_w -1
    //   4803: lcmp
    //   4804: ifne -> 4885
    //   4807: aload #17
    //   4809: invokevirtual zzgt : ()Lcom/google/android/gms/measurement/internal/zzas;
    //   4812: invokevirtual zzjg : ()Lcom/google/android/gms/measurement/internal/zzau;
    //   4815: ldc_w 'Failed to insert filter results (got -1). appId'
    //   4818: aload_1
    //   4819: invokestatic zzbw : (Ljava/lang/String;)Ljava/lang/Object;
    //   4822: invokevirtual zzg : (Ljava/lang/String;Ljava/lang/Object;)V
    //   4825: goto -> 4885
    //   4828: astore #15
    //   4830: goto -> 4835
    //   4833: astore #15
    //   4835: aload #17
    //   4837: invokevirtual zzgt : ()Lcom/google/android/gms/measurement/internal/zzas;
    //   4840: invokevirtual zzjg : ()Lcom/google/android/gms/measurement/internal/zzau;
    //   4843: ldc_w 'Error storing filter results. appId'
    //   4846: aload_1
    //   4847: invokestatic zzbw : (Ljava/lang/String;)Ljava/lang/Object;
    //   4850: aload #15
    //   4852: invokevirtual zze : (Ljava/lang/String;Ljava/lang/Object;Ljava/lang/Object;)V
    //   4855: goto -> 4885
    //   4858: astore #15
    //   4860: goto -> 4865
    //   4863: astore #15
    //   4865: aload #17
    //   4867: invokevirtual zzgt : ()Lcom/google/android/gms/measurement/internal/zzas;
    //   4870: invokevirtual zzjg : ()Lcom/google/android/gms/measurement/internal/zzau;
    //   4873: ldc_w 'Configuration loss. Failed to serialize filter results. appId'
    //   4876: aload_1
    //   4877: invokestatic zzbw : (Ljava/lang/String;)Ljava/lang/Object;
    //   4880: aload #15
    //   4882: invokevirtual zze : (Ljava/lang/String;Ljava/lang/Object;Ljava/lang/Object;)V
    //   4885: iinc #4, 1
    //   4888: goto -> 4267
    //   4891: goto -> 4267
    //   4894: aload #18
    //   4896: iload #4
    //   4898: invokestatic copyOf : ([Ljava/lang/Object;I)[Ljava/lang/Object;
    //   4901: checkcast [Lcom/google/android/gms/internal/measurement/zzfr;
    //   4904: areturn
    // Exception table:
    //   from	to	target	type
    //   1064	1071	1095	android/database/sqlite/SQLiteException
    //   1071	1087	1090	android/database/sqlite/SQLiteException
    //   4704	4718	4863	java/io/IOException
    //   4718	4740	4858	java/io/IOException
    //   4781	4788	4833	android/database/sqlite/SQLiteException
    //   4788	4825	4828	android/database/sqlite/SQLiteException
  }
  
  protected final boolean zzgy() {
    return false;
  }
}


/* Location:              /home/andrelcol/Desktop/securityDebt/onstar/meuProjeto.jar!/com/google/android/gms/measurement/internal/zzm.class
 * Java compiler version: 6 (50.0)
 * JD-Core Version:       1.1.3
 */